Workbook
Name _MailOriginal: 'Analytics to Publish'!$A$8
Name Home_edge: OffDef25!$G$1
Name mean: OffDef25!$G$2

Sheet OffDef25
F1: Home edge | G1: 3.6631115 | S1: Rankings History | U1: (After Week X)
F2: mean | G2: 22.775368 | T2: Preseason | U2: Week1 | V2: Week2 | W2: Week3 | X2: Week4 | Y2: Week5 | Z2: Week6 | AA2: Week7 | AB2: Week8 | AC2: Week9 | AD2: Week10 | AE2: Week11 | AF2: Week12 | AG2: Week13 | AH2: Week14 | AI2: Week15 | AJ2: Week16 | AK2: Week17 | AL2: Week18
B3: mean | D3: off_mean: | E3: =AVERAGE(E5:E14) -> -5.2693514e-08 | F3: def_mean: | G3: =AVERAGE(G5:G14) -> 1.7866242e-07 | P3: SSE | S3: ARC | T3: 11 | U3: 8 | V3: 11 | W3: 11 | X3: 11 | Y3: 11 | Z3: 11 | AA3: 11 | AB3: 11 | AC3: 11 | AD3: 11 | AE3: 11 | AF3: 11 | AG3: 11 | AH3: 11 | AI3: 11 | AJ3: 11 | AK3: 11
B4: Team | C4: Overall | D4: Offense Rank | E4: Offense | F4: Defense Rank | G4: Defense | P4: =SUM(P6:P277) -> 18273.42 | S4: CHI | T4: 4 | U4: 4 | V4: 2 | W4: 3 | X4: 4 | Y4: 4 | Z4: 4 | AA4: 3 | AB4: 3 | AC4: 2 | AD4: 3 | AE4: 4 | AF4: 3 | AG4: 4 | AH4: 4 | AI4: 4 | AJ4: 4 | AK4: 4
A5: 1 | B5: UTAH | C5: =E5-G5 -> 3.4176488 | D5: =RANK(E5,$E$5:$E$15,0) -> 1 | E5: 4.8535337 | F5: =RANK(G5,$G$5:$G$15,1) -> 6 | G5: 1.435885 | I5: Rnd | J5: Home Team | K5: Away Team | L5: Home Points | M5: Away Points | N5: Home Prediction | O5: Away Prediction | P5: Squared Error | S5: HOU | T5: 1 | U5: 7 | V5: 3 | W5: 5 | X5: 1 | Y5: 2 | Z5: 3 | AA5: 2 | AB5: 2 | AC5: 4 | AD5: 4 | AE5: 3 | AF5: 4 | AG5: 3 | AH5: 1 | AI5: 1 | AJ5: 3 | AK5: 2
A6: 2 | B6: HOU | C6: =E6-G6 -> 4.6010256 | D6: =RANK(E6,$E$5:$E$15,0) -> 4 | E6: 0.094130043 | F6: =RANK(G6,$G$5:$G$15,1) -> 2 | G6: -4.5068956 | I6: 1 | J6: MIA | K6: OGDC | L6: 29 | M6: 31 | N6: =IFERROR(mean+0.5*Home_edge+VLOOKUP(J6,$B$5:$G$15,4,FALSE)+VLOOKUP(K6,$B$5:$G$15,6,FALSE),"") -> 23.177632 | O6: =IFERROR(mean-0.5*Home_edge+VLOOKUP(K6,$B$5:$G$15,4,FALSE)+VLOOKUP(J6,$B$5:$G$15,6,FALSE),"") -> 21.340442 | P6: =IFERROR((N6-L6)^2+(O6-M6)^2,"") -> 127.20704 | S6: MIA | T6: 9 | U6: 6 | V6: 9 | W6: 8 | X6: 9 | Y6: 8 | Z6: 8 | AA6: 10 | AB6: 10 | AC6: 10 | AD6: 10 | AE6: 10 | AF6: 10 | AG6: 10 | AH6: 10 | AI6: 10 | AJ6: 9 | AK6: 10
A7: 3 | B7: NEFJ | C7: =E7-G7 -> 3.7860479 | D7: =RANK(E7,$E$5:$E$15,0) -> 7 | E7: -1.2736361 | F7: =RANK(G7,$G$5:$G$15,1) -> 1 | G7: -5.059684 | I7: 1 | J7: NOLA | K7: ARC | L7: 35 | M7: 14 | N7: =IFERROR(mean+0.5*Home_edge+VLOOKUP(J7,$B$5:$G$15,4,FALSE)+VLOOKUP(K7,$B$5:$G$15,6,FALSE),"") -> 36.040003 | O7: =IFERROR(mean-0.5*Home_edge+VLOOKUP(K7,$B$5:$G$15,4,FALSE)+VLOOKUP(J7,$B$5:$G$15,6,FALSE),"") -> 19.600699 | P7: =IFERROR((N7-L7)^2+(O7-M7)^2,"") -> 32.449434 | S7: NEFJ | T7: 3 | U7: 3 | V7: 5 | W7: 9 | X7: 7 | Y7: 9 | Z7: 9 | AA7: 5 | AB7: 5 | AC7: 3 | AD7: 2 | AE7: 2 | AF7: 2 | AG7: 1 | AH7: 2 | AI7: 3 | AJ7: 1 | AK7: 3
A8: 4 | B8: CHI | C8: =E8-G8 -> 2.2108853 | D8: =RANK(E8,$E$5:$E$15,0) -> 9 | E8: -1.964961 | F8: =RANK(G8,$G$5:$G$15,1) -> 3 | G8: -4.1758463 | I8: 1 | J8: HOU | K8: CHI | L8: 22 | M8: 25 | N8: =IFERROR(mean+0.5*Home_edge+VLOOKUP(J8,$B$5:$G$15,4,FALSE)+VLOOKUP(K8,$B$5:$G$15,6,FALSE),"") -> 20.525207 | O8: =IFERROR(mean-0.5*Home_edge+VLOOKUP(K8,$B$5:$G$15,4,FALSE)+VLOOKUP(J8,$B$5:$G$15,6,FALSE),"") -> 14.471955 | P8: =IFERROR((N8-L8)^2+(O8-M8)^2,"") -> 113.01474 | S8: NOLA | T8: 6 | U8: 1 | V8: 10 | W8: 7 | X8: 10 | Y8: 10 | Z8: 10 | AA8: 9 | AB8: 9 | AC8: 7 | AD8: 6 | AE8: 6 | AF8: 8 | AG8: 8 | AH8: 9 | AI8: 9 | AJ8: 10 | AK8: 9
A9: 5 | B9: SDL | C9: =E9-G9 -> 1.9052168 | D9: =RANK(E9,$E$5:$E$15,0) -> 3 | E9: 2.1899097 | F9: =RANK(G9,$G$5:$G$15,1) -> 5 | G9: 0.28469286 | I9: 1 | J9: SDL | K9: SEA | L9: 40 | M9: 26 | N9: =IFERROR(mean+0.5*Home_edge+VLOOKUP(J9,$B$5:$G$15,4,FALSE)+VLOOKUP(K9,$B$5:$G$15,6,FALSE),"") -> 25.99475 | O9: =IFERROR(mean-0.5*Home_edge+VLOOKUP(K9,$B$5:$G$15,4,FALSE)+VLOOKUP(J9,$B$5:$G$15,6,FALSE),"") -> 21.247827 | P9: =IFERROR((N9-L9)^2+(O9-M9)^2,"") -> 218.73018 | S9: OGDC | T9: 8 | U9: 5 | V9: 8 | W9: 6 | X9: 8 | Y9: 7 | Z9: 6 | AA9: 7 | AB9: 7 | AC9: 9 | AD9: 9 | AE9: 9 | AF9: 9 | AG9: 9 | AH9: 8 | AI9: 8 | AJ9: 8 | AK9: 8
A10: 6 | B10: SEA | C10: =E10-G10 -> 0.82140534 | D10: =RANK(E10,$E$5:$E$15,0) -> 5 | E10: 0.019322014 | F10: =RANK(G10,$G$5:$G$15,1) -> 4 | G10: -0.80208333 | I10: 1 | J10: RFCLA | K10: NEFJ | L10: 17 | M10: 24 | N10: =IFERROR(mean+0.5*Home_edge+VLOOKUP(J10,$B$5:$G$15,4,FALSE)+VLOOKUP(K10,$B$5:$G$15,6,FALSE),"") -> 23.39348 | O10: =IFERROR(mean-0.5*Home_edge+VLOOKUP(K10,$B$5:$G$15,4,FALSE)+VLOOKUP(J10,$B$5:$G$15,6,FALSE),"") -> 24.036738 | P10: =IFERROR((N10-L10)^2+(O10-M10)^2,"") -> 40.877935 | Q10: Home Team Offense Favorability | R10: Away Team Offense Favorability | S10: RFCLA | T10: 10 | U10: 9 | V10: 6 | W10: 10 | X10: 6 | Y10: 5 | Z10: 7 | AA10: 6 | AB10: 6 | AC10: 6 | AD10: 7 | AE10: 7 | AF10: 6 | AG10: 7 | AH10: 6 | AI10: 7 | AJ10: 5 | AK10: 7
A11: 7 | B11: RFCLA | C11: =E11-G11 -> -0.5203218 | D11: =RANK(E11,$E$5:$E$15,0) -> 2 | E11: 3.8462405 | F11: =RANK(G11,$G$5:$G$15,1) -> 10 | G11: 4.3665623 | I11: 2 | J11: ARC | K11: SDL | L11: 5 | M11: 52 | N11: =IFERROR(mean+0.5*Home_edge+VLOOKUP(J11,$B$5:$G$15,4,FALSE)+VLOOKUP(K11,$B$5:$G$15,6,FALSE),"") -> 20.034377 | O11: =IFERROR(mean-0.5*Home_edge+VLOOKUP(K11,$B$5:$G$15,4,FALSE)+VLOOKUP(J11,$B$5:$G$15,6,FALSE),"") -> 36.355433 | P11: =IFERROR((N11-L11)^2+(O11-M11)^2,"") -> 470.78497 | Q11: =VLOOKUP($J11,$B$5:$G$15,4, FALSE)+VLOOKUP($K11,$B$5:$G$15,6, FALSE) -> -4.5725462 | R11: =VLOOKUP($K11,$B$5:$G$15,4, FALSE)+VLOOKUP($J11,$B$5:$G$15,6, FALSE) -> 15.411621 | S11: SDL | T11: 5 | U11: 2 | V11: 4 | W11: 2 | X11: 3 | Y11: 1 | Z11: 1 | AA11: 1 | AB11: 1 | AC11: 5 | AD11: 5 | AE11: 5 | AF11: 5 | AG11: 5 | AH11: 5 | AI11: 5 | AJ11: 6 | AK11: 5
A12: 8 | B12: OGDC | C12: =E12-G12 -> -4.5466153 | D12: =RANK(E12,$E$5:$E$15,0) -> 6 | E12: -1.1741857 | F12: =RANK(G12,$G$5:$G$15,1) -> 8 | G12: 3.3724296 | I12: 2 | J12: MIA | K12: NOLA | L12: 30 | M12: 25 | N12: =IFERROR(mean+0.5*Home_edge+VLOOKUP(J12,$B$5:$G$15,4,FALSE)+VLOOKUP(K12,$B$5:$G$15,6,FALSE),"") -> 23.319328 | O12: =IFERROR(mean-0.5*Home_edge+VLOOKUP(K12,$B$5:$G$15,4,FALSE)+VLOOKUP(J12,$B$5:$G$15,6,FALSE),"") -> 20.725995 | P12: =IFERROR((N12-L12)^2+(O12-M12)^2,"") -> 62.898497 | Q12: =VLOOKUP($J12,$B$5:$G$15,4, FALSE)+VLOOKUP($K12,$B$5:$G$15,6, FALSE) -> -1.2875953 | R12: =VLOOKUP($K12,$B$5:$G$15,4, FALSE)+VLOOKUP($J12,$B$5:$G$15,6, FALSE) -> -0.21781721 | S12: SEA | T12: 2 | U12: 10 | V12: 7 | W12: 4 | X12: 5 | Y12: 6 | Z12: 5 | AA12: 8 | AB12: 8 | AC12: 8 | AD12: 8 | AE12: 8 | AF12: 7 | AG12: 6 | AH12: 7 | AI12: 6 | AJ12: 7 | AK12: 6
A13: 9 | B13: NOLA | C13: =E13-G13 -> -5.3027584 | D13: =RANK(E13,$E$5:$E$15,0) -> 8 | E13: -1.7886324 | F13: =RANK(G13,$G$5:$G$15,1) -> 9 | G13: 3.514126 | I13: 2 | J13: CHI | K13: UTAH | L13: 31 | M13: 45 | N13: =IFERROR(mean+0.5*Home_edge+VLOOKUP(J13,$B$5:$G$15,4,FALSE)+VLOOKUP(K13,$B$5:$G$15,6,FALSE),"") -> 24.077847 | O13: =IFERROR(mean-0.5*Home_edge+VLOOKUP(K13,$B$5:$G$15,4,FALSE)+VLOOKUP(J13,$B$5:$G$15,6,FALSE),"") -> 21.621499 | P13: =IFERROR((N13-L13)^2+(O13-M13)^2,"") -> 594.47048 | Q13: =VLOOKUP($J13,$B$5:$G$15,4, FALSE)+VLOOKUP($K13,$B$5:$G$15,6, FALSE) -> -0.52907599 | R13: =VLOOKUP($K13,$B$5:$G$15,4, FALSE)+VLOOKUP($J13,$B$5:$G$15,6, FALSE) -> 0.67768749 | S13: UTAH | T13: 7 | V13: 1 | W13: 1 | X13: 2 | Y13: 3 | Z13: 2 | AA13: 4 | AB13: 4 | AC13: 1 | AD13: 1 | AE13: 1 | AF13: 1 | AG13: 2 | AH13: 3 | AI13: 2 | AJ13: 2 | AK13: 1
A14: 10 | B14: MIA | C14: =E14-G14 -> -6.3725365 | D14: =RANK(E14,$E$5:$E$15,0) -> 10 | E14: -4.8017213 | F14: =RANK(G14,$G$5:$G$15,1) -> 7 | G14: 1.5708152 | I14: 2 | J14: RFCLA | K14: HOU | L14: 28 | M14: 45 | N14: =IFERROR(mean+0.5*Home_edge+VLOOKUP(J14,$B$5:$G$15,4,FALSE)+VLOOKUP(K14,$B$5:$G$15,6,FALSE),"") -> 23.946268 | O14: =IFERROR(mean-0.5*Home_edge+VLOOKUP(K14,$B$5:$G$15,4,FALSE)+VLOOKUP(J14,$B$5:$G$15,6,FALSE),"") -> 25.404504 | P14: =IFERROR((N14-L14)^2+(O14-M14)^2,"") -> 400.41619 | Q14: =VLOOKUP($J14,$B$5:$G$15,4, FALSE)+VLOOKUP($K14,$B$5:$G$15,6, FALSE) -> -0.66065508 | R14: =VLOOKUP($K14,$B$5:$G$15,4, FALSE)+VLOOKUP($J14,$B$5:$G$15,6, FALSE) -> 4.4606923
A15: 11 | B15: ARC | C15: =E15-G15 -> -18.078951 | D15: =RANK(E15,$E$5:$E$15,0) -> 11 | E15: -4.857239 | F15: =RANK(G15,$G$5:$G$15,1) -> 11 | G15: 13.221712 | I15: 3 | J15: ARC | K15: MIA | L15: 31 | M15: 32 | N15: =IFERROR(mean+0.5*Home_edge+VLOOKUP(J15,$B$5:$G$15,4,FALSE)+VLOOKUP(K15,$B$5:$G$15,6,FALSE),"") -> 21.3205 | O15: =IFERROR(mean-0.5*Home_edge+VLOOKUP(K15,$B$5:$G$15,4,FALSE)+VLOOKUP(J15,$B$5:$G$15,6,FALSE),"") -> 29.363802 | P15: =IFERROR((N15-L15)^2+(O15-M15)^2,"") -> 100.64227 | Q15: =VLOOKUP($J15,$B$5:$G$15,4, FALSE)+VLOOKUP($K15,$B$5:$G$15,6, FALSE) -> -3.2864238 | R15: =VLOOKUP($K15,$B$5:$G$15,4, FALSE)+VLOOKUP($J15,$B$5:$G$15,6, FALSE) -> 8.4199902 | T15: Log | AA15: Overall
I16: 3 | J16: UTAH | K16: NOLA | L16: 55 | M16: 21 | N16: =IFERROR(mean+0.5*Home_edge+VLOOKUP(J16,$B$5:$G$15,4,FALSE)+VLOOKUP(K16,$B$5:$G$15,6,FALSE),"") -> 32.974583 | O16: =IFERROR(mean-0.5*Home_edge+VLOOKUP(K16,$B$5:$G$15,4,FALSE)+VLOOKUP(J16,$B$5:$G$15,6,FALSE),"") -> 20.591065 | P16: =IFERROR((N16-L16)^2+(O16-M16)^2,"") -> 485.28621 | Q16: =VLOOKUP($J16,$B$5:$G$15,4, FALSE)+VLOOKUP($K16,$B$5:$G$15,6, FALSE) -> 8.3676598 | R16: =VLOOKUP($K16,$B$5:$G$15,4, FALSE)+VLOOKUP($J16,$B$5:$G$15,6, FALSE) -> -0.35274745 | T16: 1 | U16: OGDC | V16: 19.09785 | W16: 17.959618 | X16: MIA | Y16: Y | Z16: OGDC | AA16: Y | AB16: N
I17: 3 | J17: OGDC | K17: SDL | L17: 10 | M17: 26 | N17: =IFERROR(mean+0.5*Home_edge+VLOOKUP(J17,$B$5:$G$15,4,FALSE)+VLOOKUP(K17,$B$5:$G$15,6,FALSE),"") -> 23.717431 | O17: =IFERROR(mean-0.5*Home_edge+VLOOKUP(K17,$B$5:$G$15,4,FALSE)+VLOOKUP(J17,$B$5:$G$15,6,FALSE),"") -> 26.506151 | P17: =IFERROR((N17-L17)^2+(O17-M17)^2,"") -> 188.42409 | Q17: =VLOOKUP($J17,$B$5:$G$15,4, FALSE)+VLOOKUP($K17,$B$5:$G$15,6, FALSE) -> -0.88949281 | R17: =VLOOKUP($K17,$B$5:$G$15,4, FALSE)+VLOOKUP($J17,$B$5:$G$15,6, FALSE) -> 5.5623393 | U17: ARC | V17: 15.665113 | W17: 38.436466 | X17: NOLA | Y17: Y | Z17: NOLA | AA17: =COUNTIF(Y16:Y93,"Y") -> 47 | AB17: =COUNTIF(Y16:Y95, "N") -> 28
I18: 3 | J18: HOU | K18: SEA | L18: 24 | M18: 21 | N18: =IFERROR(mean+0.5*Home_edge+VLOOKUP(J18,$B$5:$G$15,4,FALSE)+VLOOKUP(K18,$B$5:$G$15,6,FALSE),"") -> 23.89897 | O18: =IFERROR(mean-0.5*Home_edge+VLOOKUP(K18,$B$5:$G$15,4,FALSE)+VLOOKUP(J18,$B$5:$G$15,6,FALSE),"") -> 16.456238 | P18: =IFERROR((N18-L18)^2+(O18-M18)^2,"") -> 20.655976 | Q18: =VLOOKUP($J18,$B$5:$G$15,4, FALSE)+VLOOKUP($K18,$B$5:$G$15,6, FALSE) -> -0.70795328 | R18: =VLOOKUP($K18,$B$5:$G$15,4, FALSE)+VLOOKUP($J18,$B$5:$G$15,6, FALSE) -> -4.4875736 | U18: CHI | V18: 18.801577 | W18: 25.447747 | X18: HOU | Y18: N | Z18: HOU
I19: 3 | J19: CHI | K19: NEFJ | L19: 36 | M19: 7 | N19: =IFERROR(mean+0.5*Home_edge+VLOOKUP(J19,$B$5:$G$15,4,FALSE)+VLOOKUP(K19,$B$5:$G$15,6,FALSE),"") -> 17.582278 | O19: =IFERROR(mean-0.5*Home_edge+VLOOKUP(K19,$B$5:$G$15,4,FALSE)+VLOOKUP(J19,$B$5:$G$15,6,FALSE),"") -> 15.49433 | P19: =IFERROR((N19-L19)^2+(O19-M19)^2,"") -> 411.3661 | Q19: =VLOOKUP($J19,$B$5:$G$15,4, FALSE)+VLOOKUP($K19,$B$5:$G$15,6, FALSE) -> -7.024645 | R19: =VLOOKUP($K19,$B$5:$G$15,4, FALSE)+VLOOKUP($J19,$B$5:$G$15,6, FALSE) -> -5.4494824 | U19: SEA | V19: 24.879673 | W19: 17.689527 | X19: SD | Y19: N | Z19: SEA | AA19: =COUNTIF(Y16:Y48, "Y") -> 24 | AB19: =COUNTIF(Y16:Y48, "N") -> 9
B20: Movers | I20: 4 | J20: UTAH | K20: HOU | L20: 17 | M20: 37 | N20: =IFERROR(mean+0.5*Home_edge+VLOOKUP(J20,$B$5:$G$15,4,FALSE)+VLOOKUP(K20,$B$5:$G$15,6,FALSE),"") -> 24.953562 | O20: =IFERROR(mean-0.5*Home_edge+VLOOKUP(K20,$B$5:$G$15,4,FALSE)+VLOOKUP(J20,$B$5:$G$15,6,FALSE),"") -> 22.473827 | P20: =IFERROR((N20-L20)^2+(O20-M20)^2,"") -> 274.26885 | Q20: =VLOOKUP($J20,$B$5:$G$15,4, FALSE)+VLOOKUP($K20,$B$5:$G$15,6, FALSE) -> 0.34663817 | R20: =VLOOKUP($K20,$B$5:$G$15,4, FALSE)+VLOOKUP($J20,$B$5:$G$15,6, FALSE) -> 1.530015 | U20: NEFJ | V20: 28.088044 | W20: 17.510607 | X20: RFCLA | Y20: Y | Z20: NEFJ | AA20: last few weeks
B21: Team | C21: LastRank | D21: Rank | E21: Change | F21: sum changes | I21: 4 | J21: OGDC | K21: ARC | L21: 26 | M21: 22 | N21: =IFERROR(mean+0.5*Home_edge+VLOOKUP(J21,$B$5:$G$15,4,FALSE)+VLOOKUP(K21,$B$5:$G$15,6,FALSE),"") -> 36.654449 | O21: =IFERROR(mean-0.5*Home_edge+VLOOKUP(K21,$B$5:$G$15,4,FALSE)+VLOOKUP(J21,$B$5:$G$15,6,FALSE),"") -> 19.459003 | P21: =IFERROR((N21-L21)^2+(O21-M21)^2,"") -> 119.97396 | Q21: =VLOOKUP($J21,$B$5:$G$15,4, FALSE)+VLOOKUP($K21,$B$5:$G$15,6, FALSE) -> 12.047526 | R21: =VLOOKUP($K21,$B$5:$G$15,4, FALSE)+VLOOKUP($J21,$B$5:$G$15,6, FALSE) -> -1.4848094 | T21: 2 | U21: ARC | V21: =IFERROR(mean+0.5*Home_edge+VLOOKUP(U21,$B$5:$G$14,4,FALSE)+VLOOKUP(X21,$B$5:$G$14,6,FALSE),"") | W21: =IFERROR(mean-0.5*Home_edge+VLOOKUP(X21,$B$5:$G$14,4,FALSE)+VLOOKUP(U21,$B$5:$G$14,6,FALSE),"") | X21: SDL | Y21: Y | Z21: SDL | AA21: =COUNTIF(Y49:Y94, "Y") -> 24 | AB21: =COUNTIF(Y49:Y94, "N") -> 19
B22: NEFJ | C22: 1 | D22: 3 | E22: =C22-D22 -> -2 | F22: =SUM(E22:E32) -> 0 | I22: 4 | J22: MIA | K22: CHI | L22: 18 | M22: 31 | N22: =IFERROR(mean+0.5*Home_edge+VLOOKUP(J22,$B$5:$G$15,4,FALSE)+VLOOKUP(K22,$B$5:$G$15,6,FALSE),"") -> 15.629356 | O22: =IFERROR(mean-0.5*Home_edge+VLOOKUP(K22,$B$5:$G$15,4,FALSE)+VLOOKUP(J22,$B$5:$G$15,6,FALSE),"") -> 20.549666 | P22: =IFERROR((N22-L22)^2+(O22-M22)^2,"") -> 114.82943 | Q22: =VLOOKUP($J22,$B$5:$G$15,4, FALSE)+VLOOKUP($K22,$B$5:$G$15,6, FALSE) -> -8.9775676 | R22: =VLOOKUP($K22,$B$5:$G$15,4, FALSE)+VLOOKUP($J22,$B$5:$G$15,6, FALSE) -> -0.39414576 | U22: MIA | V22: =IFERROR(mean+0.5*Home_edge+VLOOKUP(U22,$B$5:$G$14,4,FALSE)+VLOOKUP(X22,$B$5:$G$14,6,FALSE),"") -> 23.319328 | W22: =IFERROR(mean-0.5*Home_edge+VLOOKUP(X22,$B$5:$G$14,4,FALSE)+VLOOKUP(U22,$B$5:$G$14,6,FALSE),"") -> 20.725995 | X22: NOLA | Y22: N | Z22: NOLA
B23: UTAH | C23: 2 | D23: 1 | E23: =C23-D23 -> 1 | I23: 4 | J23: SDL | K23: RFCLA | L23: 36 | M23: 28 | N23: =IFERROR(mean+0.5*Home_edge+VLOOKUP(J23,$B$5:$G$15,4,FALSE)+VLOOKUP(K23,$B$5:$G$15,6,FALSE),"") -> 31.163395 | O23: =IFERROR(mean-0.5*Home_edge+VLOOKUP(K23,$B$5:$G$15,4,FALSE)+VLOOKUP(J23,$B$5:$G$15,6,FALSE),"") -> 25.074745 | P23: =IFERROR((N23-L23)^2+(O23-M23)^2,"") -> 31.949858 | Q23: =VLOOKUP($J23,$B$5:$G$15,4, FALSE)+VLOOKUP($K23,$B$5:$G$15,6, FALSE) -> 6.556472 | R23: =VLOOKUP($K23,$B$5:$G$15,4, FALSE)+VLOOKUP($J23,$B$5:$G$15,6, FALSE) -> 4.1309334 | U23: CHI | V23: =IFERROR(mean+0.5*Home_edge+VLOOKUP(U23,$B$5:$G$14,4,FALSE)+VLOOKUP(X23,$B$5:$G$14,6,FALSE),"") -> 24.077847 | W23: =IFERROR(mean-0.5*Home_edge+VLOOKUP(X23,$B$5:$G$14,4,FALSE)+VLOOKUP(U23,$B$5:$G$14,6,FALSE),"") -> 21.621499 | X23: UTAH | Y23: N | Z23: CHI
B24: HOU | C24: 3 | D24: 2 | E24: =C24-D24 -> 1 | I24: 4 | J24: SEA | K24: NEFJ | L24: 27 | M24: 24 | N24: =IFERROR(mean+0.5*Home_edge+VLOOKUP(J24,$B$5:$G$15,4,FALSE)+VLOOKUP(K24,$B$5:$G$15,6,FALSE),"") -> 19.566561 | O24: =IFERROR(mean-0.5*Home_edge+VLOOKUP(K24,$B$5:$G$15,4,FALSE)+VLOOKUP(J24,$B$5:$G$15,6,FALSE),"") -> 18.868092 | P24: =IFERROR((N24-L24)^2+(O24-M24)^2,"") -> 81.592483 | Q24: =VLOOKUP($J24,$B$5:$G$15,4, FALSE)+VLOOKUP($K24,$B$5:$G$15,6, FALSE) -> -5.040362 | R24: =VLOOKUP($K24,$B$5:$G$15,4, FALSE)+VLOOKUP($J24,$B$5:$G$15,6, FALSE) -> -2.0757195 | U24: RFCLA | V24: =IFERROR(mean+0.5*Home_edge+VLOOKUP(U24,$B$5:$G$14,4,FALSE)+VLOOKUP(X24,$B$5:$G$14,6,FALSE),"") -> 23.946268 | W24: =IFERROR(mean-0.5*Home_edge+VLOOKUP(X24,$B$5:$G$14,4,FALSE)+VLOOKUP(U24,$B$5:$G$14,6,FALSE),"") -> 25.404504 | X24: HOU | Y24: Y | Z24: HOU
B25: CHI | C25: 4 | D25: 4 | E25: =C25-D25 -> 0 | I25: 5 | J25: CHI | K25: OGDC | L25: 30 | M25: 26 | N25: =IFERROR(mean+0.5*Home_edge+VLOOKUP(J25,$B$5:$G$15,4,FALSE)+VLOOKUP(K25,$B$5:$G$15,6,FALSE),"") -> 26.014392 | O25: =IFERROR(mean-0.5*Home_edge+VLOOKUP(K25,$B$5:$G$15,4,FALSE)+VLOOKUP(J25,$B$5:$G$15,6,FALSE),"") -> 15.59378 | P25: =IFERROR((N25-L25)^2+(O25-M25)^2,"") -> 124.17448 | Q25: =VLOOKUP($J25,$B$5:$G$15,4, FALSE)+VLOOKUP($K25,$B$5:$G$15,6, FALSE) -> 1.4074687 | R25: =VLOOKUP($K25,$B$5:$G$15,4, FALSE)+VLOOKUP($J25,$B$5:$G$15,6, FALSE) -> -5.3500319 | T25: 3 | U25: ARC | V25: =IFERROR(mean+0.5*Home_edge+VLOOKUP(U25,$B$5:$G$15,4,FALSE)+VLOOKUP(X25,$B$5:$G$15,6,FALSE),"") -> 21.3205 | W25: =IFERROR(mean-0.5*Home_edge+VLOOKUP(X25,$B$5:$G$15,4,FALSE)+VLOOKUP(U25,$B$5:$G$15,6,FALSE),"") -> 29.363802 | X25: MIA | Y25: Y | Z25: MIA
B26: RFCLA | C26: 5 | D26: 7 | E26: =C26-D26 -> -2 | I26: 5 | J26: NEFJ | K26: NOLA | L26: 35 | M26: 31 | N26: =IFERROR(mean+0.5*Home_edge+VLOOKUP(J26,$B$5:$G$15,4,FALSE)+VLOOKUP(K26,$B$5:$G$15,6,FALSE),"") -> 26.847413 | O26: =IFERROR(mean-0.5*Home_edge+VLOOKUP(K26,$B$5:$G$15,4,FALSE)+VLOOKUP(J26,$B$5:$G$15,6,FALSE),"") -> 14.095495 | P26: =IFERROR((N26-L26)^2+(O26-M26)^2,"") -> 352.22694 | Q26: =VLOOKUP($J26,$B$5:$G$15,4, FALSE)+VLOOKUP($K26,$B$5:$G$15,6, FALSE) -> 2.2404899 | R26: =VLOOKUP($K26,$B$5:$G$15,4, FALSE)+VLOOKUP($J26,$B$5:$G$15,6, FALSE) -> -6.8483165 | U26: UTAH | V26: =IFERROR(mean+0.5*Home_edge+VLOOKUP(U26,$B$5:$G$15,4,FALSE)+VLOOKUP(X26,$B$5:$G$15,6,FALSE),"") -> 32.974583 | W26: =IFERROR(mean-0.5*Home_edge+VLOOKUP(X26,$B$5:$G$15,4,FALSE)+VLOOKUP(U26,$B$5:$G$15,6,FALSE),"") -> 20.591065 | X26: NOLA | Y26: Y | Z26: UTAH
B27: SDL | C27: 6 | D27: 5 | E27: =C27-D27 -> 1 | I27: 5 | J27: MIA | K27: UTAH | L27: 19 | M27: 36 | N27: =IFERROR(mean+0.5*Home_edge+VLOOKUP(J27,$B$5:$G$15,4,FALSE)+VLOOKUP(K27,$B$5:$G$15,6,FALSE),"") -> 21.241087 | O27: =IFERROR(mean-0.5*Home_edge+VLOOKUP(K27,$B$5:$G$15,4,FALSE)+VLOOKUP(J27,$B$5:$G$15,6,FALSE),"") -> 27.368161 | P27: =IFERROR((N27-L27)^2+(O27-M27)^2,"") -> 79.531117 | Q27: =VLOOKUP($J27,$B$5:$G$15,4, FALSE)+VLOOKUP($K27,$B$5:$G$15,6, FALSE) -> -3.3658364 | R27: =VLOOKUP($K27,$B$5:$G$15,4, FALSE)+VLOOKUP($J27,$B$5:$G$15,6, FALSE) -> 6.424349 | U27: OGDC | V27: =IFERROR(mean+0.5*Home_edge+VLOOKUP(U27,$B$5:$G$15,4,FALSE)+VLOOKUP(X27,$B$5:$G$15,6,FALSE),"") -> 23.717431 | W27: =IFERROR(mean-0.5*Home_edge+VLOOKUP(X27,$B$5:$G$15,4,FALSE)+VLOOKUP(U27,$B$5:$G$15,6,FALSE),"") -> 26.506151 | X27: SDL | Y27: Y | Z27: SDL
B28: SEA | C28: 7 | D28: 6 | E28: =C28-D28 -> 1 | I28: 5 | J28: RFCLA | K28: SEA | L28: 35 | M28: 29 | N28: =IFERROR(mean+0.5*Home_edge+VLOOKUP(J28,$B$5:$G$15,4,FALSE)+VLOOKUP(K28,$B$5:$G$15,6,FALSE),"") -> 27.651081 | O28: =IFERROR(mean-0.5*Home_edge+VLOOKUP(K28,$B$5:$G$15,4,FALSE)+VLOOKUP(J28,$B$5:$G$15,6,FALSE),"") -> 25.329696 | P28: =IFERROR((N28-L28)^2+(O28-M28)^2,"") -> 67.477745 | Q28: =VLOOKUP($J28,$B$5:$G$15,4, FALSE)+VLOOKUP($K28,$B$5:$G$15,6, FALSE) -> 3.0441572 | R28: =VLOOKUP($K28,$B$5:$G$15,4, FALSE)+VLOOKUP($J28,$B$5:$G$15,6, FALSE) -> 4.3858843 | U28: HOU | V28: =IFERROR(mean+0.5*Home_edge+VLOOKUP(U28,$B$5:$G$15,4,FALSE)+VLOOKUP(X28,$B$5:$G$15,6,FALSE),"") -> 23.89897 | W28: =IFERROR(mean-0.5*Home_edge+VLOOKUP(X28,$B$5:$G$15,4,FALSE)+VLOOKUP(U28,$B$5:$G$15,6,FALSE),"") -> 16.456238 | X28: SEA | Y28: Y | Z28: HOU | AC28: parlay analyzer
B29: OGDC | C29: 8 | D29: 8 | E29: =C29-D29 -> 0 | I29: 6 | J29: OGDC | K29: NEFJ | L29: 28 | M29: 15 | N29: =IFERROR(mean+0.5*Home_edge+VLOOKUP(J29,$B$5:$G$15,4,FALSE)+VLOOKUP(K29,$B$5:$G$15,6,FALSE),"") -> 18.373054 | O29: =IFERROR(mean-0.5*Home_edge+VLOOKUP(K29,$B$5:$G$15,4,FALSE)+VLOOKUP(J29,$B$5:$G$15,6,FALSE),"") -> 23.042605 | P29: =IFERROR((N29-L29)^2+(O29-M29)^2,"") -> 157.3616 | Q29: =VLOOKUP($J29,$B$5:$G$15,4, FALSE)+VLOOKUP($K29,$B$5:$G$15,6, FALSE) -> -6.2338697 | R29: =VLOOKUP($K29,$B$5:$G$15,4, FALSE)+VLOOKUP($J29,$B$5:$G$15,6, FALSE) -> 2.0987935 | U29: CHI | V29: =IFERROR(mean+0.5*Home_edge+VLOOKUP(U29,$B$5:$G$15,4,FALSE)+VLOOKUP(X29,$B$5:$G$15,6,FALSE),"") -> 17.582278 | W29: =IFERROR(mean-0.5*Home_edge+VLOOKUP(X29,$B$5:$G$15,4,FALSE)+VLOOKUP(U29,$B$5:$G$15,6,FALSE),"") -> 15.49433 | X29: NEFJ | Y29: Y | Z29: CHI | AC29: CHI | AD29: SDL | AE29: UTAH | AF29: CHI | AG29: SDL | AH29: UTAH
B30: MIA | C30: 9 | D30: 10 | E30: =C30-D30 -> -1 | I30: 6 | J30: ARC | K30: HOU | L30: 45 | M30: 46 | N30: =IFERROR(mean+0.5*Home_edge+VLOOKUP(J30,$B$5:$G$15,4,FALSE)+VLOOKUP(K30,$B$5:$G$15,6,FALSE),"") -> 15.242789 | O30: =IFERROR(mean-0.5*Home_edge+VLOOKUP(K30,$B$5:$G$15,4,FALSE)+VLOOKUP(J30,$B$5:$G$15,6,FALSE),"") -> 34.259654 | P30: =IFERROR((N30-L30)^2+(O30-M30)^2,"") -> 1023.3273 | Q30: =VLOOKUP($J30,$B$5:$G$15,4, FALSE)+VLOOKUP($K30,$B$5:$G$15,6, FALSE) -> -9.3641346 | R30: =VLOOKUP($K30,$B$5:$G$15,4, FALSE)+VLOOKUP($J30,$B$5:$G$15,6, FALSE) -> 13.315842 | T30: 4 | U30: UTAH | V30: =IFERROR(mean+0.5*Home_edge+VLOOKUP(U30,$B$5:$G$15,4,FALSE)+VLOOKUP(X30,$B$5:$G$15,6,FALSE),"") -> 24.953562 | W30: =IFERROR(mean-0.5*Home_edge+VLOOKUP(X30,$B$5:$G$15,4,FALSE)+VLOOKUP(U30,$B$5:$G$15,6,FALSE),"") -> 22.473827 | X30: HOU | Y30: N | Z30: UTAH | AC30: W | AD30: W | AE30: W | AF30: =IF(AC30="W", 18.69, 0) -> 18.69 | AG30: =IF(AD30="W", 18.69, 0) -> 18.69 | AH30: =IF(AE30="W", 19.52, 0) -> 19.52
B31: NOLA | C31: 10 | D31: 9 | E31: =C31-D31 -> 1 | I31: 6 | J31: NOLA | K31: RFCLA | L31: 24 | M31: 31 | N31: =IFERROR(mean+0.5*Home_edge+VLOOKUP(J31,$B$5:$G$15,4,FALSE)+VLOOKUP(K31,$B$5:$G$15,6,FALSE),"") -> 27.184853 | O31: =IFERROR(mean-0.5*Home_edge+VLOOKUP(K31,$B$5:$G$15,4,FALSE)+VLOOKUP(J31,$B$5:$G$15,6,FALSE),"") -> 28.304178 | P31: =IFERROR((N31-L31)^2+(O31-M31)^2,"") -> 17.410745 | Q31: =VLOOKUP($J31,$B$5:$G$15,4, FALSE)+VLOOKUP($K31,$B$5:$G$15,6, FALSE) -> 2.5779299 | R31: =VLOOKUP($K31,$B$5:$G$15,4, FALSE)+VLOOKUP($J31,$B$5:$G$15,6, FALSE) -> 7.3603665 | U31: OGDC | V31: =IFERROR(mean+0.5*Home_edge+VLOOKUP(U31,$B$5:$G$15,4,FALSE)+VLOOKUP(X31,$B$5:$G$15,6,FALSE),"") -> 36.654449 | W31: =IFERROR(mean-0.5*Home_edge+VLOOKUP(X31,$B$5:$G$15,4,FALSE)+VLOOKUP(U31,$B$5:$G$15,6,FALSE),"") -> 19.459003 | X31: ARC | Y31: Y | Z31: OGDC | AC31: W | AD31: W | AE31: L | AF31: =IF(AC31="W", 18.69, 0) -> 18.69 | AG31: =IF(AD31="W", 18.69, 0) -> 18.69 | AH31: =IF(AE31="W", 19.52, 0) -> 0
B32: ARC | C32: 11 | D32: 11 | E32: =C32-D32 -> 0 | I32: 6 | J32: SDL | K32: MIA | L32: 31 | M32: 12 | N32: =IFERROR(mean+0.5*Home_edge+VLOOKUP(J32,$B$5:$G$15,4,FALSE)+VLOOKUP(K32,$B$5:$G$15,6,FALSE),"") -> 28.367648 | O32: =IFERROR(mean-0.5*Home_edge+VLOOKUP(K32,$B$5:$G$15,4,FALSE)+VLOOKUP(J32,$B$5:$G$15,6,FALSE),"") -> 16.426783 | P32: =IFERROR((N32-L32)^2+(O32-M32)^2,"") -> 26.525687 | Q32: =VLOOKUP($J32,$B$5:$G$15,4, FALSE)+VLOOKUP($K32,$B$5:$G$15,6, FALSE) -> 3.7607249 | R32: =VLOOKUP($K32,$B$5:$G$15,4, FALSE)+VLOOKUP($J32,$B$5:$G$15,6, FALSE) -> -4.5170285 | U32: MIA | V32: =IFERROR(mean+0.5*Home_edge+VLOOKUP(U32,$B$5:$G$15,4,FALSE)+VLOOKUP(X32,$B$5:$G$15,6,FALSE),"") -> 15.629356 | W32: =IFERROR(mean-0.5*Home_edge+VLOOKUP(X32,$B$5:$G$15,4,FALSE)+VLOOKUP(U32,$B$5:$G$15,6,FALSE),"") -> 20.549666 | X32: CHI | Y32: Y | Z32: CHI | AC32: L | AD32: W | AE32: W | AF32: =IF(AC32="W", 18.69, 0) -> 0 | AG32: =IF(AD32="W", 18.69, 0) -> 18.69 | AH32: =IF(AE32="W", 19.52, 0) -> 19.52
I33: 6 | J33: SEA | K33: UTAH | L33: 27 | M33: 30 | N33: =IFERROR(mean+0.5*Home_edge+VLOOKUP(J33,$B$5:$G$15,4,FALSE)+VLOOKUP(K33,$B$5:$G$15,6,FALSE),"") -> 26.06213 | O33: =IFERROR(mean-0.5*Home_edge+VLOOKUP(K33,$B$5:$G$15,4,FALSE)+VLOOKUP(J33,$B$5:$G$15,6,FALSE),"") -> 24.995262 | P33: =IFERROR((N33-L33)^2+(O33-M33)^2,"") -> 25.926998 | Q33: =VLOOKUP($J33,$B$5:$G$15,4, FALSE)+VLOOKUP($K33,$B$5:$G$15,6, FALSE) -> 1.455207 | R33: =VLOOKUP($K33,$B$5:$G$15,4, FALSE)+VLOOKUP($J33,$B$5:$G$15,6, FALSE) -> 4.0514504 | U33: SDL | V33: =IFERROR(mean+0.5*Home_edge+VLOOKUP(U33,$B$5:$G$15,4,FALSE)+VLOOKUP(X33,$B$5:$G$15,6,FALSE),"") -> 31.163395 | W33: =IFERROR(mean-0.5*Home_edge+VLOOKUP(X33,$B$5:$G$15,4,FALSE)+VLOOKUP(U33,$B$5:$G$15,6,FALSE),"") -> 25.074745 | X33: RFCLA | Y33: Y | Z33: SDL | AC33: W | AD33: L | AE33: W | AF33: =IF(AC33="W", 18.69, 0) -> 18.69 | AG33: =IF(AD33="W", 18.69, 0) -> 0 | AH33: =IF(AE33="W", 19.52, 0) -> 19.52
I34: 7 | J34: NOLA | K34: CHI | L34: 18 | M34: 20 | N34: =IFERROR(mean+0.5*Home_edge+VLOOKUP(J34,$B$5:$G$15,4,FALSE)+VLOOKUP(K34,$B$5:$G$15,6,FALSE),"") -> 18.642445 | O34: =IFERROR(mean-0.5*Home_edge+VLOOKUP(K34,$B$5:$G$15,4,FALSE)+VLOOKUP(J34,$B$5:$G$15,6,FALSE),"") -> 22.492977 | P34: =IFERROR((N34-L34)^2+(O34-M34)^2,"") -> 6.6276698 | Q34: =VLOOKUP($J34,$B$5:$G$15,4, FALSE)+VLOOKUP($K34,$B$5:$G$15,6, FALSE) -> -5.9644787 | R34: =VLOOKUP($K34,$B$5:$G$15,4, FALSE)+VLOOKUP($J34,$B$5:$G$15,6, FALSE) -> 1.5491651 | U34: SEA | V34: =IFERROR(mean+0.5*Home_edge+VLOOKUP(U34,$B$5:$G$15,4,FALSE)+VLOOKUP(X34,$B$5:$G$15,6,FALSE),"") -> 19.566561 | W34: =IFERROR(mean-0.5*Home_edge+VLOOKUP(X34,$B$5:$G$15,4,FALSE)+VLOOKUP(U34,$B$5:$G$15,6,FALSE),"") -> 18.868092 | X34: NEFJ | Y34: Y | Z34: SEA | AC34: W | AD34: L | AE34: L | AF34: =IF(AC34="W", 18.69, 0) -> 18.69 | AG34: =IF(AD34="W", 18.69, 0) -> 0 | AH34: =IF(AE34="W", 19.52, 0) -> 0
I35: 7 | J35: HOU | K35: SDL | L35: 34 | M35: 14 | N35: =IFERROR(mean+0.5*Home_edge+VLOOKUP(J35,$B$5:$G$15,4,FALSE)+VLOOKUP(K35,$B$5:$G$15,6,FALSE),"") -> 24.985746 | O35: =IFERROR(mean-0.5*Home_edge+VLOOKUP(K35,$B$5:$G$15,4,FALSE)+VLOOKUP(J35,$B$5:$G$15,6,FALSE),"") -> 18.626826 | P35: =IFERROR((N35-L35)^2+(O35-M35)^2,"") -> 102.66429 | Q35: =VLOOKUP($J35,$B$5:$G$15,4, FALSE)+VLOOKUP($K35,$B$5:$G$15,6, FALSE) -> 0.3788229 | R35: =VLOOKUP($K35,$B$5:$G$15,4, FALSE)+VLOOKUP($J35,$B$5:$G$15,6, FALSE) -> -2.3169859 | T35: 5 | U35: CHI | V35: =IFERROR(mean+0.5*Home_edge+VLOOKUP(U35,$B$5:$G$15,4,FALSE)+VLOOKUP(X35,$B$5:$G$15,6,FALSE),"") -> 26.014392 | W35: =IFERROR(mean-0.5*Home_edge+VLOOKUP(X35,$B$5:$G$15,4,FALSE)+VLOOKUP(U35,$B$5:$G$15,6,FALSE),"") -> 15.59378 | X35: OGDC | Y35: Y | Z35: CHI | AC35: L | AD35: W | AE35: L | AF35: =IF(AC35="W", 18.69, 0) -> 0 | AG35: =IF(AD35="W", 18.69, 0) -> 18.69 | AH35: =IF(AE35="W", 19.52, 0) -> 0
I36: 7 | J36: SEA | K36: ARC | L36: 25 | M36: 17 | N36: =IFERROR(mean+0.5*Home_edge+VLOOKUP(J36,$B$5:$G$15,4,FALSE)+VLOOKUP(K36,$B$5:$G$15,6,FALSE),"") -> 37.847957 | O36: =IFERROR(mean-0.5*Home_edge+VLOOKUP(K36,$B$5:$G$15,4,FALSE)+VLOOKUP(J36,$B$5:$G$15,6,FALSE),"") -> 15.28449 | P36: =IFERROR((N36-L36)^2+(O36-M36)^2,"") -> 168.01298 | Q36: =VLOOKUP($J36,$B$5:$G$15,4, FALSE)+VLOOKUP($K36,$B$5:$G$15,6, FALSE) -> 13.241034 | R36: =VLOOKUP($K36,$B$5:$G$15,4, FALSE)+VLOOKUP($J36,$B$5:$G$15,6, FALSE) -> -5.6593224 | U36: NEFJ | V36: =IFERROR(mean+0.5*Home_edge+VLOOKUP(U36,$B$5:$G$15,4,FALSE)+VLOOKUP(X36,$B$5:$G$15,6,FALSE),"") -> 26.847413 | W36: =IFERROR(mean-0.5*Home_edge+VLOOKUP(X36,$B$5:$G$15,4,FALSE)+VLOOKUP(U36,$B$5:$G$15,6,FALSE),"") -> 14.095495 | X36: NOLA | Y36: Y | Z36: NEFJ | AC36: L | AD36: L | AE36: W | AF36: =IF(AC36="W", 18.69, 0) -> 0 | AG36: =IF(AD36="W", 18.69, 0) -> 0 | AH36: =IF(AE36="W", 19.52, 0) -> 19.52
I37: 7 | J37: UTAH | K37: NEFJ | L37: 26 | M37: 33 | N37: =IFERROR(mean+0.5*Home_edge+VLOOKUP(J37,$B$5:$G$15,4,FALSE)+VLOOKUP(K37,$B$5:$G$15,6,FALSE),"") -> 24.400773 | O37: =IFERROR(mean-0.5*Home_edge+VLOOKUP(K37,$B$5:$G$15,4,FALSE)+VLOOKUP(J37,$B$5:$G$15,6,FALSE),"") -> 21.106061 | P37: =IFERROR((N37-L37)^2+(O37-M37)^2,"") -> 144.02332 | Q37: =VLOOKUP($J37,$B$5:$G$15,4, FALSE)+VLOOKUP($K37,$B$5:$G$15,6, FALSE) -> -0.2061503 | R37: =VLOOKUP($K37,$B$5:$G$15,4, FALSE)+VLOOKUP($J37,$B$5:$G$15,6, FALSE) -> 0.16224882 | U37: MIA | V37: =IFERROR(mean+0.5*Home_edge+VLOOKUP(U37,$B$5:$G$15,4,FALSE)+VLOOKUP(X37,$B$5:$G$15,6,FALSE),"") -> 21.241087 | W37: =IFERROR(mean-0.5*Home_edge+VLOOKUP(X37,$B$5:$G$15,4,FALSE)+VLOOKUP(U37,$B$5:$G$15,6,FALSE),"") -> 27.368161 | X37: UTAH | Y37: Y | Z37: UTAH | AC37: L | AD37: L | AE37: L | AF37: =IF(AC37="W", 18.69, 0) -> 0 | AG37: =IF(AD37="W", 18.69, 0) -> 0 | AH37: =IF(AE37="W", 19.52, 0) -> 0
I38: 7 | J38: RFCLA | K38: OGDC | L38: 54 | M38: 44 | N38: =IFERROR(mean+0.5*Home_edge+VLOOKUP(J38,$B$5:$G$15,4,FALSE)+VLOOKUP(K38,$B$5:$G$15,6,FALSE),"") -> 31.825594 | O38: =IFERROR(mean-0.5*Home_edge+VLOOKUP(K38,$B$5:$G$15,4,FALSE)+VLOOKUP(J38,$B$5:$G$15,6,FALSE),"") -> 24.136189 | P38: =IFERROR((N38-L38)^2+(O38-M38)^2,"") -> 886.2753 | Q38: =VLOOKUP($J38,$B$5:$G$15,4, FALSE)+VLOOKUP($K38,$B$5:$G$15,6, FALSE) -> 7.2186701 | R38: =VLOOKUP($K38,$B$5:$G$15,4, FALSE)+VLOOKUP($J38,$B$5:$G$15,6, FALSE) -> 3.1923766 | U38: RFCLA | V38: =IFERROR(mean+0.5*Home_edge+VLOOKUP(U38,$B$5:$G$15,4,FALSE)+VLOOKUP(X38,$B$5:$G$15,6,FALSE),"") -> 27.651081 | W38: =IFERROR(mean-0.5*Home_edge+VLOOKUP(X38,$B$5:$G$15,4,FALSE)+VLOOKUP(U38,$B$5:$G$15,6,FALSE),"") -> 25.329696 | X38: SEA | Y38: N | Z38: SEA
I39: 8 | J39: OGDC | K39: SEA | L39: 29 | M39: 12 | N39: =IFERROR(mean+0.5*Home_edge+VLOOKUP(J39,$B$5:$G$15,4,FALSE)+VLOOKUP(K39,$B$5:$G$15,6,FALSE),"") -> 22.630654 | O39: =IFERROR(mean-0.5*Home_edge+VLOOKUP(K39,$B$5:$G$15,4,FALSE)+VLOOKUP(J39,$B$5:$G$15,6,FALSE),"") -> 24.335564 | P39: =IFERROR((N39-L39)^2+(O39-M39)^2,"") -> 192.73469 | Q39: =VLOOKUP($J39,$B$5:$G$15,4, FALSE)+VLOOKUP($K39,$B$5:$G$15,6, FALSE) -> -1.976269 | R39: =VLOOKUP($K39,$B$5:$G$15,4, FALSE)+VLOOKUP($J39,$B$5:$G$15,6, FALSE) -> 3.3917517 | T39: 6 | U39: OGDC | V39: 13.804044 | W39: 13.067094 | X39: NEFJ | Y39: Y | Z39: OGDC
I40: 8 | J40: ARC | K40: NOLA | L40: 19 | M40: 33 | N40: =IFERROR(mean+0.5*Home_edge+VLOOKUP(J40,$B$5:$G$15,4,FALSE)+VLOOKUP(K40,$B$5:$G$15,6,FALSE),"") -> 23.26381 | O40: =IFERROR(mean-0.5*Home_edge+VLOOKUP(K40,$B$5:$G$15,4,FALSE)+VLOOKUP(J40,$B$5:$G$15,6,FALSE),"") -> 32.376891 | P40: =IFERROR((N40-L40)^2+(O40-M40)^2,"") -> 18.568344 | Q40: =VLOOKUP($J40,$B$5:$G$15,4, FALSE)+VLOOKUP($K40,$B$5:$G$15,6, FALSE) -> -1.343113 | R40: =VLOOKUP($K40,$B$5:$G$15,4, FALSE)+VLOOKUP($J40,$B$5:$G$15,6, FALSE) -> 11.433079 | U40: ARC | V40: 5.9253455 | W40: 42.955169 | X40: HOU | Y40: Y | Z40: HOU
I41: 8 | J41: HOU | K41: RFCLA | L41: 22 | M41: 24 | N41: =IFERROR(mean+0.5*Home_edge+VLOOKUP(J41,$B$5:$G$15,4,FALSE)+VLOOKUP(K41,$B$5:$G$15,6,FALSE),"") -> 29.067616 | O41: =IFERROR(mean-0.5*Home_edge+VLOOKUP(K41,$B$5:$G$15,4,FALSE)+VLOOKUP(J41,$B$5:$G$15,6,FALSE),"") -> 20.283157 | P41: =IFERROR((N41-L41)^2+(O41-M41)^2,"") -> 63.766116 | Q41: =VLOOKUP($J41,$B$5:$G$15,4, FALSE)+VLOOKUP($K41,$B$5:$G$15,6, FALSE) -> 4.4606923 | R41: =VLOOKUP($K41,$B$5:$G$15,4, FALSE)+VLOOKUP($J41,$B$5:$G$15,6, FALSE) -> -0.66065508 | U41: NOLA | V41: 22.240836 | W41: 36.566011 | X41: RFCLA | Y41: Y | Z41: RFCLA
I42: 8 | J42: SDL | K42: CHI | L42: 20 | M42: 27 | N42: =IFERROR(mean+0.5*Home_edge+VLOOKUP(J42,$B$5:$G$15,4,FALSE)+VLOOKUP(K42,$B$5:$G$15,6,FALSE),"") -> 22.620987 | O42: =IFERROR(mean-0.5*Home_edge+VLOOKUP(K42,$B$5:$G$15,4,FALSE)+VLOOKUP(J42,$B$5:$G$15,6,FALSE),"") -> 19.263544 | P42: =IFERROR((N42-L42)^2+(O42-M42)^2,"") -> 66.722326 | Q42: =VLOOKUP($J42,$B$5:$G$15,4, FALSE)+VLOOKUP($K42,$B$5:$G$15,6, FALSE) -> -1.9859366 | R42: =VLOOKUP($K42,$B$5:$G$15,4, FALSE)+VLOOKUP($J42,$B$5:$G$15,6, FALSE) -> -1.6802681 | U42: SDL | V42: 29.992504 | W42: 10.264665 | X42: MIA | Y42: Y | Z42: SDL | AE42: approx -115 each
I43: 8 | J43: NEFJ | K43: MIA | L43: 43 | M43: 6 | N43: =IFERROR(mean+0.5*Home_edge+VLOOKUP(J43,$B$5:$G$15,4,FALSE)+VLOOKUP(K43,$B$5:$G$15,6,FALSE),"") -> 24.904103 | O43: =IFERROR(mean-0.5*Home_edge+VLOOKUP(K43,$B$5:$G$15,4,FALSE)+VLOOKUP(J43,$B$5:$G$15,6,FALSE),"") -> 11.082407 | P43: =IFERROR((N43-L43)^2+(O43-M43)^2,"") -> 353.29236 | Q43: =VLOOKUP($J43,$B$5:$G$15,4, FALSE)+VLOOKUP($K43,$B$5:$G$15,6, FALSE) -> 0.29717906 | R43: =VLOOKUP($K43,$B$5:$G$15,4, FALSE)+VLOOKUP($J43,$B$5:$G$15,6, FALSE) -> -9.8614054 | U43: SEA | V43: 22.362405 | W43: 37.442734 | X43: UTAH | Y43: Y | Z43: UTAH | AE43: 10 | AG43: CHI | AH43: SDL | AI43: UTAH
I44: 9 | J44: NEFJ | K44: SDL | L44: 39 | M44: 12 | N44: =IFERROR(mean+0.5*Home_edge+VLOOKUP(J44,$B$5:$G$15,4,FALSE)+VLOOKUP(K44,$B$5:$G$15,6,FALSE),"") -> 23.61798 | O44: =IFERROR(mean-0.5*Home_edge+VLOOKUP(K44,$B$5:$G$15,4,FALSE)+VLOOKUP(J44,$B$5:$G$15,6,FALSE),"") -> 18.074038 | P44: =IFERROR((N44-L44)^2+(O44-M44)^2,"") -> 273.50047 | Q44: =VLOOKUP($J44,$B$5:$G$15,4, FALSE)+VLOOKUP($K44,$B$5:$G$15,6, FALSE) -> -0.98894329 | R44: =VLOOKUP($K44,$B$5:$G$15,4, FALSE)+VLOOKUP($J44,$B$5:$G$15,6, FALSE) -> -2.8697743 | T44: 7 | U44: NOLA | X44: CHI | Y44: Y | Z44: CHI | AC44: =Z44 -> CHI | AD44: =W44-V44 -> 0 | AE44: Y | AF44: CHI | AG44: 18.69 | AH44: 34.95 | AI44: 36.5
I45: 9 | J45: MIA | K45: HOU | L45: 31 | M45: 22 | N45: =IFERROR(mean+0.5*Home_edge+VLOOKUP(J45,$B$5:$G$15,4,FALSE)+VLOOKUP(K45,$B$5:$G$15,6,FALSE),"") -> 15.298307 | O45: =IFERROR(mean-0.5*Home_edge+VLOOKUP(K45,$B$5:$G$15,4,FALSE)+VLOOKUP(J45,$B$5:$G$15,6,FALSE),"") -> 22.608757 | P45: =IFERROR((N45-L45)^2+(O45-M45)^2,"") -> 246.91376 | Q45: =VLOOKUP($J45,$B$5:$G$15,4, FALSE)+VLOOKUP($K45,$B$5:$G$15,6, FALSE) -> -9.3086169 | R45: =VLOOKUP($K45,$B$5:$G$15,4, FALSE)+VLOOKUP($J45,$B$5:$G$15,6, FALSE) -> 1.6649452 | U45: HOU | X45: SDL | Y45: N | Z45: SDL | AC45: =Z45 -> SDL | AD45: =W45-V45 -> 0 | AE45: Y | AF45: SDL | AH45: 18.69 | AI45: 36.5
I46: 9 | J46: NOLA | K46: OGDC | L46: 51 | M46: 29 | N46: =IFERROR(mean+0.5*Home_edge+VLOOKUP(J46,$B$5:$G$15,4,FALSE)+VLOOKUP(K46,$B$5:$G$15,6,FALSE),"") -> 26.190721 | O46: =IFERROR(mean-0.5*Home_edge+VLOOKUP(K46,$B$5:$G$15,4,FALSE)+VLOOKUP(J46,$B$5:$G$15,6,FALSE),"") -> 23.283752 | P46: =IFERROR((N46-L46)^2+(O46-M46)^2,"") -> 648.17583 | Q46: =VLOOKUP($J46,$B$5:$G$15,4, FALSE)+VLOOKUP($K46,$B$5:$G$15,6, FALSE) -> 1.5837972 | R46: =VLOOKUP($K46,$B$5:$G$15,4, FALSE)+VLOOKUP($J46,$B$5:$G$15,6, FALSE) -> 2.3399404 | U46: SEA | X46: ARC | Y46: Y | Z46: SEA | AC46: =Z46 -> SEA | AD46: =V46-W46 -> 0 | AE46: N | AF46: UTAH | AI46: 19.52
I47: 9 | J47: RFCLA | K47: UTAH | L47: 28 | M47: 45 | N47: =IFERROR(mean+0.5*Home_edge+VLOOKUP(J47,$B$5:$G$15,4,FALSE)+VLOOKUP(K47,$B$5:$G$15,6,FALSE),"") -> 29.889049 | O47: =IFERROR(mean-0.5*Home_edge+VLOOKUP(K47,$B$5:$G$15,4,FALSE)+VLOOKUP(J47,$B$5:$G$15,6,FALSE),"") -> 30.163908 | P47: =IFERROR((N47-L47)^2+(O47-M47)^2,"") -> 223.67813 | Q47: =VLOOKUP($J47,$B$5:$G$15,4, FALSE)+VLOOKUP($K47,$B$5:$G$15,6, FALSE) -> 5.2821255 | R47: =VLOOKUP($K47,$B$5:$G$15,4, FALSE)+VLOOKUP($J47,$B$5:$G$15,6, FALSE) -> 9.220096 | U47: UTAH | X47: NEFJ | Y47: N | Z47: UTAH | AC47: =Z47 -> UTAH | AD47: =V47-W47 -> 0 | AE47: Y | AF47: All 3: | AG47: 68.24
I48: 9 | J48: CHI | K48: ARC | L48: 28 | M48: 20 | N48: =IFERROR(mean+0.5*Home_edge+VLOOKUP(J48,$B$5:$G$15,4,FALSE)+VLOOKUP(K48,$B$5:$G$15,6,FALSE),"") -> 35.863674 | O48: =IFERROR(mean-0.5*Home_edge+VLOOKUP(K48,$B$5:$G$15,4,FALSE)+VLOOKUP(J48,$B$5:$G$15,6,FALSE),"") -> 11.910727 | P48: =IFERROR((N48-L48)^2+(O48-M48)^2,"") -> 127.27371 | Q48: =VLOOKUP($J48,$B$5:$G$15,4, FALSE)+VLOOKUP($K48,$B$5:$G$15,6, FALSE) -> 11.256751 | R48: =VLOOKUP($K48,$B$5:$G$15,4, FALSE)+VLOOKUP($J48,$B$5:$G$15,6, FALSE) -> -9.0330853 | U48: RFCLA | X48: OGDC | Y48: N | Z48: OGDC | AC48: =Z48 -> OGDC | AD48: =W48-V48 -> 0 | AE48: N
I49: 10 | J49: ARC | K49: NEFJ | L49: 6 | M49: 26 | N49: =IFERROR(mean+0.5*Home_edge+VLOOKUP(J49,$B$5:$G$15,4,FALSE)+VLOOKUP(K49,$B$5:$G$15,6,FALSE),"") -> 14.69 | O49: =IFERROR(mean-0.5*Home_edge+VLOOKUP(K49,$B$5:$G$15,4,FALSE)+VLOOKUP(J49,$B$5:$G$15,6,FALSE),"") -> 32.891887 | P49: =IFERROR((N49-L49)^2+(O49-M49)^2,"") -> 123.01422 | Q49: =VLOOKUP($J49,$B$5:$G$15,4, FALSE)+VLOOKUP($K49,$B$5:$G$15,6, FALSE) -> -9.9169231 | R49: =VLOOKUP($K49,$B$5:$G$15,4, FALSE)+VLOOKUP($J49,$B$5:$G$15,6, FALSE) -> 11.948075 | T49: 8 | U49: OGDC | V49: 19.361879 | W49: 21.151828 | X49: SEA | Y49: N | Z49: SEA | AC49: =Z49 -> SEA | AD49: =W49-V49 -> 1.7899492 | AH49: Profit
I50: 10 | J50: SEA | K50: CHI | L50: 28 | M50: 22 | N50: =IFERROR(mean+0.5*Home_edge+VLOOKUP(J50,$B$5:$G$15,4,FALSE)+VLOOKUP(K50,$B$5:$G$15,6,FALSE),"") -> 20.450399 | O50: =IFERROR(mean-0.5*Home_edge+VLOOKUP(K50,$B$5:$G$15,4,FALSE)+VLOOKUP(J50,$B$5:$G$15,6,FALSE),"") -> 18.176768 | P50: =IFERROR((N50-L50)^2+(O50-M50)^2,"") -> 71.613577 | Q50: =VLOOKUP($J50,$B$5:$G$15,4, FALSE)+VLOOKUP($K50,$B$5:$G$15,6, FALSE) -> -4.1565242 | R50: =VLOOKUP($K50,$B$5:$G$15,4, FALSE)+VLOOKUP($J50,$B$5:$G$15,6, FALSE) -> -2.7670443 | U50: ARC | V50: 26.718213 | W50: 31.423607 | X50: NOLA | Y50: Y | Z50: NOLA | AC50: NOLA | AD50: =W50-V50 -> 4.7053943 | AH50: -$70 in | AI50: chance
I51: 10 | J51: OGDC | K51: MIA | L51: 35 | M51: 37 | N51: =IFERROR(mean+0.5*Home_edge+VLOOKUP(J51,$B$5:$G$15,4,FALSE)+VLOOKUP(K51,$B$5:$G$15,6,FALSE),"") -> 25.003553 | O51: =IFERROR(mean-0.5*Home_edge+VLOOKUP(K51,$B$5:$G$15,4,FALSE)+VLOOKUP(J51,$B$5:$G$15,6,FALSE),"") -> 19.51452 | P51: =IFERROR((N51-L51)^2+(O51-M51)^2,"") -> 405.67095 | Q51: =VLOOKUP($J51,$B$5:$G$15,4, FALSE)+VLOOKUP($K51,$B$5:$G$15,6, FALSE) -> 0.39662954 | R51: =VLOOKUP($K51,$B$5:$G$15,4, FALSE)+VLOOKUP($J51,$B$5:$G$15,6, FALSE) -> -1.4292917 | U51: HOU | V51: 36.619311 | W51: 24.032409 | X51: RFCLA | Y51: N | Z51: HOU | AC51: HOU | AD51: =V51-W51 -> 12.586903 | AG51: All 3 hit | AH51: =SUM(AG44:AI47)-70 -> 163.09 | AI51: =1/8 -> 0.125 | AJ51: =AI51*AH51 -> 20.38625
I52: 10 | J52: HOU | K52: NOLA | L52: 17 | M52: 15 | N52: =IFERROR(mean+0.5*Home_edge+VLOOKUP(J52,$B$5:$G$15,4,FALSE)+VLOOKUP(K52,$B$5:$G$15,6,FALSE),"") -> 28.21518 | O52: =IFERROR(mean-0.5*Home_edge+VLOOKUP(K52,$B$5:$G$15,4,FALSE)+VLOOKUP(J52,$B$5:$G$15,6,FALSE),"") -> 14.648284 | P52: =IFERROR((N52-L52)^2+(O52-M52)^2,"") -> 125.90396 | Q52: =VLOOKUP($J52,$B$5:$G$15,4, FALSE)+VLOOKUP($K52,$B$5:$G$15,6, FALSE) -> 3.6082561 | R52: =VLOOKUP($K52,$B$5:$G$15,4, FALSE)+VLOOKUP($J52,$B$5:$G$15,6, FALSE) -> -6.295528 | U52: SDL | V52: 21.818199 | W52: 14.60621 | X52: CHI | Y52: N | Z52: SDL | AC52: SDL | AD52: =V52-W52 -> 7.2119893 | AG52: CHI Lose | AH52: =SUM(AF45:AI46)-70 -> 4.71 | AI52: =1/8 -> 0.125 | AJ52: =AI52*AH52 -> 0.58875
H53: Pick: | I53: 10 | J53: SDL | K53: UTAH | L53: 18 | M53: 31 | N53: =IFERROR(mean+0.5*Home_edge+VLOOKUP(J53,$B$5:$G$15,4,FALSE)+VLOOKUP(K53,$B$5:$G$15,6,FALSE),"") -> 28.232718 | O53: =IFERROR(mean-0.5*Home_edge+VLOOKUP(K53,$B$5:$G$15,4,FALSE)+VLOOKUP(J53,$B$5:$G$15,6,FALSE),"") -> 26.082039 | P53: =IFERROR((N53-L53)^2+(O53-M53)^2,"") -> 128.89487 | Q53: =VLOOKUP($J53,$B$5:$G$15,4, FALSE)+VLOOKUP($K53,$B$5:$G$15,6, FALSE) -> 3.6257947 | R53: =VLOOKUP($K53,$B$5:$G$15,4, FALSE)+VLOOKUP($J53,$B$5:$G$15,6, FALSE) -> 5.1382266 | U53: NEFJ | V53: 20.357214 | W53: 15.547893 | X53: MIA | Y53: Y | Z53: NEFJ | AA53: TFR | AC53: NEFJ | AD53: =V53-W53 -> 4.8093219 | AG53: SDL Lose | AH53: =SUM(AG44,AI44,AI46,AI46)-70 -> 24.23 | AI53: =1/8 -> 0.125 | AJ53: =AI53*AH53 -> 3.02875
G54: Y | H54: SEA | I54: 11 | J54: HOU | K54: OGDC | L54: 48 | M54: 27 | N54: =IFERROR(mean+0.5*Home_edge+VLOOKUP(J54,$B$5:$G$15,4,FALSE)+VLOOKUP(K54,$B$5:$G$15,6,FALSE),"") -> 28.073483 | O54: =IFERROR(mean-0.5*Home_edge+VLOOKUP(K54,$B$5:$G$15,4,FALSE)+VLOOKUP(J54,$B$5:$G$15,6,FALSE),"") -> 15.262731 | P54: =IFERROR((N54-L54)^2+(O54-M54)^2,"") -> 534.82956 | Q54: =VLOOKUP($J54,$B$5:$G$15,4, FALSE)+VLOOKUP($K54,$B$5:$G$15,6, FALSE) -> 3.4665597 | R54: =VLOOKUP($K54,$B$5:$G$15,4, FALSE)+VLOOKUP($J54,$B$5:$G$15,6, FALSE) -> -5.6810812 | T54: 9 | U54: NEFJ | V54: 15.403744 | W54: 21.02248 | X54: SDL | Y54: N | Z54: SDL | AA54: SDL | AG54: UTAH Lose | AH54: =SUM(AG44:AH45)-70 -> 2.33 | AI54: =1/8 -> 0.125 | AJ54: =AI54*AH54 -> 0.29125
G55: N | H55: MIA | I55: 11 | J55: UTAH | K55: CHI | L55: 41 | M55: 31 | N55: =IFERROR(mean+0.5*Home_edge+VLOOKUP(J55,$B$5:$G$15,4,FALSE)+VLOOKUP(K55,$B$5:$G$15,6,FALSE),"") -> 25.284611 | O55: =IFERROR(mean-0.5*Home_edge+VLOOKUP(K55,$B$5:$G$15,4,FALSE)+VLOOKUP(J55,$B$5:$G$15,6,FALSE),"") -> 20.414736 | P55: =IFERROR((N55-L55)^2+(O55-M55)^2,"") -> 359.02127 | Q55: =VLOOKUP($J55,$B$5:$G$15,4, FALSE)+VLOOKUP($K55,$B$5:$G$15,6, FALSE) -> 0.67768749 | R55: =VLOOKUP($K55,$B$5:$G$15,4, FALSE)+VLOOKUP($J55,$B$5:$G$15,6, FALSE) -> -0.52907599 | U55: MIA | V55: 11.928218 | W55: 30.525517 | X55: HOU | Y55: N | Z55: HOU | AA55: HOU | AG55: CHI/SDL | AH55: =AI46-70 -> -50.48 | AI55: =1/8 -> 0.125 | AJ55: =AI55*AH55 -> -6.31
G56: Y | H56: HOU | I56: 11 | J56: RFCLA | K56: SDL | L56: 36 | M56: 38 | N56: =IFERROR(mean+0.5*Home_edge+VLOOKUP(J56,$B$5:$G$15,4,FALSE)+VLOOKUP(K56,$B$5:$G$15,6,FALSE),"") -> 28.737857 | O56: =IFERROR(mean-0.5*Home_edge+VLOOKUP(K56,$B$5:$G$15,4,FALSE)+VLOOKUP(J56,$B$5:$G$15,6,FALSE),"") -> 27.500284 | P56: =IFERROR((N56-L56)^2+(O56-M56)^2,"") -> 162.98276 | Q56: =VLOOKUP($J56,$B$5:$G$15,4, FALSE)+VLOOKUP($K56,$B$5:$G$15,6, FALSE) -> 4.1309334 | R56: =VLOOKUP($K56,$B$5:$G$15,4, FALSE)+VLOOKUP($J56,$B$5:$G$15,6, FALSE) -> 6.556472 | U56: NOLA | V56: 19.025198 | W56: 22.049805 | X56: OGDC | Y56: N | Z56: OGDC | AA56: OGDC | AG56: CHI/UTAH | AH56: =AH45-70 -> -51.31 | AI56: =1/8 -> 0.125 | AJ56: =AI56*AH56 -> -6.41375
G57: N | H57: NEFJ | I57: 11 | J57: NOLA | K57: SEA | L57: 44 | M57: 36 | N57: =IFERROR(mean+0.5*Home_edge+VLOOKUP(J57,$B$5:$G$15,4,FALSE)+VLOOKUP(K57,$B$5:$G$15,6,FALSE),"") -> 22.016208 | O57: =IFERROR(mean-0.5*Home_edge+VLOOKUP(K57,$B$5:$G$15,4,FALSE)+VLOOKUP(J57,$B$5:$G$15,6,FALSE),"") -> 24.47726 | P57: =IFERROR((N57-L57)^2+(O57-M57)^2,"") -> 616.06066 | Q57: =VLOOKUP($J57,$B$5:$G$15,4, FALSE)+VLOOKUP($K57,$B$5:$G$15,6, FALSE) -> -2.5907157 | R57: =VLOOKUP($K57,$B$5:$G$15,4, FALSE)+VLOOKUP($J57,$B$5:$G$15,6, FALSE) -> 3.533448 | U57: RFCLA | V57: 33.058372 | W57: 36.250196 | X57: UTAH | Y57: Y | Z57: UTAH | AA57: RFCLA | AG57: SDL/UTAH | AH57: =AG44-70 -> -51.31 | AI57: =1/8 -> 0.125 | AJ57: =AI57*AH57 -> -6.41375
G58: N | H58: DAL | I58: 11 | J58: MIA | K58: ARC | L58: 31 | M58: 5 | N58: =IFERROR(mean+0.5*Home_edge+VLOOKUP(J58,$B$5:$G$15,4,FALSE)+VLOOKUP(K58,$B$5:$G$15,6,FALSE),"") -> 33.026914 | O58: =IFERROR(mean-0.5*Home_edge+VLOOKUP(K58,$B$5:$G$15,4,FALSE)+VLOOKUP(J58,$B$5:$G$15,6,FALSE),"") -> 17.657388 | P58: =IFERROR((N58-L58)^2+(O58-M58)^2,"") -> 164.31785 | Q58: =VLOOKUP($J58,$B$5:$G$15,4, FALSE)+VLOOKUP($K58,$B$5:$G$15,6, FALSE) -> 8.4199902 | R58: =VLOOKUP($K58,$B$5:$G$15,4, FALSE)+VLOOKUP($J58,$B$5:$G$15,6, FALSE) -> -3.2864238 | U58: CHI | V58: 41.673375 | W58: 16.926549 | X58: ARC | Y58: Y | Z58: CHI | AA58: CHI | AG58: All 3 lose | AH58: -70 | AI58: =1/8 -> 0.125 | AJ58: =AI58*AH58 -> -8.75
G59: Y | H59: HOU | I59: 12 | J59: SEA | K59: RFCLA | L59: 26 | M59: 26 | N59: =IFERROR(mean+0.5*Home_edge+VLOOKUP(J59,$B$5:$G$15,4,FALSE)+VLOOKUP(K59,$B$5:$G$15,6,FALSE),"") -> 28.992808 | O59: =IFERROR(mean-0.5*Home_edge+VLOOKUP(K59,$B$5:$G$15,4,FALSE)+VLOOKUP(J59,$B$5:$G$15,6,FALSE),"") -> 23.987969 | P59: =IFERROR((N59-L59)^2+(O59-M59)^2,"") -> 13.005167 | Q59: =VLOOKUP($J59,$B$5:$G$15,4, FALSE)+VLOOKUP($K59,$B$5:$G$15,6, FALSE) -> 4.3858843 | R59: =VLOOKUP($K59,$B$5:$G$15,4, FALSE)+VLOOKUP($J59,$B$5:$G$15,6, FALSE) -> 3.0441572 | T59: 10 | U59: ARC | V59: 18.977493 | W59: 34.686162 | X59: NEFJ | Y59: Y | Z59: NEFJ | AA59: ARC | AB59: 12.5 | AC59: anything more than 10 to cover | AH59: =SUM(AH51:AH58) -> -28.74 | AJ59: =SUM(AJ51:AJ58) -> -3.5925
G60: N | H60: DAL | I60: 12 | J60: OGDC | K60: UTAH | L60: 28 | M60: 12 | N60: =IFERROR(mean+0.5*Home_edge+VLOOKUP(J60,$B$5:$G$15,4,FALSE)+VLOOKUP(K60,$B$5:$G$15,6,FALSE),"") -> 24.868623 | O60: =IFERROR(mean-0.5*Home_edge+VLOOKUP(K60,$B$5:$G$15,4,FALSE)+VLOOKUP(J60,$B$5:$G$15,6,FALSE),"") -> 29.169775 | P60: =IFERROR((N60-L60)^2+(O60-M60)^2,"") -> 304.60671 | Q60: =VLOOKUP($J60,$B$5:$G$15,4, FALSE)+VLOOKUP($K60,$B$5:$G$15,6, FALSE) -> 0.2616993 | R60: =VLOOKUP($K60,$B$5:$G$15,4, FALSE)+VLOOKUP($J60,$B$5:$G$15,6, FALSE) -> 8.2259634 | U60: SEA | V60: 13.235731 | W60: 19.229836 | X60: CHI | Y60: N | Z60: CHI | AA60: CHI | AB60: -10.5
B61: 2024 info: | G61: N | H61: SEA | I61: 12 | J61: NEFJ | K61: HOU | L61: 36 | M61: 17 | N61: =IFERROR(mean+0.5*Home_edge+VLOOKUP(J61,$B$5:$G$15,4,FALSE)+VLOOKUP(K61,$B$5:$G$15,6,FALSE),"") -> 18.826392 | O61: =IFERROR(mean-0.5*Home_edge+VLOOKUP(K61,$B$5:$G$15,4,FALSE)+VLOOKUP(J61,$B$5:$G$15,6,FALSE),"") -> 15.978258 | P61: =IFERROR((N61-L61)^2+(O61-M61)^2,"") -> 295.97678 | Q61: =VLOOKUP($J61,$B$5:$G$15,4, FALSE)+VLOOKUP($K61,$B$5:$G$15,6, FALSE) -> -5.7805317 | R61: =VLOOKUP($K61,$B$5:$G$15,4, FALSE)+VLOOKUP($J61,$B$5:$G$15,6, FALSE) -> -4.965554 | U61: OGDC | V61: 27.513882 | W61: 19.098077 | X61: MIA | Y61: N | Z61: OGDC | AA61: OGDC | AB61: -2.5
G62: N | H62: CHI | I62: 12 | J62: CHI | K62: MIA | L62: 14 | M62: 7 | N62: =IFERROR(mean+0.5*Home_edge+VLOOKUP(J62,$B$5:$G$15,4,FALSE)+VLOOKUP(K62,$B$5:$G$15,6,FALSE),"") -> 24.212778 | O62: =IFERROR(mean-0.5*Home_edge+VLOOKUP(K62,$B$5:$G$15,4,FALSE)+VLOOKUP(J62,$B$5:$G$15,6,FALSE),"") -> 11.966244 | P62: =IFERROR((N62-L62)^2+(O62-M62)^2,"") -> 128.96441 | Q62: =VLOOKUP($J62,$B$5:$G$15,4, FALSE)+VLOOKUP($K62,$B$5:$G$15,6, FALSE) -> -0.39414576 | R62: =VLOOKUP($K62,$B$5:$G$15,4, FALSE)+VLOOKUP($J62,$B$5:$G$15,6, FALSE) -> -8.9775676 | U62: HOU | V62: 27.689538 | W62: 17.658492 | X62: NOLA | Y62: Y | Z62: HOU | AA62: HOU | AB62: -7.5
G63: N | H63: UTA | I63: 12 | J63: SDL | K63: NOLA | L63: 45 | M63: 36 | N63: =IFERROR(mean+0.5*Home_edge+VLOOKUP(J63,$B$5:$G$15,4,FALSE)+VLOOKUP(K63,$B$5:$G$15,6,FALSE),"") -> 30.310959 | O63: =IFERROR(mean-0.5*Home_edge+VLOOKUP(K63,$B$5:$G$15,4,FALSE)+VLOOKUP(J63,$B$5:$G$15,6,FALSE),"") -> 19.439872 | P63: =IFERROR((N63-L63)^2+(O63-M63)^2,"") -> 490.00574 | Q63: =VLOOKUP($J63,$B$5:$G$15,4, FALSE)+VLOOKUP($K63,$B$5:$G$15,6, FALSE) -> 5.7040357 | R63: =VLOOKUP($K63,$B$5:$G$15,4, FALSE)+VLOOKUP($J63,$B$5:$G$15,6, FALSE) -> -1.5039396 | U63: SDL | V63: 25.525038 | W63: 26.596551 | X63: UTAH | Y63: Y | Z63: UTAH | AA63: UTAH | AB63: -2.5 | AC63: ML Underdog
B64: 45430 | C64: ARC | D64: 19.210025 | E64: 38.121256 | F64: RFCLA | G64: Y | H64: RFCLA | I64: 13 | J64: NOLA | K64: MIA | L64: 19 | M64: 25 | N64: =IFERROR(mean+0.5*Home_edge+VLOOKUP(J64,$B$5:$G$15,4,FALSE)+VLOOKUP(K64,$B$5:$G$15,6,FALSE),"") -> 24.389106 | O64: =IFERROR(mean-0.5*Home_edge+VLOOKUP(K64,$B$5:$G$15,4,FALSE)+VLOOKUP(J64,$B$5:$G$15,6,FALSE),"") -> 19.656217 | P64: =IFERROR((N64-L64)^2+(O64-M64)^2,"") -> 57.598487 | Q64: =VLOOKUP($J64,$B$5:$G$15,4, FALSE)+VLOOKUP($K64,$B$5:$G$15,6, FALSE) -> -0.21781721 | R64: =VLOOKUP($K64,$B$5:$G$15,4, FALSE)+VLOOKUP($J64,$B$5:$G$15,6, FALSE) -> -1.2875953 | T64: midweek | Z64: SEA
B65: 45430 | C65: NOLA | D65: 18.02018 | E65: 21.293058 | F65: UTA | G65: N | H65: UTA | I65: 13 | J65: NEFJ | K65: CHI | L65: 27 | M65: 17 | N65: =IFERROR(mean+0.5*Home_edge+VLOOKUP(J65,$B$5:$G$15,4,FALSE)+VLOOKUP(K65,$B$5:$G$15,6,FALSE),"") -> 19.157441 | O65: =IFERROR(mean-0.5*Home_edge+VLOOKUP(K65,$B$5:$G$15,4,FALSE)+VLOOKUP(J65,$B$5:$G$15,6,FALSE),"") -> 13.919167 | P65: =IFERROR((N65-L65)^2+(O65-M65)^2,"") -> 70.997263 | Q65: =VLOOKUP($J65,$B$5:$G$15,4, FALSE)+VLOOKUP($K65,$B$5:$G$15,6, FALSE) -> -5.4494824 | R65: =VLOOKUP($K65,$B$5:$G$15,4, FALSE)+VLOOKUP($J65,$B$5:$G$15,6, FALSE) -> -7.024645 | T65: midweek | Z65: NEFJ | AA65: TFR | AB65: TFR_line
B66: 45430 | C66: HOU | D66: 27.5992 | E66: 23.739508 | F66: CHI | G66: Y | H66: HOU | I66: 13 | J66: SDL | K66: HOU | L66: 20 | M66: 37 | N66: =IFERROR(mean+0.5*Home_edge+VLOOKUP(J66,$B$5:$G$15,4,FALSE)+VLOOKUP(K66,$B$5:$G$15,6,FALSE),"") -> 22.289938 | O66: =IFERROR(mean-0.5*Home_edge+VLOOKUP(K66,$B$5:$G$15,4,FALSE)+VLOOKUP(J66,$B$5:$G$15,6,FALSE),"") -> 21.322635 | P66: =IFERROR((N66-L66)^2+(O66-M66)^2,"") -> 251.02359 | Q66: =VLOOKUP($J66,$B$5:$G$15,4, FALSE)+VLOOKUP($K66,$B$5:$G$15,6, FALSE) -> -2.3169859 | R66: =VLOOKUP($K66,$B$5:$G$15,4, FALSE)+VLOOKUP($J66,$B$5:$G$15,6, FALSE) -> 0.3788229 | T66: 11 | U66: HOU | V66: 30.163105 | W66: 18.495862 | X66: OGDC | Y66: Y | Z66: HOU | AA66: HOU | AB66: -6.5 | AC66: OGDC +10.5 or HOU -
B67: 45431 | C67: SD | D67: 14.192521 | E67: 22.516074 | F67: NEFJ | G67: Y | H67: NEFJ | I67: 13 | J67: RFCLA | K67: ARC | L67: 45 | M67: 17 | N67: =IFERROR(mean+0.5*Home_edge+VLOOKUP(J67,$B$5:$G$15,4,FALSE)+VLOOKUP(K67,$B$5:$G$15,6,FALSE),"") -> 41.674876 | O67: =IFERROR(mean-0.5*Home_edge+VLOOKUP(K67,$B$5:$G$15,4,FALSE)+VLOOKUP(J67,$B$5:$G$15,6,FALSE),"") -> 20.453135 | P67: =IFERROR((N67-L67)^2+(O67-M67)^2,"") -> 22.980596 | Q67: =VLOOKUP($J67,$B$5:$G$15,4, FALSE)+VLOOKUP($K67,$B$5:$G$15,6, FALSE) -> 17.067952 | R67: =VLOOKUP($K67,$B$5:$G$15,4, FALSE)+VLOOKUP($J67,$B$5:$G$15,6, FALSE) -> -0.49067674 | U67: UTAH | V67: 29.710182 | W67: 21.134337 | X67: CHI | Y67: Y | Z67: UTAH | AA67: CHI | AB67: UTAH | AC67: ML UTAH underdog
B68: 45431 | C68: DAL | D68: 23.074514 | E68: 31.1127 | F68: SEA | G68: N | H68: SEA | I68: 13 | J68: UTAH | K68: SEA | L68: 24 | M68: 28 | N68: =IFERROR(mean+0.5*Home_edge+VLOOKUP(J68,$B$5:$G$15,4,FALSE)+VLOOKUP(K68,$B$5:$G$15,6,FALSE),"") -> 28.658374 | O68: =IFERROR(mean-0.5*Home_edge+VLOOKUP(K68,$B$5:$G$15,4,FALSE)+VLOOKUP(J68,$B$5:$G$15,6,FALSE),"") -> 22.399019 | P68: =IFERROR((N68-L68)^2+(O68-M68)^2,"") -> 53.071436 | Q68: =VLOOKUP($J68,$B$5:$G$15,4, FALSE)+VLOOKUP($K68,$B$5:$G$15,6, FALSE) -> 4.0514504 | R68: =VLOOKUP($K68,$B$5:$G$15,4, FALSE)+VLOOKUP($J68,$B$5:$G$15,6, FALSE) -> 1.455207 | U68: RFCLA | V68: 24.938711 | W68: 26.465435 | X68: SDL | Y68: Y | Z68: SDL | AA68: RFCLA | AB68: -5.5 | AC68: if RFCLA underdog hammer | AD68: RFCLA ML
B69: 45436 | C69: SEA | D69: 24.176519 | E69: 13.646507 | F69: OGDC | G69: Y | H69: SEA | I69: 14 | J69: MIA | K69: NEFJ | L69: 30 | M69: 19 | N69: =IFERROR(mean+0.5*Home_edge+VLOOKUP(J69,$B$5:$G$15,4,FALSE)+VLOOKUP(K69,$B$5:$G$15,6,FALSE),"") -> 14.745518 | O69: =IFERROR(mean-0.5*Home_edge+VLOOKUP(K69,$B$5:$G$15,4,FALSE)+VLOOKUP(J69,$B$5:$G$15,6,FALSE),"") -> 21.240991 | P69: =IFERROR((N69-L69)^2+(O69-M69)^2,"") -> 237.72126 | Q69: =VLOOKUP($J69,$B$5:$G$15,4, FALSE)+VLOOKUP($K69,$B$5:$G$15,6, FALSE) -> -9.8614054 | R69: =VLOOKUP($K69,$B$5:$G$15,4, FALSE)+VLOOKUP($J69,$B$5:$G$15,6, FALSE) -> 0.29717906 | U69: NOLA | V69: 21.444164 | W69: 17.409531 | X69: SEA | Y69: Y | Z69: NOLA | AA69: NOLA | AB69: -1.5 | AC69: SEA ML
B70: 45437 | C70: MIA | D70: 14.164246 | E70: 24.611394 | F70: NEFJ | G70: N | H70: NEFJ | I70: 14 | J70: HOU | K70: UTAH | L70: 40 | M70: 19 | N70: =IFERROR(mean+0.5*Home_edge+VLOOKUP(J70,$B$5:$G$15,4,FALSE)+VLOOKUP(K70,$B$5:$G$15,6,FALSE),"") -> 26.136938 | O70: =IFERROR(mean-0.5*Home_edge+VLOOKUP(K70,$B$5:$G$15,4,FALSE)+VLOOKUP(J70,$B$5:$G$15,6,FALSE),"") -> 21.29045 | P70: =IFERROR((N70-L70)^2+(O70-M70)^2,"") -> 197.43064 | Q70: =VLOOKUP($J70,$B$5:$G$15,4, FALSE)+VLOOKUP($K70,$B$5:$G$15,6, FALSE) -> 1.530015 | R70: =VLOOKUP($K70,$B$5:$G$15,4, FALSE)+VLOOKUP($J70,$B$5:$G$15,6, FALSE) -> 0.34663817 | U70: MIA | V70: 32.750475 | W70: 23.526674 | X70: ARC | Y70: Y | Z70: MIA | AA70: MIA | AB70: -13.5 | AC70: ARC cover
B71: 45438 | C71: CHI | D71: 24.413924 | E71: 21.591112 | F71: NOLA | G71: N | H71: CHI | I71: 14 | J71: SEA | K71: SDL | L71: 29 | M71: 25 | N71: =IFERROR(mean+0.5*Home_edge+VLOOKUP(J71,$B$5:$G$15,4,FALSE)+VLOOKUP(K71,$B$5:$G$15,6,FALSE),"") -> 24.910938 | O71: =IFERROR(mean-0.5*Home_edge+VLOOKUP(K71,$B$5:$G$15,4,FALSE)+VLOOKUP(J71,$B$5:$G$15,6,FALSE),"") -> 22.331638 | P71: =IFERROR((N71-L71)^2+(O71-M71)^2,"") -> 23.840579 | Q71: =VLOOKUP($J71,$B$5:$G$15,4, FALSE)+VLOOKUP($K71,$B$5:$G$15,6, FALSE) -> 0.30401487 | R71: =VLOOKUP($K71,$B$5:$G$15,4, FALSE)+VLOOKUP($J71,$B$5:$G$15,6, FALSE) -> 1.3878264 | T71: 12 | U71: SEA | V71: 27.35079 | W71: 25.07222 | X71: RFCLA | Y71: T | Z71: SEA | AA71: RFCLA
A72: Week | B72: 45438 | C72: RFCLA | D72: 15.595287 | E72: 25.731789 | F72: SD | G72: Y | H72: SD | I72: 14 | J72: ARC | K72: OGDC | L72: 19 | M72: 41 | N72: =IFERROR(mean+0.5*Home_edge+VLOOKUP(J72,$B$5:$G$15,4,FALSE)+VLOOKUP(K72,$B$5:$G$15,6,FALSE),"") -> 23.122114 | O72: =IFERROR(mean-0.5*Home_edge+VLOOKUP(K72,$B$5:$G$15,4,FALSE)+VLOOKUP(J72,$B$5:$G$15,6,FALSE),"") -> 32.991338 | P72: =IFERROR((N72-L72)^2+(O72-M72)^2,"") -> 81.130494 | Q72: =VLOOKUP($J72,$B$5:$G$15,4, FALSE)+VLOOKUP($K72,$B$5:$G$15,6, FALSE) -> -1.4848094 | R72: =VLOOKUP($K72,$B$5:$G$15,4, FALSE)+VLOOKUP($J72,$B$5:$G$15,6, FALSE) -> 12.047526 | U72: OGDC | V72: 24.512272 | W72: 37.066081 | X72: UTAH | Y72: N | Z72: UTAH | AA72: UTAH
A73: 14 | B73: 45444 | C73: OGDC | D73: 36.856917 | E73: 18.849681 | F73: ARC | G73: Y | H73: OGDC | I73: 14 | J73: CHI | K73: RFCLA | L73: 24 | M73: 26 | N73: =IFERROR(mean+0.5*Home_edge+VLOOKUP(J73,$B$5:$G$15,4,FALSE)+VLOOKUP(K73,$B$5:$G$15,6,FALSE),"") -> 27.008525 | O73: =IFERROR(mean-0.5*Home_edge+VLOOKUP(K73,$B$5:$G$15,4,FALSE)+VLOOKUP(J73,$B$5:$G$15,6,FALSE),"") -> 20.614206 | P73: =IFERROR((N73-L73)^2+(O73-M73)^2,"") -> 38.057996 | Q73: =VLOOKUP($J73,$B$5:$G$15,4, FALSE)+VLOOKUP($K73,$B$5:$G$15,6, FALSE) -> 2.4016013 | R73: =VLOOKUP($K73,$B$5:$G$15,4, FALSE)+VLOOKUP($J73,$B$5:$G$15,6, FALSE) -> -0.32960577 | U73: NEFJ | V73: 18.98752 | W73: 14.256853 | X73: HOU | Y73: Y | Z73: NEFJ | AA73: NEFJ
A74: 14 | B74: 45444 | C74: NOLA | D74: 18.114328 | E74: 25.857452 | F74: HOU | G74: Y | H74: HOU | I74: 15 | J74: RFCLA | K74: MIA | L74: 26 | M74: 20 | N74: =IFERROR(mean+0.5*Home_edge+VLOOKUP(J74,$B$5:$G$15,4,FALSE)+VLOOKUP(K74,$B$5:$G$15,6,FALSE),"") -> 30.023979 | O74: =IFERROR(mean-0.5*Home_edge+VLOOKUP(K74,$B$5:$G$15,4,FALSE)+VLOOKUP(J74,$B$5:$G$15,6,FALSE),"") -> 20.508653 | P74: =IFERROR((N74-L74)^2+(O74-M74)^2,"") -> 16.451136 | Q74: =VLOOKUP($J74,$B$5:$G$15,4, FALSE)+VLOOKUP($K74,$B$5:$G$15,6, FALSE) -> 5.4170557 | R74: =VLOOKUP($K74,$B$5:$G$15,4, FALSE)+VLOOKUP($J74,$B$5:$G$15,6, FALSE) -> -0.43515904 | U74: CHI | V74: 26.353301 | W74: 11.508091 | X74: MIA | Y74: Y | Z74: CHI | AA74: MIA
A75: 14 | B75: 45444 | C75: UTA | D75: 18.136691 | E75: 20.035572 | F75: SD | G75: Y | H75: SD | I75: 15 | J75: SEA | K75: HOU | L75: 14 | M75: 9 | N75: =IFERROR(mean+0.5*Home_edge+VLOOKUP(J75,$B$5:$G$15,4,FALSE)+VLOOKUP(K75,$B$5:$G$15,6,FALSE),"") -> 20.11935 | O75: =IFERROR(mean-0.5*Home_edge+VLOOKUP(K75,$B$5:$G$15,4,FALSE)+VLOOKUP(J75,$B$5:$G$15,6,FALSE),"") -> 20.235859 | P75: =IFERROR((N75-L75)^2+(O75-M75)^2,"") -> 163.69096 | Q75: =VLOOKUP($J75,$B$5:$G$15,4, FALSE)+VLOOKUP($K75,$B$5:$G$15,6, FALSE) -> -4.4875736 | R75: =VLOOKUP($K75,$B$5:$G$15,4, FALSE)+VLOOKUP($J75,$B$5:$G$15,6, FALSE) -> -0.70795328 | U75: SDL | V75: 25.188748 | W75: 17.457803 | X75: NOLA | Y75: Y | Z75: SDL | AA75: SDL | AB75: TFR_pick | AC75: TFR_line
A76: 14 | B76: 45445 | C76: NEFJ | D76: 26.120133 | E76: 23.064289 | F76: DAL | G76: Y | H76: NEFJ | I76: 15 | J76: NEFJ | K76: OGDC | L76: 17 | M76: 20 | N76: =IFERROR(mean+0.5*Home_edge+VLOOKUP(J76,$B$5:$G$15,4,FALSE)+VLOOKUP(K76,$B$5:$G$15,6,FALSE),"") -> 26.705717 | O76: =IFERROR(mean-0.5*Home_edge+VLOOKUP(K76,$B$5:$G$15,4,FALSE)+VLOOKUP(J76,$B$5:$G$15,6,FALSE),"") -> 14.709942 | P76: =IFERROR((N76-L76)^2+(O76-M76)^2,"") -> 122.18565 | Q76: =VLOOKUP($J76,$B$5:$G$15,4, FALSE)+VLOOKUP($K76,$B$5:$G$15,6, FALSE) -> 2.0987935 | R76: =VLOOKUP($K76,$B$5:$G$15,4, FALSE)+VLOOKUP($J76,$B$5:$G$15,6, FALSE) -> -6.2338697 | T76: 13 | U76: NOLA | V76: 26.216777 | W76: 16.886499 | X76: MIA | Y76: N | Z76: NOLA | AA76: =V76-W76 -> 9.3302776 | AB76: NOLA | AC76: -5.5
A77: 14 | B77: 45445 | C77: RFCLA | D77: 16.071638 | E77: 23.289605 | F77: MIA | G77: N | H77: MIA | I77: 15 | J77: NOLA | K77: UTAH | L77: 28 | M77: 31 | N77: =IFERROR(mean+0.5*Home_edge+VLOOKUP(J77,$B$5:$G$15,4,FALSE)+VLOOKUP(K77,$B$5:$G$15,6,FALSE),"") -> 24.254176 | O77: =IFERROR(mean-0.5*Home_edge+VLOOKUP(K77,$B$5:$G$15,4,FALSE)+VLOOKUP(J77,$B$5:$G$15,6,FALSE),"") -> 29.311472 | P77: =IFERROR((N77-L77)^2+(O77-M77)^2,"") -> 16.882325 | Q77: =VLOOKUP($J77,$B$5:$G$15,4, FALSE)+VLOOKUP($K77,$B$5:$G$15,6, FALSE) -> -0.35274745 | R77: =VLOOKUP($K77,$B$5:$G$15,4, FALSE)+VLOOKUP($J77,$B$5:$G$15,6, FALSE) -> 8.3676598 | U77: NEFJ | V77: 18.825646 | W77: 11.242151 | X77: CHI | Y77: Y | Z77: NEFJ | AA77: =V77-W77 -> 7.5834952 | AB77: NEFJ | AC77: -2.5 | AD77: if NEFJ underdog SMASH
A78: 15 | B78: 45451 | C78: OGDC | D78: 15.081305 | E78: 25.475478 | F78: NEFJ | G78: Y | H78: NEFJ | I78: 15 | J78: ARC | K78: CHI | L78: 19 | M78: 33 | N78: =IFERROR(mean+0.5*Home_edge+VLOOKUP(J78,$B$5:$G$15,4,FALSE)+VLOOKUP(K78,$B$5:$G$15,6,FALSE),"") -> 15.573838 | O78: =IFERROR(mean-0.5*Home_edge+VLOOKUP(K78,$B$5:$G$15,4,FALSE)+VLOOKUP(J78,$B$5:$G$15,6,FALSE),"") -> 32.200563 | P78: =IFERROR((N78-L78)^2+(O78-M78)^2,"") -> 12.377685 | Q78: =VLOOKUP($J78,$B$5:$G$15,4, FALSE)+VLOOKUP($K78,$B$5:$G$15,6, FALSE) -> -9.0330853 | R78: =VLOOKUP($K78,$B$5:$G$15,4, FALSE)+VLOOKUP($J78,$B$5:$G$15,6, FALSE) -> 11.256751 | U78: SDL | V78: 24.634996 | W78: 20.961071 | X78: HOU | Y78: N | Z78: SDL | AA78: =V78-W78 -> 3.6739244 | AB78: HOU | AC78: 5.5 | AD78: HOU cover
A79: 15 | B79: 45451 | C79: HOU | D79: 30.282448 | E79: 17.077826 | F79: RFCLA | G79: Y | H79: HOU | I79: 16 | J79: OGDC | K79: RFCLA | L79: 32 | M79: 43 | N79: =IFERROR(mean+0.5*Home_edge+VLOOKUP(J79,$B$5:$G$15,4,FALSE)+VLOOKUP(K79,$B$5:$G$15,6,FALSE),"") -> 27.7993 | O79: =IFERROR(mean-0.5*Home_edge+VLOOKUP(K79,$B$5:$G$15,4,FALSE)+VLOOKUP(J79,$B$5:$G$15,6,FALSE),"") -> 28.162482 | P79: =IFERROR((N79-L79)^2+(O79-M79)^2,"") -> 237.79782 | Q79: =VLOOKUP($J79,$B$5:$G$15,4, FALSE)+VLOOKUP($K79,$B$5:$G$15,6, FALSE) -> 3.1923766 | R79: =VLOOKUP($K79,$B$5:$G$15,4, FALSE)+VLOOKUP($J79,$B$5:$G$15,6, FALSE) -> 7.2186701 | U79: RFCLA | V79: 42.067018 | W79: 21.577719 | X79: ARC | Y79: Y | Z79: RFCLA | AA79: =V79-W79 -> 20.4893 | AB79: RFCLA | AC79: 18.5 | AD79: ARC cover
A80: 15 | B80: 45452 | C80: SD | D80: 40.842238 | E80: 16.334163 | F80: ARC | G80: Y | H80: SD | I80: 16 | J80: MIA | K80: SDL | L80: 36 | M80: 32 | N80: =IFERROR(mean+0.5*Home_edge+VLOOKUP(J80,$B$5:$G$15,4,FALSE)+VLOOKUP(K80,$B$5:$G$15,6,FALSE),"") -> 20.089895 | O80: =IFERROR(mean-0.5*Home_edge+VLOOKUP(K80,$B$5:$G$15,4,FALSE)+VLOOKUP(J80,$B$5:$G$15,6,FALSE),"") -> 24.704537 | P80: =IFERROR((N80-L80)^2+(O80-M80)^2,"") -> 306.35522 | Q80: =VLOOKUP($J80,$B$5:$G$15,4, FALSE)+VLOOKUP($K80,$B$5:$G$15,6, FALSE) -> -4.5170285 | R80: =VLOOKUP($K80,$B$5:$G$15,4, FALSE)+VLOOKUP($J80,$B$5:$G$15,6, FALSE) -> 3.7607249 | U80: UTAH | V80: 33.193 | W80: 18.749802 | X80: SEA | Y80: N | Z80: UTAH | AA80: =V80-W80 -> 14.443198 | AB80: UTAH | AC80: -10.5 | AD80: SEA cover
A81: 15 | B81: 45452 | C81: MIA | D81: 14.469474 | E81: 20.070493 | F81: NOLA | G81: Y | H81: NOLA | I81: 16 | J81: CHI | K81: NOLA | L81: 38 | M81: 17 | N81: =IFERROR(mean+0.5*Home_edge+VLOOKUP(J81,$B$5:$G$15,4,FALSE)+VLOOKUP(K81,$B$5:$G$15,6,FALSE),"") -> 26.156089 | O81: =IFERROR(mean-0.5*Home_edge+VLOOKUP(K81,$B$5:$G$15,4,FALSE)+VLOOKUP(J81,$B$5:$G$15,6,FALSE),"") -> 14.979333 | P81: =IFERROR((N81-L81)^2+(O81-M81)^2,"") -> 144.36133 | Q81: =VLOOKUP($J81,$B$5:$G$15,4, FALSE)+VLOOKUP($K81,$B$5:$G$15,6, FALSE) -> 1.5491651 | R81: =VLOOKUP($K81,$B$5:$G$15,4, FALSE)+VLOOKUP($J81,$B$5:$G$15,6, FALSE) -> -5.9644787 | T81: midweek | U81: NOLA | V81: 29.716777 | W81: 23.435885 | X81: OGDC | Y81: N | Z81: NOLA
A82: 15 | B82: 45452 | C82: DAL | D82: 26.174088 | E82: 26.534335 | F82: CHI | G82: N | H82: CHI | I82: 16 | J82: UTAH | K82: ARC | L82: 31 | M82: 10 | N82: =IFERROR(mean+0.5*Home_edge+VLOOKUP(J82,$B$5:$G$15,4,FALSE)+VLOOKUP(K82,$B$5:$G$15,6,FALSE),"") -> 42.682169 | O82: =IFERROR(mean-0.5*Home_edge+VLOOKUP(K82,$B$5:$G$15,4,FALSE)+VLOOKUP(J82,$B$5:$G$15,6,FALSE),"") -> 17.522458 | P82: =IFERROR((N82-L82)^2+(O82-M82)^2,"") -> 193.06044 | Q82: =VLOOKUP($J82,$B$5:$G$15,4, FALSE)+VLOOKUP($K82,$B$5:$G$15,6, FALSE) -> 18.075245 | R82: =VLOOKUP($K82,$B$5:$G$15,4, FALSE)+VLOOKUP($J82,$B$5:$G$15,6, FALSE) -> -3.4213541 | T82: 14 | U82: MIA | V82: 10.745729 | W82: 19.762651 | X82: NEFJ | Y82: N | Z82: NEFJ | AA82: =W82-V82 -> 9.016922
A83: 15 | B83: 45452 | C83: SEA | D83: 23.188622 | E83: 17.773944 | F83: UTA | G83: Y | H83: SEA | I83: 16 | J83: NEFJ | K83: SEA | L83: 37 | M83: 30 | N83: =IFERROR(mean+0.5*Home_edge+VLOOKUP(J83,$B$5:$G$15,4,FALSE)+VLOOKUP(K83,$B$5:$G$15,6,FALSE),"") -> 22.531204 | O83: =IFERROR(mean-0.5*Home_edge+VLOOKUP(K83,$B$5:$G$15,4,FALSE)+VLOOKUP(J83,$B$5:$G$15,6,FALSE),"") -> 15.90345 | P83: =IFERROR((N83-L83)^2+(O83-M83)^2,"") -> 408.05878 | Q83: =VLOOKUP($J83,$B$5:$G$15,4, FALSE)+VLOOKUP($K83,$B$5:$G$15,6, FALSE) -> -2.0757195 | R83: =VLOOKUP($K83,$B$5:$G$15,4, FALSE)+VLOOKUP($J83,$B$5:$G$15,6, FALSE) -> -5.040362 | U83: HOU | V83: 27.135052 | W83: 25.746096 | X83: UTAH | Y83: Y | Z83: HOU | AA83: =V83-W83 -> 1.3889564
I84: Midweeks: | J84: SEA | K84: ARC | L84: 60 | M84: 19 | N84: =IFERROR(mean+0.5*Home_edge+VLOOKUP(J84,$B$5:$G$15,4,FALSE)+VLOOKUP(K84,$B$5:$G$15,6,FALSE),"") -> 37.847957 | O84: =IFERROR(mean-0.5*Home_edge+VLOOKUP(K84,$B$5:$G$15,4,FALSE)+VLOOKUP(J84,$B$5:$G$15,6,FALSE),"") -> 15.28449 | P84: =IFERROR((N84-L84)^2+(O84-M84)^2,"") -> 504.51802 | Q84: =VLOOKUP($J84,$B$5:$G$15,4, FALSE)+VLOOKUP($K84,$B$5:$G$15,6, FALSE) -> 13.241034 | R84: =VLOOKUP($K84,$B$5:$G$15,4, FALSE)+VLOOKUP($J84,$B$5:$G$15,6, FALSE) -> -5.6593224 | U84: SEA | V84: 23.650757 | W84: 21.439351 | X84: SDL | Y84: Y | Z84: SEA | AA84: =V84-W84 -> 2.2114054
J85: RFCLA | K85: NEFJ | L85: 21 | M85: 23 | N85: =IFERROR(mean+0.5*Home_edge+VLOOKUP(J85,$B$5:$G$15,4,FALSE)+VLOOKUP(K85,$B$5:$G$15,6,FALSE),"") -> 23.39348 | O85: =IFERROR(mean-0.5*Home_edge+VLOOKUP(K85,$B$5:$G$15,4,FALSE)+VLOOKUP(J85,$B$5:$G$15,6,FALSE),"") -> 24.036738 | P85: =IFERROR((N85-L85)^2+(O85-M85)^2,"") -> 6.8035721 | Q85: =VLOOKUP($J85,$B$5:$G$15,4, FALSE)+VLOOKUP($K85,$B$5:$G$15,6, FALSE) -> -1.2134436 | R85: =VLOOKUP($K85,$B$5:$G$15,4, FALSE)+VLOOKUP($J85,$B$5:$G$15,6, FALSE) -> 3.0929262 | U85: ARC | V85: 24.124988 | W85: 35.268112 | X85: OGDC | Y85: Y | Z85: OGDC | AA85: =W85-V85 -> 11.143123
J86: SDL | K86: UTAH | L86: 31 | M86: 38 | N86: =IFERROR(mean+0.5*Home_edge+VLOOKUP(J86,$B$5:$G$15,4,FALSE)+VLOOKUP(K86,$B$5:$G$15,6,FALSE),"") -> 28.232718 | O86: =IFERROR(mean-0.5*Home_edge+VLOOKUP(K86,$B$5:$G$15,4,FALSE)+VLOOKUP(J86,$B$5:$G$15,6,FALSE),"") -> 26.082039 | P86: =IFERROR((N86-L86)^2+(O86-M86)^2,"") -> 149.69565 | Q86: =VLOOKUP($J86,$B$5:$G$15,4, FALSE)+VLOOKUP($K86,$B$5:$G$15,6, FALSE) -> 3.6257947 | R86: =VLOOKUP($K86,$B$5:$G$15,4, FALSE)+VLOOKUP($J86,$B$5:$G$15,6, FALSE) -> 5.1382266 | U86: CHI | V86: 27.093731 | W86: 19.78354 | X86: RFCLA | Y86: N | Z86: CHI | AA86: =V86-W86 -> 7.3101912
J87: NOLA | K87: OGDC | L87: 14 | M87: 27 | N87: =IFERROR(mean+0.5*Home_edge+VLOOKUP(J87,$B$5:$G$15,4,FALSE)+VLOOKUP(K87,$B$5:$G$15,6,FALSE),"") -> 26.190721 | O87: =IFERROR(mean-0.5*Home_edge+VLOOKUP(K87,$B$5:$G$15,4,FALSE)+VLOOKUP(J87,$B$5:$G$15,6,FALSE),"") -> 23.283752 | P87: =IFERROR((N87-L87)^2+(O87-M87)^2,"") -> 162.42417 | Q87: =VLOOKUP($J87,$B$5:$G$15,4, FALSE)+VLOOKUP($K87,$B$5:$G$15,6, FALSE) -> 1.5837972 | R87: =VLOOKUP($K87,$B$5:$G$15,4, FALSE)+VLOOKUP($J87,$B$5:$G$15,6, FALSE) -> 2.3399404 | T87: 15 | U87: RFCLA | X87: MIA | Y87: Y | Z87: RFCLA
I88: 17 | J88: NOLA | K88: NEFJ | L88: 17 | M88: 21 | N88: =IFERROR(mean+0.5*Home_edge+VLOOKUP(J88,$B$5:$G$15,4,FALSE)+VLOOKUP(K88,$B$5:$G$15,6,FALSE),"") -> 17.758607 | O88: =IFERROR(mean-0.5*Home_edge+VLOOKUP(K88,$B$5:$G$15,4,FALSE)+VLOOKUP(J88,$B$5:$G$15,6,FALSE),"") -> 23.184302 | P88: =IFERROR((N88-L88)^2+(O88-M88)^2,"") -> 5.3466592 | Q88: =VLOOKUP($J88,$B$5:$G$15,4, FALSE)+VLOOKUP($K88,$B$5:$G$15,6, FALSE) -> -6.8483165 | R88: =VLOOKUP($K88,$B$5:$G$15,4, FALSE)+VLOOKUP($J88,$B$5:$G$15,6, FALSE) -> 2.2404899 | U88: SEA | X88: HOU | Y88: N | Z88: HOU
I89: 17 | J89: UTAH | K89: RFCLA | L89: 48 | M89: 33 | N89: =IFERROR(mean+0.5*Home_edge+VLOOKUP(J89,$B$5:$G$15,4,FALSE)+VLOOKUP(K89,$B$5:$G$15,6,FALSE),"") -> 33.82702 | O89: =IFERROR(mean-0.5*Home_edge+VLOOKUP(K89,$B$5:$G$15,4,FALSE)+VLOOKUP(J89,$B$5:$G$15,6,FALSE),"") -> 26.225937 | P89: =IFERROR((N89-L89)^2+(O89-M89)^2,"") -> 246.7613 | Q89: =VLOOKUP($J89,$B$5:$G$15,4, FALSE)+VLOOKUP($K89,$B$5:$G$15,6, FALSE) -> 9.220096 | R89: =VLOOKUP($K89,$B$5:$G$15,4, FALSE)+VLOOKUP($J89,$B$5:$G$15,6, FALSE) -> 5.2821255 | U89: NEFJ | X89: OGDC | Y89: N | Z89: NEFJ
I90: 17 | J90: SDL | K90: OGDC | L90: 50 | M90: 5 | N90: =IFERROR(mean+0.5*Home_edge+VLOOKUP(J90,$B$5:$G$15,4,FALSE)+VLOOKUP(K90,$B$5:$G$15,6,FALSE),"") -> 30.169263 | O90: =IFERROR(mean-0.5*Home_edge+VLOOKUP(K90,$B$5:$G$15,4,FALSE)+VLOOKUP(J90,$B$5:$G$15,6,FALSE),"") -> 20.054319 | P90: =IFERROR((N90-L90)^2+(O90-M90)^2,"") -> 619.89066 | Q90: =VLOOKUP($J90,$B$5:$G$15,4, FALSE)+VLOOKUP($K90,$B$5:$G$15,6, FALSE) -> 5.5623393 | R90: =VLOOKUP($K90,$B$5:$G$15,4, FALSE)+VLOOKUP($J90,$B$5:$G$15,6, FALSE) -> -0.88949281 | U90: NOLA | X90: UTAH | Y90: Y | Z90: UTAH
I91: 17 | J91: HOU | K91: ARC | L91: 26 | M91: 14 | N91: =IFERROR(mean+0.5*Home_edge+VLOOKUP(J91,$B$5:$G$15,4,FALSE)+VLOOKUP(K91,$B$5:$G$15,6,FALSE),"") -> 37.922765 | O91: =IFERROR(mean-0.5*Home_edge+VLOOKUP(K91,$B$5:$G$15,4,FALSE)+VLOOKUP(J91,$B$5:$G$15,6,FALSE),"") -> 11.579677 | P91: =IFERROR((N91-L91)^2+(O91-M91)^2,"") -> 148.01029 | Q91: =VLOOKUP($J91,$B$5:$G$15,4, FALSE)+VLOOKUP($K91,$B$5:$G$15,6, FALSE) -> 13.315842 | R91: =VLOOKUP($K91,$B$5:$G$15,4, FALSE)+VLOOKUP($J91,$B$5:$G$15,6, FALSE) -> -9.3641346 | U91: ARC | X91: CHI | Y91: Y | Z91: CHI
I92: 17 | J92: SEA | K92: MIA | L92: 42 | M92: 17 | N92: =IFERROR(mean+0.5*Home_edge+VLOOKUP(J92,$B$5:$G$15,4,FALSE)+VLOOKUP(K92,$B$5:$G$15,6,FALSE),"") -> 26.197061 | O92: =IFERROR(mean-0.5*Home_edge+VLOOKUP(K92,$B$5:$G$15,4,FALSE)+VLOOKUP(J92,$B$5:$G$15,6,FALSE),"") -> 15.340007 | P92: =IFERROR((N92-L92)^2+(O92-M92)^2,"") -> 252.48847 | Q92: =VLOOKUP($J92,$B$5:$G$15,4, FALSE)+VLOOKUP($K92,$B$5:$G$15,6, FALSE) -> 1.5901372 | R92: =VLOOKUP($K92,$B$5:$G$15,4, FALSE)+VLOOKUP($J92,$B$5:$G$15,6, FALSE) -> -5.6038047 | T92: 16 | U92: OGDC | V92: 28.976878 | W92: 25.847571 | X92: RFCLA | Y92: N | Z92: OGDC
I93: 17 | J93: CHI | K93: HOU | L93: 15 | M93: 12 | N93: =IFERROR(mean+0.5*Home_edge+VLOOKUP(J93,$B$5:$G$15,4,FALSE)+VLOOKUP(K93,$B$5:$G$15,6,FALSE),"") -> 18.135067 | O93: =IFERROR(mean-0.5*Home_edge+VLOOKUP(K93,$B$5:$G$15,4,FALSE)+VLOOKUP(J93,$B$5:$G$15,6,FALSE),"") -> 16.862096 | P93: =IFERROR((N93-L93)^2+(O93-M93)^2,"") -> 33.46862 | Q93: =VLOOKUP($J93,$B$5:$G$15,4, FALSE)+VLOOKUP($K93,$B$5:$G$15,6, FALSE) -> -6.4718565 | R93: =VLOOKUP($K93,$B$5:$G$15,4, FALSE)+VLOOKUP($J93,$B$5:$G$15,6, FALSE) -> -4.0817162 | U93: MIA | V93: 20.179409 | W93: 22.082635 | X93: SDL | Y93: N | Z93: SDL
A94: QF | B94: NEFJ | C94: 24.205334 | D94: 10.807608 | E94: MIA | F94: Y | G94: NEFJ | I94: Playoffs | J94: NEFJ | K94: MIA | L94: 32 | M94: 10 | N94: =IFERROR(mean+0.5*Home_edge+VLOOKUP(J94,$B$5:$G$15,4,FALSE)+VLOOKUP(K94,$B$5:$G$15,6,FALSE),"") -> 24.904103 | O94: =IFERROR(mean-0.5*Home_edge+VLOOKUP(K94,$B$5:$G$15,4,FALSE)+VLOOKUP(J94,$B$5:$G$15,6,FALSE),"") -> 11.082407 | P94: =IFERROR((N94-L94)^2+(O94-M94)^2,"") -> 51.523365 | Q94: =VLOOKUP($J94,$B$5:$G$15,4, FALSE)+VLOOKUP($K94,$B$5:$G$15,6, FALSE) -> 0.29717906 | R94: =VLOOKUP($K94,$B$5:$G$15,4, FALSE)+VLOOKUP($J94,$B$5:$G$15,6, FALSE) -> -9.8614054 | U94: CHI | V94: 25.840758 | W94: 16.772153 | X94: NOLA | Y94: Y | Z94: CHI
A95: QF | B95: HOU | C95: 28.973049 | D95: 20.526549 | E95: RFCLA | F95: Y | G95: HOU | J95: HOU | K95: RFCLA | L95: 27 | M95: 21 | N95: =IFERROR(mean+0.5*Home_edge+VLOOKUP(J95,$B$5:$G$15,4,FALSE)+VLOOKUP(K95,$B$5:$G$15,6,FALSE),"") -> 29.067616 | O95: =IFERROR(mean-0.5*Home_edge+VLOOKUP(K95,$B$5:$G$15,4,FALSE)+VLOOKUP(J95,$B$5:$G$15,6,FALSE),"") -> 20.283157 | P95: =IFERROR((N95-L95)^2+(O95-M95)^2,"") -> 4.7888993 | Q95: =VLOOKUP($J95,$B$5:$G$15,4, FALSE)+VLOOKUP($K95,$B$5:$G$15,6, FALSE) -> 4.4606923 | R95: =VLOOKUP($K95,$B$5:$G$15,4, FALSE)+VLOOKUP($J95,$B$5:$G$15,6, FALSE) -> -0.66065508 | U95: UTAH | V95: 45.790822 | W95: 18.737442 | X95: ARC | Y95: Y | Z95: UTAH
A96: QF | B96: CHI | C96: 25.825081 | D96: 15.47837 | E96: OGDC | F96: Y | G96: CHI | J96: CHI | K96: OGDC | L96: 27 | M96: 16 | N96: =IFERROR(mean+0.5*Home_edge+VLOOKUP(J96,$B$5:$G$15,4,FALSE)+VLOOKUP(K96,$B$5:$G$15,6,FALSE),"") -> 26.014392 | O96: =IFERROR(mean-0.5*Home_edge+VLOOKUP(K96,$B$5:$G$15,4,FALSE)+VLOOKUP(J96,$B$5:$G$15,6,FALSE),"") -> 15.59378 | P96: =IFERROR((N96-L96)^2+(O96-M96)^2,"") -> 1.1364375 | Q96: =VLOOKUP($J96,$B$5:$G$15,4, FALSE)+VLOOKUP($K96,$B$5:$G$15,6, FALSE) -> 1.4074687 | R96: =VLOOKUP($K96,$B$5:$G$15,4, FALSE)+VLOOKUP($J96,$B$5:$G$15,6, FALSE) -> -5.3500319 | U96: NEFJ | V96: 21.76857 | W96: 13.81757 | X96: SEA | Y96: Y | Z96: NEFJ
A97: QF | B97: UTAH | C97: 29.978824 | D97: 21.903519 | E97: SEA | F97: Y | G97: UTAH | J97: UTAH | K97: SEA | L97: 23 | M97: 21 | N97: =IFERROR(mean+0.5*Home_edge+VLOOKUP(J97,$B$5:$G$15,4,FALSE)+VLOOKUP(K97,$B$5:$G$15,6,FALSE),"") -> 28.658374 | O97: =IFERROR(mean-0.5*Home_edge+VLOOKUP(K97,$B$5:$G$15,4,FALSE)+VLOOKUP(J97,$B$5:$G$15,6,FALSE),"") -> 22.399019 | P97: =IFERROR((N97-L97)^2+(O97-M97)^2,"") -> 33.974449 | Q97: =VLOOKUP($J97,$B$5:$G$15,4, FALSE)+VLOOKUP($K97,$B$5:$G$15,6, FALSE) -> 4.0514504 | R97: =VLOOKUP($K97,$B$5:$G$15,4, FALSE)+VLOOKUP($J97,$B$5:$G$15,6, FALSE) -> 1.455207 | T97: 17 | U97: NOLA | V97: 18.121102 | W97: 23.652022 | X97: NEFJ | Y97: Y | Z97: NEFJ
A98: SF | B98: NEFJ | C98: 19.162044 | D98: 13.205112 | E98: CHI | G98: NEFJ | J98: NEFJ | K98: CHI | L98: 21 | M98: 20 | N98: =IFERROR(mean+0.5*Home_edge+VLOOKUP(J98,$B$5:$G$15,4,FALSE)+VLOOKUP(K98,$B$5:$G$15,6,FALSE),"") -> 19.157441 | O98: =IFERROR(mean-0.5*Home_edge+VLOOKUP(K98,$B$5:$G$15,4,FALSE)+VLOOKUP(J98,$B$5:$G$15,6,FALSE),"") -> 13.919167 | P98: =IFERROR((N98-L98)^2+(O98-M98)^2,"") -> 40.371554 | Q98: =VLOOKUP($J98,$B$5:$G$15,4, FALSE)+VLOOKUP($K98,$B$5:$G$15,6, FALSE) -> -5.4494824 | R98: =VLOOKUP($K98,$B$5:$G$15,4, FALSE)+VLOOKUP($J98,$B$5:$G$15,6, FALSE) -> -7.024645 | U98: UTAH | V98: 32.882785 | W98: 25.271066 | X98: RFCLA | Y98: Y | Z98: UTAH
A99: SF | B99: UTAH | C99: 25.829835 | D99: 21.337056 | E99: HOU | G99: UTAH | J99: UTAH | K99: HOU | L99: 19 | M99: 33 | N99: =IFERROR(mean+0.5*Home_edge+VLOOKUP(J99,$B$5:$G$15,4,FALSE)+VLOOKUP(K99,$B$5:$G$15,6,FALSE),"") -> 24.953562 | O99: =IFERROR(mean-0.5*Home_edge+VLOOKUP(K99,$B$5:$G$15,4,FALSE)+VLOOKUP(J99,$B$5:$G$15,6,FALSE),"") -> 22.473827 | P99: =IFERROR((N99-L99)^2+(O99-M99)^2,"") -> 146.24521 | Q99: =VLOOKUP($J99,$B$5:$G$15,4, FALSE)+VLOOKUP($K99,$B$5:$G$15,6, FALSE) -> 0.34663817 | R99: =VLOOKUP($K99,$B$5:$G$15,4, FALSE)+VLOOKUP($J99,$B$5:$G$15,6, FALSE) -> 1.530015 | U99: SDL | V99: 28.140838 | W99: 22.674372 | X99: OGDC | Y99: Y | Z99: SDL
A100: F | B100: HOU | C100: =AVERAGE(C104,D103) -> 17.809814 | D100: =AVERAGE(D104,C103) -> 16.994836 | E100: NEFJ | G100: HOU | J100: NEFJ | K100: HOU | N100: =IFERROR(mean+0.5*Home_edge+VLOOKUP(J100,$B$5:$G$15,4,FALSE)+VLOOKUP(K100,$B$5:$G$15,6,FALSE),"") -> 18.826392 | O100: =IFERROR(mean-0.5*Home_edge+VLOOKUP(K100,$B$5:$G$15,4,FALSE)+VLOOKUP(J100,$B$5:$G$15,6,FALSE),"") -> 15.978258 | Q100: =VLOOKUP($J100,$B$5:$G$15,4, FALSE)+VLOOKUP($K100,$B$5:$G$15,6, FALSE) -> -5.7805317 | R100: =VLOOKUP($K100,$B$5:$G$15,4, FALSE)+VLOOKUP($J100,$B$5:$G$15,6, FALSE) -> -4.965554 | U100: HOU | V100: 39.429527 | W100: 12.621621 | X100: ARC | Z100: HOU
...

Sheet PlayerIDs
A1: Abe Turpen | B1: 811
A2: Adriaan Carelse | B2: 4
A3: Aidan King | B3: 812
A4: AJ Alatimu | B4: 6
A5: Aki Seiuli | B5: 858
A6: Albert O'Shannessey | B6: 527
A7: Alec McDonnell | B7: 8
A8: Alejandro Martinez Tapia | B8: 827
A9: Alesana Pohla | B9: 687
A10: Alessandro Heaney | B10: 589
A11: Alex Lopeti | B11: 7
A12: Alex Maughan | B12: 14
... A433: Zurab Zhvania | B433: 546

Sheet FRvsDef
A1: FR vs Def 2025 | F1: Finished Week: | G1: 13
B2: 0
A3: Mean: | B3: =AVERAGE(B6:B49) -> 6.1036242e-09 | F3: Home | G3: 0.076396245
A4: (highest rank is most helpful matchup) | F4: Away | G4: =-G3 -> -0.076396245
A5: Team | B5: Rating | C5: Rank | Q5: =SUM($Q$7:$Q1000) -> 2470.0599
A6: SDL | B6: 1.4302 | C6: =RANK($B6,$B$6:$B$16,0) -> 1 | J6: Rnd | K6: Team | L6: Player | M6: Points | N6: home | O6: Opp | P6: Forecast | Q6: Squared Error | R6: GroupRnk | T6: Remaining Games for ROFS Calc
A7: ARC | B7: 0.56968285 | C7: =RANK($B7,$B$6:$B$16,0) -> 2 | J7: 1 | K7: NOLA | L7: Pat O'Toole | M7: 15.2 | N7: Home | O7: ARC | P7: =VLOOKUP($N7,$F$3:$G$4,2,FALSE)+VLOOKUP($L7,$B$20:$C$150,2,FALSE)+VLOOKUP($O7,$A$6:$B$16,2,FALSE) -> 11.693074 | Q7: =IFERROR(($M7-$P7)^2,"") -> 12.298529 | R7: {=SUMPRODUCT((J7=$J$7:$J$1000)*(P7<$P$7:$P$1000))+1} -> 1 | T7: {=_xlfn._xlws.FILTER($J$7:$P$10000,($J$7:$J$10000>$G$1)*($J$7:$J$10000<18))} -> 14 | U7: ARC | V7: Alex Maughan | W7: NULL | X7: Home | Y7: OGDC | Z7: 2.8843747
A8: LA | B8: 0.36202543 | C8: =RANK($B8,$B$6:$B$16,0) -> 3 | J8: 1 | K8: NEFJ | L8: Kaleb Geiger | M8: 8.6 | N8: Away | O8: LA | P8: =VLOOKUP($N8,$F$3:$G$4,2,FALSE)+VLOOKUP($L8,$B$20:$C$150,2,FALSE)+VLOOKUP($O8,$A$6:$B$16,2,FALSE) -> 5.9737489 | Q8: =IFERROR(($M8-$P8)^2,"") -> 6.897195 | R8: {=SUMPRODUCT((J8=$J$7:$J$1000)*(P8<$P$7:$P$1000))+1} -> 7 | T8: 14 | U8: ARC | V8: Alexander Hernandez | W8: NULL | X8: Home | Y8: OGDC | Z8: 1.3514586
A9: NEFJ | B9: 0.22713605 | C9: =RANK($B9,$B$6:$B$16,0) -> 4 | J9: 1 | K9: SEA | L9: Cameron Orr | M9: 7.7 | N9: Away | O9: SDL | P9: =VLOOKUP($N9,$F$3:$G$4,2,FALSE)+VLOOKUP($L9,$B$20:$C$150,2,FALSE)+VLOOKUP($O9,$A$6:$B$16,2,FALSE) -> 6.9103973 | Q9: =IFERROR(($M9-$P9)^2,"") -> 0.62347246 | R9: {=SUMPRODUCT((J9=$J$7:$J$1000)*(P9<$P$7:$P$1000))+1} -> 4 | T9: 14 | U9: ARC | V9: Connor Robinson | W9: NULL | X9: Home | Y9: OGDC | Z9: 5.0191906
A10: HOU | B10: 0.1496193 | C10: =RANK($B10,$B$6:$B$16,0) -> 5 | J10: 1 | K10: NEFJ | L10: Andrew Quattrin | M10: 7.6 | N10: Away | O10: LA | P10: =VLOOKUP($N10,$F$3:$G$4,2,FALSE)+VLOOKUP($L10,$B$20:$C$150,2,FALSE)+VLOOKUP($O10,$A$6:$B$16,2,FALSE) -> 6.4561451 | Q10: =IFERROR(($M10-$P10)^2,"") -> 1.3084039 | R10: {=SUMPRODUCT((J10=$J$7:$J$1000)*(P10<$P$7:$P$1000))+1} -> 6 | T10: 14 | U10: ARC | V10: Dan Hanson | W10: NULL | X10: Home | Y10: OGDC | Z10: 1.435512
A11: NOLA | B11: 0.070668616 | C11: =RANK($B11,$B$6:$B$16,0) -> 6 | J11: 1 | K11: CHI | L11: Dylan Fawsitt | M11: 7.2 | N11: Away | O11: HOU | P11: =VLOOKUP($N11,$F$3:$G$4,2,FALSE)+VLOOKUP($L11,$B$20:$C$150,2,FALSE)+VLOOKUP($O11,$A$6:$B$16,2,FALSE) -> 7.8761386 | Q11: =IFERROR(($M11-$P11)^2,"") -> 0.45716337 | R11: {=SUMPRODUCT((J11=$J$7:$J$1000)*(P11<$P$7:$P$1000))+1} -> 2 | T11: 14 | U11: ARC | V11: Ethan Howard | W11: NULL | X11: Home | Y11: OGDC | Z11: 5.2756223
A12: CHI | B12: -0.028426274 | C12: =RANK($B12,$B$6:$B$16,0) -> 7 | J12: 1 | K12: MIA | L12: Ma'ake Muti | M12: 6.6 | N12: Home | O12: OGDC | P12: =VLOOKUP($N12,$F$3:$G$4,2,FALSE)+VLOOKUP($L12,$B$20:$C$150,2,FALSE)+VLOOKUP($O12,$A$6:$B$16,2,FALSE) -> 2.3146356 | Q12: =IFERROR(($M12-$P12)^2,"") -> 18.364348 | R12: {=SUMPRODUCT((J12=$J$7:$J$1000)*(P12<$P$7:$P$1000))+1} -> 26 | T12: 14 | U12: ARC | V12: Jake Turnbull | W12: NULL | X12: Home | Y12: OGDC | Z12: 3.0778227
A13: MIA | B13: -0.26375398 | C13: =RANK($B13,$B$6:$B$16,0) -> 8 | J13: 1 | K13: CHI | L13: Charlie Abel | M13: 5.3 | N13: Away | O13: HOU | P13: =VLOOKUP($N13,$F$3:$G$4,2,FALSE)+VLOOKUP($L13,$B$20:$C$150,2,FALSE)+VLOOKUP($O13,$A$6:$B$16,2,FALSE) -> 3.7295944 | Q13: =IFERROR(($M13-$P13)^2,"") -> 2.4661736 | R13: {=SUMPRODUCT((J13=$J$7:$J$1000)*(P13<$P$7:$P$1000))+1} -> 18 | T13: 14 | U13: ARC | V13: Joe Apikotoa | W13: NULL | X13: Home | Y13: OGDC | Z13: 4.4938413
A14: SEA | B14: -0.52755576 | C14: =RANK($B14,$B$6:$B$16,0) -> 9 | J14: 1 | K14: OGDC | L14: Facundo Gattas | M14: 4.7 | N14: Away | O14: MIA | P14: =VLOOKUP($N14,$F$3:$G$4,2,FALSE)+VLOOKUP($L14,$B$20:$C$150,2,FALSE)+VLOOKUP($O14,$A$6:$B$16,2,FALSE) -> 5.0533443 | Q14: =IFERROR(($M14-$P14)^2,"") -> 0.12485219 | R14: {=SUMPRODUCT((J14=$J$7:$J$1000)*(P14<$P$7:$P$1000))+1} -> 10 | T14: 14 | U14: ARC | V14: Stephan Bernal-Wendt | W14: NULL | X14: Home | Y14: OGDC | Z14: 2.4237843
A15: OGDC | B15: -0.63922174 | C15: =RANK($B15,$B$6:$B$16,0) -> 10 | J15: 1 | K15: HOU | L15: Pono Davis | M15: 4.1 | N15: Home | O15: CHI | P15: =VLOOKUP($N15,$F$3:$G$4,2,FALSE)+VLOOKUP($L15,$B$20:$C$150,2,FALSE)+VLOOKUP($O15,$A$6:$B$16,2,FALSE) -> 3.204212 | Q15: =IFERROR(($M15-$P15)^2,"") -> 0.8024361 | R15: {=SUMPRODUCT((J15=$J$7:$J$1000)*(P15<$P$7:$P$1000))+1} -> 21 | T15: 14 | U15: CHI | V15: Charlie Abel | W15: NULL | X15: Home | Y15: LA | Z15: 4.0947931
A16: UTAH | B16: -1.3503744 | C16: =RANK($B16,$B$6:$B$16,0) -> 11 | J16: 1 | K16: HOU | L16: Seth Smith | M16: 4 | N16: Home | O16: CHI | P16: =VLOOKUP($N16,$F$3:$G$4,2,FALSE)+VLOOKUP($L16,$B$20:$C$150,2,FALSE)+VLOOKUP($O16,$A$6:$B$16,2,FALSE) -> 5.7124413 | Q16: =IFERROR(($M16-$P16)^2,"") -> 2.9324552 | R16: {=SUMPRODUCT((J16=$J$7:$J$1000)*(P16<$P$7:$P$1000))+1} -> 9 | T16: 14 | U16: CHI | V16: Dylan Fawsitt | W16: NULL | X16: Home | Y16: LA | Z16: 8.2413372
J17: 1 | K17: LA | L17: Alessandro Heaney | M17: 4 | N17: Home | O17: NEFJ | P17: =VLOOKUP($N17,$F$3:$G$4,2,FALSE)+VLOOKUP($L17,$B$20:$C$150,2,FALSE)+VLOOKUP($O17,$A$6:$B$16,2,FALSE) -> 3.7835866 | Q17: =IFERROR(($M17-$P17)^2,"") -> 0.04683475 | R17: {=SUMPRODUCT((J17=$J$7:$J$1000)*(P17<$P$7:$P$1000))+1} -> 17 | T17: 14 | U17: CHI | V17: Faka'osi Pifeleti | W17: NULL | X17: Home | Y17: LA | Z17: 2.807155
J18: 1 | K18: SDL | L18: Hugh Roach | M18: 3.9 | N18: Home | O18: SEA | P18: =VLOOKUP($N18,$F$3:$G$4,2,FALSE)+VLOOKUP($L18,$B$20:$C$150,2,FALSE)+VLOOKUP($O18,$A$6:$B$16,2,FALSE) -> 6.9577449 | Q18: =IFERROR(($M18-$P18)^2,"") -> 9.3498039 | R18: {=SUMPRODUCT((J18=$J$7:$J$1000)*(P18<$P$7:$P$1000))+1} -> 3 | T18: 14 | U18: CHI | V18: Ignacio Peculo | W18: NULL | X18: Home | Y18: LA | Z18: 5.9127591
A19: PlayerID | B19: Player | C19: OverallRating | D19: OverallRank | E19: WeeklyRating | F19: WeeklyRank | G19: ROFSRating | H19: ROFSRank | I19: Last5GamesStart% | J19: 1 | K19: NEFJ | L19: Malakai Hala-Ngatai | M19: 3.7 | N19: Away | O19: LA | P19: =VLOOKUP($N19,$F$3:$G$4,2,FALSE)+VLOOKUP($L19,$B$20:$C$150,2,FALSE)+VLOOKUP($O19,$A$6:$B$16,2,FALSE) -> 2.2794781 | Q19: =IFERROR(($M19-$P19)^2,"") -> 2.0178825 | R19: {=SUMPRODUCT((J19=$J$7:$J$1000)*(P19<$P$7:$P$1000))+1} -> 28 | T19: 14 | U19: CHI | V19: Janus Venter | W19: NULL | X19: Home | Y19: LA | Z19: 4.5467103
A20: =VLOOKUP($B20, PlayerIDs!$A$1:$B$1000, 2, FALSE) -> 32 | B20: Ben Strang | C20: 11.05214 | D20: =RANK($C20,$C$20:$C$106) -> 1 | E20: {=IFERROR(VLOOKUP($B20,_xlfn._xlws.FILTER($L$7:$P$10000,$J$7:$J$10000=G$1+1),5, FALSE), 0)} -> 10.947317 | F20: =RANK(E20,$E$20:$E$150) -> 1 | G20: =SUMIF(V:Z,$B20,Z:Z) -> 32.148621 | H20: =RANK($G20,$G$20:$G$106) -> 1 | I20: {=COUNT(_xlfn._xlws.FILTER($J$7:$J$10000,($L$7:$L$10000=B20)*($M$7:$M$10000<>"NULL")*($J$7:$J$10000 >= ($G$1-4))))/5} -> 0.2 | J20: 1 | K20: SDL | L20: Darcy Breen | M20: 3.6 | N20: Home | O20: SEA | P20: =VLOOKUP($N20,$F$3:$G$4,2,FALSE)+VLOOKUP($L20,$B$20:$C$150,2,FALSE)+VLOOKUP($O20,$A$6:$B$16,2,FALSE) -> 3.6377643 | Q20: =IFERROR(($M20-$P20)^2,"") -> 0.0014261433 | R20: {=SUMPRODUCT((J20=$J$7:$J$1000)*(P20<$P$7:$P$1000))+1} -> 19 | T20: 14 | U20: CHI | V20: Paddy Ryan | W20: NULL | X20: Home | Y20: LA | Z20: 2.8635043
A21: =VLOOKUP($B21, PlayerIDs!$A$1:$B$1000, 2, FALSE) -> 343 | B21: Pat O'Toole | C21: 11.046995 | D21: =RANK($C21,$C$20:$C$106) -> 2 | E21: {=IFERROR(VLOOKUP($B21,_xlfn._xlws.FILTER($L$7:$P$10000,$J$7:$J$10000=G$1+1),5, FALSE), 0)} -> 0 | F21: =RANK(E21,$E$20:$E$150) -> 74 | G21: =SUMIF(V:Z,$B21,Z:Z) -> 20.71519 | H21: =RANK($G21,$G$20:$G$106) -> 8 | I21: {=COUNT(_xlfn._xlws.FILTER($J$7:$J$10000,($L$7:$L$10000=B21)*($M$7:$M$10000<>"NULL")*($J$7:$J$10000 >= ($G$1-4))))/5} -> 0 | J21: 1 | K21: SDL | L21: Payton Telea-Ilalio | M21: 3.6 | N21: Home | O21: SEA | P21: =VLOOKUP($N21,$F$3:$G$4,2,FALSE)+VLOOKUP($L21,$B$20:$C$150,2,FALSE)+VLOOKUP($O21,$A$6:$B$16,2,FALSE) -> 4.1520716 | Q21: =IFERROR(($M21-$P21)^2,"") -> 0.30478309 | R21: {=SUMPRODUCT((J21=$J$7:$J$1000)*(P21<$P$7:$P$1000))+1} -> 15 | T21: 14 | U21: CHI | V21: Zurab Zhvania | W21: NULL | X21: Home | Y21: LA | Z21: 6.4203012
A22: =VLOOKUP($B22, PlayerIDs!$A$1:$B$1000, 2, FALSE) -> 726 | B22: Shilo Klein | C22: 10.747806 | D22: =RANK($C22,$C$20:$C$106) -> 3 | E22: {=IFERROR(VLOOKUP($B22,_xlfn._xlws.FILTER($L$7:$P$10000,$J$7:$J$10000=G$1+1),5, FALSE), 0)} -> 10.143854 | F22: =RANK(E22,$E$20:$E$150) -> 2 | G22: =SUMIF(V:Z,$B22,Z:Z) -> 20.55151 | H22: =RANK($G22,$G$20:$G$106) -> 9 | I22: {=COUNT(_xlfn._xlws.FILTER($J$7:$J$10000,($L$7:$L$10000=B22)*($M$7:$M$10000<>"NULL")*($J$7:$J$10000 >= ($G$1-4))))/5} -> 0.2 | J22: 1 | K22: SEA | L22: Juan Pablo Zeiss | M22: 3.6 | N22: Away | O22: SDL | P22: =VLOOKUP($N22,$F$3:$G$4,2,FALSE)+VLOOKUP($L22,$B$20:$C$150,2,FALSE)+VLOOKUP($O22,$A$6:$B$16,2,FALSE) -> 4.3102084 | Q22: =IFERROR(($M22-$P22)^2,"") -> 0.50439602 | R22: {=SUMPRODUCT((J22=$J$7:$J$1000)*(P22<$P$7:$P$1000))+1} -> 14 | T22: 14 | U22: HOU | V22: Ezekiel Lindenmuth | W22: NULL | X22: Home | Y22: UTAH | Z22: 2.765179
A23: =VLOOKUP($B23, PlayerIDs!$A$1:$B$1000, 2, FALSE) -> 738 | B23: Liam Coltman | C23: 9.2229621 | D23: =RANK($C23,$C$20:$C$106) -> 4 | E23: {=IFERROR(VLOOKUP($B23,_xlfn._xlws.FILTER($L$7:$P$10000,$J$7:$J$10000=G$1+1),5, FALSE), 0)} -> 9.2961852 | F23: =RANK(E23,$E$20:$E$150) -> 3 | G23: =SUMIF(V:Z,$B23,Z:Z) -> 28.382461 | H23: =RANK($G23,$G$20:$G$106) -> 2 | I23: {=COUNT(_xlfn._xlws.FILTER($J$7:$J$10000,($L$7:$L$10000=B23)*($M$7:$M$10000<>"NULL")*($J$7:$J$10000 >= ($G$1-4))))/5} -> 0.8 | J23: 1 | K23: ARC | L23: Ethan Howard | M23: 3.5 | N23: Away | O23: NOLA | P23: =VLOOKUP($N23,$F$3:$G$4,2,FALSE)+VLOOKUP($L23,$B$20:$C$150,2,FALSE)+VLOOKUP($O23,$A$6:$B$16,2,FALSE) -> 5.8327202 | Q23: =IFERROR(($M23-$P23)^2,"") -> 5.4415835 | R23: {=SUMPRODUCT((J23=$J$7:$J$1000)*(P23<$P$7:$P$1000))+1} -> 8 | T23: 14 | U23: HOU | V23: Michael Scott | W23: NULL | X23: Home | Y23: UTAH | Z23: 0.61396838
A24: =VLOOKUP($B24, PlayerIDs!$A$1:$B$1000, 2, FALSE) -> 696 | B24: Pita Anae-Ah Sue | C24: 8.7451072 | D24: =RANK($C24,$C$20:$C$106) -> 5 | E24: {=IFERROR(VLOOKUP($B24,_xlfn._xlws.FILTER($L$7:$P$10000,$J$7:$J$10000=G$1+1),5, FALSE), 0)} -> 7.471129 | F24: =RANK(E24,$E$20:$E$150) -> 8 | G24: =SUMIF(V:Z,$B24,Z:Z) -> 15.612284 | H24: =RANK($G24,$G$20:$G$106) -> 22 | I24: {=COUNT(_xlfn._xlws.FILTER($J$7:$J$10000,($L$7:$L$10000=B24)*($M$7:$M$10000<>"NULL")*($J$7:$J$10000 >= ($G$1-4))))/5} -> 0.8 | J24: 1 | K24: OGDC | L24: Jack Iscaro | M24: 2.9 | N24: Away | O24: MIA | P24: =VLOOKUP($N24,$F$3:$G$4,2,FALSE)+VLOOKUP($L24,$B$20:$C$150,2,FALSE)+VLOOKUP($O24,$A$6:$B$16,2,FALSE) -> 4.4895056 | Q24: =IFERROR(($M24-$P24)^2,"") -> 2.5265279 | R24: {=SUMPRODUCT((J24=$J$7:$J$1000)*(P24<$P$7:$P$1000))+1} -> 13 | T24: 14 | U24: HOU | V24: Pita Anae-Ah Sue | W24: NULL | X24: Home | Y24: UTAH | Z24: 7.471129
A25: =VLOOKUP($B25, PlayerIDs!$A$1:$B$1000, 2, FALSE) -> 124 | B25: Dylan Fawsitt | C25: 7.8029155 | D25: =RANK($C25,$C$20:$C$106) -> 6 | E25: {=IFERROR(VLOOKUP($B25,_xlfn._xlws.FILTER($L$7:$P$10000,$J$7:$J$10000=G$1+1),5, FALSE), 0)} -> 8.2413372 | F25: =RANK(E25,$E$20:$E$150) -> 4 | G25: =SUMIF(V:Z,$B25,Z:Z) -> 24.48752 | H25: =RANK($G25,$G$20:$G$106) -> 3 | I25: {=COUNT(_xlfn._xlws.FILTER($J$7:$J$10000,($L$7:$L$10000=B25)*($M$7:$M$10000<>"NULL")*($J$7:$J$10000 >= ($G$1-4))))/5} -> 0.8 | J25: 1 | K25: ARC | L25: Jake Turnbull | M25: 2.8 | N25: Away | O25: NOLA | P25: =VLOOKUP($N25,$F$3:$G$4,2,FALSE)+VLOOKUP($L25,$B$20:$C$150,2,FALSE)+VLOOKUP($O25,$A$6:$B$16,2,FALSE) -> 3.6349205 | Q25: =IFERROR(($M25-$P25)^2,"") -> 0.69709231 | R25: {=SUMPRODUCT((J25=$J$7:$J$1000)*(P25<$P$7:$P$1000))+1} -> 20 | T25: 14 | U25: HOU | V25: Pono Davis | W25: NULL | X25: Home | Y25: UTAH | Z25: 1.8822639
A26: =VLOOKUP($B26, PlayerIDs!$A$1:$B$1000, 2, FALSE) -> 679 | B26: Phil Bradford | C26: 7.7498686 | D26: =RANK($C26,$C$20:$C$106) -> 7 | E26: {=IFERROR(VLOOKUP($B26,_xlfn._xlws.FILTER($L$7:$P$10000,$J$7:$J$10000=G$1+1),5, FALSE), 0)} -> 7.8230916 | F26: =RANK(E26,$E$20:$E$150) -> 6 | G26: =SUMIF(V:Z,$B26,Z:Z) -> 23.96318 | H26: =RANK($G26,$G$20:$G$106) -> 5 | I26: {=COUNT(_xlfn._xlws.FILTER($J$7:$J$10000,($L$7:$L$10000=B26)*($M$7:$M$10000<>"NULL")*($J$7:$J$10000 >= ($G$1-4))))/5} -> 0.2 | J26: 1 | K26: HOU | L26: Val Lee-Lo | M26: 2.6 | N26: Home | O26: CHI | P26: =VLOOKUP($N26,$F$3:$G$4,2,FALSE)+VLOOKUP($L26,$B$20:$C$150,2,FALSE)+VLOOKUP($O26,$A$6:$B$16,2,FALSE) -> 2.2835865 | Q26: =IFERROR(($M26-$P26)^2,"") -> 0.10011752 | R26: {=SUMPRODUCT((J26=$J$7:$J$1000)*(P26<$P$7:$P$1000))+1} -> 27 | T26: 14 | U26: HOU | V26: Seth Smith | W26: NULL | X26: Home | Y26: UTAH | Z26: 4.3904932
A27: =VLOOKUP($B27, PlayerIDs!$A$1:$B$1000, 2, FALSE) -> 642 | B27: Martin Vaca | C27: 7.7272766 | D27: =RANK($C27,$C$20:$C$106) -> 8 | E27: {=IFERROR(VLOOKUP($B27,_xlfn._xlws.FILTER($L$7:$P$10000,$J$7:$J$10000=G$1+1),5, FALSE), 0)} -> 8.2205632 | F27: =RANK(E27,$E$20:$E$150) -> 5 | G27: =SUMIF(V:Z,$B27,Z:Z) -> 24.264278 | H27: =RANK($G27,$G$20:$G$106) -> 4 | I27: {=COUNT(_xlfn._xlws.FILTER($J$7:$J$10000,($L$7:$L$10000=B27)*($M$7:$M$10000<>"NULL")*($J$7:$J$10000 >= ($G$1-4))))/5} -> 0.2 | J27: 1 | K27: NOLA | L27: Paul Mullen | M27: 2.6 | N27: Home | O27: ARC | P27: =VLOOKUP($N27,$F$3:$G$4,2,FALSE)+VLOOKUP($L27,$B$20:$C$150,2,FALSE)+VLOOKUP($O27,$A$6:$B$16,2,FALSE) -> 3.8580744 | Q27: =IFERROR(($M27-$P27)^2,"") -> 1.5827513 | R27: {=SUMPRODUCT((J27=$J$7:$J$1000)*(P27<$P$7:$P$1000))+1} -> 16 | T27: 14 | U27: HOU | V27: Val Lee-Lo | W27: NULL | X27: Home | Y27: UTAH | Z27: 0.96163835
A28: =VLOOKUP($B28, PlayerIDs!$A$1:$B$1000, 2, FALSE) -> 868 | B28: Justus Tavai | C28: 7.6533041 | D28: =RANK($C28,$C$20:$C$106) -> 9 | E28: {=IFERROR(VLOOKUP($B28,_xlfn._xlws.FILTER($L$7:$P$10000,$J$7:$J$10000=G$1+1),5, FALSE), 0)} -> 7.5484815 | F28: =RANK(E28,$E$20:$E$150) -> 7 | G28: =SUMIF(V:Z,$B28,Z:Z) -> 21.952114 | H28: =RANK($G28,$G$20:$G$106) -> 7 | I28: {=COUNT(_xlfn._xlws.FILTER($J$7:$J$10000,($L$7:$L$10000=B28)*($M$7:$M$10000<>"NULL")*($J$7:$J$10000 >= ($G$1-4))))/5} -> 0.2 | J28: 1 | K28: SEA | L28: Dewald Kotze | M28: 2.5 | N28: Away | O28: SDL | P28: =VLOOKUP($N28,$F$3:$G$4,2,FALSE)+VLOOKUP($L28,$B$20:$C$150,2,FALSE)+VLOOKUP($O28,$A$6:$B$16,2,FALSE) -> 6.6389312 | Q28: =IFERROR(($M28-$P28)^2,"") -> 17.130751 | R28: {=SUMPRODUCT((J28=$J$7:$J$1000)*(P28<$P$7:$P$1000))+1} -> 5 | T28: 14 | U28: LA | V28: Alessandro Heaney | W28: NULL | X28: Away | Y28: CHI | Z28: 3.3752318
A29: =VLOOKUP($B29, PlayerIDs!$A$1:$B$1000, 2, FALSE) -> 171 | B29: Hugh Roach | C29: 7.4089044 | D29: =RANK($C29,$C$20:$C$106) -> 10 | E29: {=IFERROR(VLOOKUP($B29,_xlfn._xlws.FILTER($L$7:$P$10000,$J$7:$J$10000=G$1+1),5, FALSE), 0)} -> 6.8049524 | F29: =RANK(E29,$E$20:$E$150) -> 12 | G29: =SUMIF(V:Z,$B29,Z:Z) -> 13.873707 | H29: =RANK($G29,$G$20:$G$106) -> 29 | I29: {=COUNT(_xlfn._xlws.FILTER($J$7:$J$10000,($L$7:$L$10000=B29)*($M$7:$M$10000<>"NULL")*($J$7:$J$10000 >= ($G$1-4))))/5} -> 1 | J29: 1 | K29: OGDC | L29: Cali Martinez | M29: 2.3 | N29: Away | O29: MIA | P29: =VLOOKUP($N29,$F$3:$G$4,2,FALSE)+VLOOKUP($L29,$B$20:$C$150,2,FALSE)+VLOOKUP($O29,$A$6:$B$16,2,FALSE) -> 2.9488127 | Q29: =IFERROR(($M29-$P29)^2,"") -> 0.42095794 | R29: {=SUMPRODUCT((J29=$J$7:$J$1000)*(P29<$P$7:$P$1000))+1} -> 23 | T29: 14 | U29: LA | V29: Ben Strang | W29: NULL | X29: Away | Y29: CHI | Z29: 10.947317
A30: =VLOOKUP($B30, PlayerIDs!$A$1:$B$1000, 2, FALSE) -> 801 | B30: Declan Leaney | C30: 7.1502017 | D30: =RANK($C30,$C$20:$C$106) -> 11 | E30: {=IFERROR(VLOOKUP($B30,_xlfn._xlws.FILTER($L$7:$P$10000,$J$7:$J$10000=G$1+1),5, FALSE), 0)} -> 7.0453792 | F30: =RANK(E30,$E$20:$E$150) -> 10 | G30: =SUMIF(V:Z,$B30,Z:Z) -> 20.442807 | H30: =RANK($G30,$G$20:$G$106) -> 10 | I30: {=COUNT(_xlfn._xlws.FILTER($J$7:$J$10000,($L$7:$L$10000=B30)*($M$7:$M$10000<>"NULL")*($J$7:$J$10000 >= ($G$1-4))))/5} -> 0.2 | J30: 1 | K30: LA | L30: Ben Sugars | M30: 1.9 | N30: Home | O30: NEFJ | P30: =VLOOKUP($N30,$F$3:$G$4,2,FALSE)+VLOOKUP($L30,$B$20:$C$150,2,FALSE)+VLOOKUP($O30,$A$6:$B$16,2,FALSE) -> 5.0056938 | Q30: =IFERROR(($M30-$P30)^2,"") -> 9.6453339 | R30: {=SUMPRODUCT((J30=$J$7:$J$1000)*(P30<$P$7:$P$1000))+1} -> 12 | T30: 14 | U30: LA | V30: Ben Sugars | W30: NULL | X30: Away | Y30: CHI | Z30: 4.597339
A31: =VLOOKUP($B31, PlayerIDs!$A$1:$B$1000, 2, FALSE) -> 787 | B31: Connal McInerney | C31: 7.1275856 | D31: =RANK($C31,$C$20:$C$106) -> 12 | E31: {=IFERROR(VLOOKUP($B31,_xlfn._xlws.FILTER($L$7:$P$10000,$J$7:$J$10000=G$1+1),5, FALSE), 0)} -> 6.7874354 | F31: =RANK(E31,$E$20:$E$150) -> 14 | G31: =SUMIF(V:Z,$B31,Z:Z) -> 20.028622 | H31: =RANK($G31,$G$20:$G$106) -> 11 | I31: {=COUNT(_xlfn._xlws.FILTER($J$7:$J$10000,($L$7:$L$10000=B31)*($M$7:$M$10000<>"NULL")*($J$7:$J$10000 >= ($G$1-4))))/5} -> 0 | J31: 1 | K31: MIA | L31: Sean McNulty | M31: 1.8 | N31: Home | O31: OGDC | P31: =VLOOKUP($N31,$F$3:$G$4,2,FALSE)+VLOOKUP($L31,$B$20:$C$150,2,FALSE)+VLOOKUP($O31,$A$6:$B$16,2,FALSE) -> 2.7087205 | Q31: =IFERROR(($M31-$P31)^2,"") -> 0.82577286 | R31: {=SUMPRODUCT((J31=$J$7:$J$1000)*(P31<$P$7:$P$1000))+1} -> 24 | T31: 14 | U31: LA | V31: Cronan Gleeson | W31: NULL | X31: Away | Y31: CHI | Z31: 0.20497369
... A103: =VLOOKUP($B103, PlayerIDs!$A$1:$B$1000, 2, FALSE) -> 641 | B103: Joe Wrafter | C103: -2.7317218 | D103: =RANK($C103,$C$20:$C$106) -> 84 | E103: {=IFERROR(VLOOKUP($B103,_xlfn._xlws.FILTER($L$7:$P$10000,$J$7:$J$10000=G$1+1),5, FALSE), 0)} -> -2.2384352 | F103: =RANK(E103,$E$20:$E$150) -> 84 | G103: =SUMIF(V:Z,$B103,Z:Z) -> -7.1127173 | H103: =RANK($G103,$G$20:$G$106) -> 84 | I103: {=COUNT(_xlfn._xlws.FILTER($J$7:$J$10000,($L$7:$L$10000=B103)*($M$7:$M$10000<>"NULL")*($J$7:$J$10000 >= ($G$1-4))))/5} -> 0 | J103: 4 | K103: SDL | L103: Darcy Breen | M103: 4.4 | N103: Home | O103: LA | P103: =VLOOKUP($N103,$F$3:$G$4,2,FALSE)+VLOOKUP($L103,$B$20:$C$150,2,FALSE)+VLOOKUP($O103,$A$6:$B$16,2,FALSE) -> 4.5273455 | Q103: =IFERROR(($M103-$P103)^2,"") -> 0.016216875 | R103: {=SUMPRODUCT((J103=$J$7:$J$1000)*(P103<$P$7:$P$1000))+1} -> 13 | T103: 15 | U103: HOU | V103: Val Lee-Lo | W103: NULL | X103: Away | Y103: SEA | Z103: 1.6316645
J104: 4 | K104: ARC | L104: Jake Turnbull | M104: 4.2 | N104: Away | O104: OGDC | P104: =VLOOKUP($N104,$F$3:$G$4,2,FALSE)+VLOOKUP($L104,$B$20:$C$150,2,FALSE)+VLOOKUP($O104,$A$6:$B$16,2,FALSE) -> 2.9250302 | Q104: =IFERROR(($M104-$P104)^2,"") -> 1.625548 | R104: {=SUMPRODUCT((J104=$J$7:$J$1000)*(P104<$P$7:$P$1000))+1} -> 21 | T104: 15 | U104: LA | V104: Alessandro Heaney | W104: NULL | X104: Home | Y104: MIA | Z104: 3.2926966
J105: 4 | K105: SEA | L105: Kerron van Vuuren | M105: 3.7 | N105: Home | O105: NEFJ | P105: =VLOOKUP($N105,$F$3:$G$4,2,FALSE)+VLOOKUP($L105,$B$20:$C$150,2,FALSE)+VLOOKUP($O105,$A$6:$B$16,2,FALSE) -> 4.8333719 | Q105: =IFERROR(($M105-$P105)^2,"") -> 1.2845319 | R105: {=SUMPRODUCT((J105=$J$7:$J$1000)*(P105<$P$7:$P$1000))+1} -> 12 | T105: 15 | U105: LA | V105: Ben Strang | W105: NULL | X105: Home | Y105: MIA | Z105: 10.864782
J106: 4 | K106: ARC | L106: Alex Maughan | M106: 3.6 | N106: Away | O106: OGDC | P106: =VLOOKUP($N106,$F$3:$G$4,2,FALSE)+VLOOKUP($L106,$B$20:$C$150,2,FALSE)+VLOOKUP($O106,$A$6:$B$16,2,FALSE) -> 2.7315822 | Q106: =IFERROR(($M106-$P106)^2,"") -> 0.75414947 | R106: {=SUMPRODUCT((J106=$J$7:$J$1000)*(P106<$P$7:$P$1000))+1} -> 22 | T106: 15 | U106: LA | V106: Ben Sugars | W106: NULL | X106: Home | Y106: MIA | Z106: 4.5148038
J107: 4 | K107: HOU | L107: Pono Davis | M107: 3.3 | N107: Away | O107: UTAH | P107: =VLOOKUP($N107,$F$3:$G$4,2,FALSE)+VLOOKUP($L107,$B$20:$C$150,2,FALSE)+VLOOKUP($O107,$A$6:$B$16,2,FALSE) -> 1.7294714 | Q107: =IFERROR(($M107-$P107)^2,"") -> 2.46656 | R107: {=SUMPRODUCT((J107=$J$7:$J$1000)*(P107<$P$7:$P$1000))+1} -> 24 | T107: 15 | U107: LA | V107: Cronan Gleeson | W107: NULL | X107: Home | Y107: MIA | Z107: 0.12243848
J108: 4 | K108: LA | L108: Maliu Niuafe | M108: 3.2 | N108: Away | O108: SDL | P108: =VLOOKUP($N108,$F$3:$G$4,2,FALSE)+VLOOKUP($L108,$B$20:$C$150,2,FALSE)+VLOOKUP($O108,$A$6:$B$16,2,FALSE) -> 3.6210704 | Q108: =IFERROR(($M108-$P108)^2,"") -> 0.17730027 | R108: {=SUMPRODUCT((J108=$J$7:$J$1000)*(P108<$P$7:$P$1000))+1} -> 18 | T108: 15 | U108: LA | V108: Dane Zander | W108: NULL | X108: Home | Y108: MIA | Z108: -1.1409229
J109: 4 | K109: HOU | L109: Val Lee-Lo | M109: 2.9 | N109: Away | O109: UTAH | P109: =VLOOKUP($N109,$F$3:$G$4,2,FALSE)+VLOOKUP($L109,$B$20:$C$150,2,FALSE)+VLOOKUP($O109,$A$6:$B$16,2,FALSE) -> 0.80884586 | Q109: =IFERROR(($M109-$P109)^2,"") -> 4.3729256 | R109: {=SUMPRODUCT((J109=$J$7:$J$1000)*(P109<$P$7:$P$1000))+1} -> 26 | T109: 15 | U109: LA | V109: Declan Leaney | W109: NULL | X109: Home | Y109: MIA | Z109: 6.962844
J110: 4 | K110: CHI | L110: Janus Venter | M110: 2.8 | N110: Away | O110: MIA | P110: =VLOOKUP($N110,$F$3:$G$4,2,FALSE)+VLOOKUP($L110,$B$20:$C$150,2,FALSE)+VLOOKUP($O110,$A$6:$B$16,2,FALSE) -> 3.7681384 | Q110: =IFERROR(($M110-$P110)^2,"") -> 0.93729197 | R110: {=SUMPRODUCT((J110=$J$7:$J$1000)*(P110<$P$7:$P$1000))+1} -> 16 | T110: 15 | U110: LA | V110: Franco van den Berg | W110: NULL | X110: Home | Y110: MIA | Z110: 2.2061847
J111: 4 | K111: CHI | L111: Faka'osi Pifeleti | M111: 2.7 | N111: Away | O111: MIA | P111: =VLOOKUP($N111,$F$3:$G$4,2,FALSE)+VLOOKUP($L111,$B$20:$C$150,2,FALSE)+VLOOKUP($O111,$A$6:$B$16,2,FALSE) -> 2.0285831 | Q111: =IFERROR(($M111-$P111)^2,"") -> 0.45080069 | R111: {=SUMPRODUCT((J111=$J$7:$J$1000)*(P111<$P$7:$P$1000))+1} -> 23 | T111: 15 | U111: LA | V111: Justus Tavai | W111: NULL | X111: Home | Y111: MIA | Z111: 7.4659463
J112: 4 | K112: SEA | L112: Juan Pablo Zeiss | M112: 2.5 | N112: Home | O112: NEFJ | P112: =VLOOKUP($N112,$F$3:$G$4,2,FALSE)+VLOOKUP($L112,$B$20:$C$150,2,FALSE)+VLOOKUP($O112,$A$6:$B$16,2,FALSE) -> 3.259937 | Q112: =IFERROR(($M112-$P112)^2,"") -> 0.57750425 | R112: {=SUMPRODUCT((J112=$J$7:$J$1000)*(P112<$P$7:$P$1000))+1} -> 19 | T112: 15 | U112: LA | V112: Maliu Niuafe | W112: NULL | X112: Home | Y112: MIA | Z112: 2.0799089
J113: 4 | K113: SDL | L113: Payton Telea-Ilalio | M113: 2.4 | N113: Home | O113: LA | P113: =VLOOKUP($N113,$F$3:$G$4,2,FALSE)+VLOOKUP($L113,$B$20:$C$150,2,FALSE)+VLOOKUP($O113,$A$6:$B$16,2,FALSE) -> 5.0416528 | Q113: =IFERROR(($M113-$P113)^2,"") -> 6.9783296 | R113: {=SUMPRODUCT((J113=$J$7:$J$1000)*(P113<$P$7:$P$1000))+1} -> 10 | T113: 15 | U113: LA | V113: Mike Sosene Feagai | W113: NULL | X113: Home | Y113: MIA | Z113: 4.729032
J114: 4 | K114: NEFJ | L114: Jone Koroiduadua | M114: 2.3 | N114: Away | O114: SEA | P114: =VLOOKUP($N114,$F$3:$G$4,2,FALSE)+VLOOKUP($L114,$B$20:$C$150,2,FALSE)+VLOOKUP($O114,$A$6:$B$16,2,FALSE) -> -0.58174197 | Q114: =IFERROR(($M114-$P114)^2,"") -> 8.3044368 | R114: {=SUMPRODUCT((J114=$J$7:$J$1000)*(P114<$P$7:$P$1000))+1} -> 29 | T114: 15 | U114: MIA | V114: Alec McDonnell | W114: NULL | X114: Away | Y114: LA | Z114: 0.053819228
J115: 4 | K115: LA | L115: Dane Zander | M115: 2.1 | N115: Away | O115: SDL | P115: =VLOOKUP($N115,$F$3:$G$4,2,FALSE)+VLOOKUP($L115,$B$20:$C$150,2,FALSE)+VLOOKUP($O115,$A$6:$B$16,2,FALSE) -> 0.40023852 | Q115: =IFERROR(($M115-$P115)^2,"") -> 2.8891891 | R115: {=SUMPRODUCT((J115=$J$7:$J$1000)*(P115<$P$7:$P$1000))+1} -> 28 | T115: 15 | U115: MIA | V115: Alex Tucci | W115: NULL | X115: Away | Y115: LA | Z115: 6.9194208
... J237: 9 | K237: OGDC | L237: Facundo Gattas | M237: 14.8 | N237: Away | O237: NOLA | P237: =VLOOKUP($N237,$F$3:$G$4,2,FALSE)+VLOOKUP($L237,$B$20:$C$150,2,FALSE)+VLOOKUP($O237,$A$6:$B$16,2,FALSE) -> 5.3877669 | Q237: =IFERROR(($M237-$P237)^2,"") -> 88.590132 | R237: {=SUMPRODUCT((J237=$J$7:$J$1000)*(P237<$P$7:$P$1000))+1} -> 10 | T237: 16 | U237: UTAH | V237: Tuvere Vugakoto | W237: NULL | X237: Home | Y237: ARC | Z237: 0.9786768
J238: 9 | K238: CHI | L238: Dylan Fawsitt | M238: 12.9 | N238: Home | O238: ARC | P238: =VLOOKUP($N238,$F$3:$G$4,2,FALSE)+VLOOKUP($L238,$B$20:$C$150,2,FALSE)+VLOOKUP($O238,$A$6:$B$16,2,FALSE) -> 8.4489946 | Q238: =IFERROR(($M238-$P238)^2,"") -> 19.811449 | R238: {=SUMPRODUCT((J238=$J$7:$J$1000)*(P238<$P$7:$P$1000))+1} -> 2
J239: 9 | K239: UTAH | L239: Liam Coltman | M239: 8 | N239: Away | O239: LA | P239: =VLOOKUP($N239,$F$3:$G$4,2,FALSE)+VLOOKUP($L239,$B$20:$C$150,2,FALSE)+VLOOKUP($O239,$A$6:$B$16,2,FALSE) -> 9.5085913 | Q239: =IFERROR(($M239-$P239)^2,"") -> 2.2758477 | R239: {=SUMPRODUCT((J239=$J$7:$J$1000)*(P239<$P$7:$P$1000))+1} -> 1
J240: 9 | K240: HOU | L240: Pita Anae-Ah Sue | M240: 6.6 | N240: Away | O240: MIA | P240: =VLOOKUP($N240,$F$3:$G$4,2,FALSE)+VLOOKUP($L240,$B$20:$C$150,2,FALSE)+VLOOKUP($O240,$A$6:$B$16,2,FALSE) -> 8.404957 | Q240: =IFERROR(($M240-$P240)^2,"") -> 3.2578696 | R240: {=SUMPRODUCT((J240=$J$7:$J$1000)*(P240<$P$7:$P$1000))+1} -> 3
J241: 9 | K241: ARC | L241: Connor Robinson | M241: 5.7 | N241: Away | O241: CHI | P241: =VLOOKUP($N241,$F$3:$G$4,2,FALSE)+VLOOKUP($L241,$B$20:$C$150,2,FALSE)+VLOOKUP($O241,$A$6:$B$16,2,FALSE) -> 5.4771936 | Q241: =IFERROR(($M241-$P241)^2,"") -> 0.049642711 | R241: {=SUMPRODUCT((J241=$J$7:$J$1000)*(P241<$P$7:$P$1000))+1} -> 9
J242: 9 | K242: CHI | L242: Ignacio Peculo | M242: 4.7 | N242: Home | O242: ARC | P242: =VLOOKUP($N242,$F$3:$G$4,2,FALSE)+VLOOKUP($L242,$B$20:$C$150,2,FALSE)+VLOOKUP($O242,$A$6:$B$16,2,FALSE) -> 6.1204165 | Q242: =IFERROR(($M242-$P242)^2,"") -> 2.0175831 | R242: {=SUMPRODUCT((J242=$J$7:$J$1000)*(P242<$P$7:$P$1000))+1} -> 7
J243: 9 | K243: SDL | L243: Darcy Breen | M243: 4.7 | N243: Away | O243: NEFJ | P243: =VLOOKUP($N243,$F$3:$G$4,2,FALSE)+VLOOKUP($L243,$B$20:$C$150,2,FALSE)+VLOOKUP($O243,$A$6:$B$16,2,FALSE) -> 4.2396636 | Q243: =IFERROR(($M243-$P243)^2,"") -> 0.21190958 | R243: {=SUMPRODUCT((J243=$J$7:$J$1000)*(P243<$P$7:$P$1000))+1} -> 12
J244: 9 | K244: SDL | L244: Payton Telea-Ilalio | M244: 4.7 | N244: Away | O244: NEFJ | P244: =VLOOKUP($N244,$F$3:$G$4,2,FALSE)+VLOOKUP($L244,$B$20:$C$150,2,FALSE)+VLOOKUP($O244,$A$6:$B$16,2,FALSE) -> 4.7539709 | Q244: =IFERROR(($M244-$P244)^2,"") -> 0.0029128632 | R244: {=SUMPRODUCT((J244=$J$7:$J$1000)*(P244<$P$7:$P$1000))+1} -> 11
J245: 9 | K245: UTAH | L245: Tonga Kofe | M245: 4.2 | N245: Away | O245: LA | P245: =VLOOKUP($N245,$F$3:$G$4,2,FALSE)+VLOOKUP($L245,$B$20:$C$150,2,FALSE)+VLOOKUP($O245,$A$6:$B$16,2,FALSE) -> 3.6975346 | Q245: =IFERROR(($M245-$P245)^2,"") -> 0.25247144 | R245: {=SUMPRODUCT((J245=$J$7:$J$1000)*(P245<$P$7:$P$1000))+1} -> 14
J246: 9 | K246: LA | L246: Ben Sugars | M246: 3.8 | N246: Home | O246: UTAH | P246: =VLOOKUP($N246,$F$3:$G$4,2,FALSE)+VLOOKUP($L246,$B$20:$C$150,2,FALSE)+VLOOKUP($O246,$A$6:$B$16,2,FALSE) -> 3.4281833 | Q246: =IFERROR(($M246-$P246)^2,"") -> 0.13824763 | R246: {=SUMPRODUCT((J246=$J$7:$J$1000)*(P246<$P$7:$P$1000))+1} -> 17
J247: 9 | K247: NOLA | L247: Joe Taufete'e | M247: 3.7 | N247: Home | O247: OGDC | P247: =VLOOKUP($N247,$F$3:$G$4,2,FALSE)+VLOOKUP($L247,$B$20:$C$150,2,FALSE)+VLOOKUP($O247,$A$6:$B$16,2,FALSE) -> 3.1749763 | Q247: =IFERROR(($M247-$P247)^2,"") -> 0.27564985 | R247: {=SUMPRODUCT((J247=$J$7:$J$1000)*(P247<$P$7:$P$1000))+1} -> 20
J248: 9 | K248: UTAH | L248: Aki Seiuli | M248: 3.7 | N248: Away | O248: LA | P248: =VLOOKUP($N248,$F$3:$G$4,2,FALSE)+VLOOKUP($L248,$B$20:$C$150,2,FALSE)+VLOOKUP($O248,$A$6:$B$16,2,FALSE) -> 6.3197173 | Q248: =IFERROR(($M248-$P248)^2,"") -> 6.8629185 | R248: {=SUMPRODUCT((J248=$J$7:$J$1000)*(P248<$P$7:$P$1000))+1} -> 6
J249: 9 | K249: HOU | L249: Ezekiel Lindenmuth | M249: 3.3 | N249: Away | O249: MIA | P249: =VLOOKUP($N249,$F$3:$G$4,2,FALSE)+VLOOKUP($L249,$B$20:$C$150,2,FALSE)+VLOOKUP($O249,$A$6:$B$16,2,FALSE) -> 3.6990069 | Q249: =IFERROR(($M249-$P249)^2,"") -> 0.15920653 | R249: {=SUMPRODUCT((J249=$J$7:$J$1000)*(P249<$P$7:$P$1000))+1} -> 13
... J399: 13 | K399: NEFJ | L399: Jone Koroiduadua | M399: -5.9 | N399: Home | O399: CHI | P399: =VLOOKUP($N399,$F$3:$G$4,2,FALSE)+VLOOKUP($L399,$B$20:$C$150,2,FALSE)+VLOOKUP($O399,$A$6:$B$16,2,FALSE) -> 0.070180006 | Q399: =IFERROR(($M399-$P399)^2,"") -> 35.643049 | R399: {=SUMPRODUCT((J399=$J$7:$J$1000)*(P399<$P$7:$P$1000))+1} -> 29
J400: 14 | K400: ARC | L400: Alex Maughan | M400: NULL | N400: Home | O400: OGDC | P400: =VLOOKUP($N400,$F$3:$G$4,2,FALSE)+VLOOKUP($L400,$B$20:$C$150,2,FALSE)+VLOOKUP($O400,$A$6:$B$16,2,FALSE) -> 2.8843747 | Q400: =IFERROR(($M400-$P400)^2,"") | R400: {=SUMPRODUCT((J400=$J$7:$J$1000)*(P400<$P$7:$P$1000))+1} -> 48
J401: 14 | K401: ARC | L401: Alexander Hernandez | M401: NULL | N401: Home | O401: OGDC | P401: =VLOOKUP($N401,$F$3:$G$4,2,FALSE)+VLOOKUP($L401,$B$20:$C$150,2,FALSE)+VLOOKUP($O401,$A$6:$B$16,2,FALSE) -> 1.3514586 | Q401: =IFERROR(($M401-$P401)^2,"") | R401: {=SUMPRODUCT((J401=$J$7:$J$1000)*(P401<$P$7:$P$1000))+1} -> 65
J402: 14 | K402: ARC | L402: Connor Robinson | M402: NULL | N402: Home | O402: OGDC | P402: =VLOOKUP($N402,$F$3:$G$4,2,FALSE)+VLOOKUP($L402,$B$20:$C$150,2,FALSE)+VLOOKUP($O402,$A$6:$B$16,2,FALSE) -> 5.0191906 | Q402: =IFERROR(($M402-$P402)^2,"") | R402: {=SUMPRODUCT((J402=$J$7:$J$1000)*(P402<$P$7:$P$1000))+1} -> 28
J403: 14 | K403: ARC | L403: Dan Hanson | M403: NULL | N403: Home | O403: OGDC | P403: =VLOOKUP($N403,$F$3:$G$4,2,FALSE)+VLOOKUP($L403,$B$20:$C$150,2,FALSE)+VLOOKUP($O403,$A$6:$B$16,2,FALSE) -> 1.435512 | Q403: =IFERROR(($M403-$P403)^2,"") | R403: {=SUMPRODUCT((J403=$J$7:$J$1000)*(P403<$P$7:$P$1000))+1} -> 64
J404: 14 | K404: ARC | L404: Ethan Howard | M404: NULL | N404: Home | O404: OGDC | P404: =VLOOKUP($N404,$F$3:$G$4,2,FALSE)+VLOOKUP($L404,$B$20:$C$150,2,FALSE)+VLOOKUP($O404,$A$6:$B$16,2,FALSE) -> 5.2756223 | Q404: =IFERROR(($M404-$P404)^2,"") | R404: {=SUMPRODUCT((J404=$J$7:$J$1000)*(P404<$P$7:$P$1000))+1} -> 27
J405: 14 | K405: ARC | L405: Jake Turnbull | M405: NULL | N405: Home | O405: OGDC | P405: =VLOOKUP($N405,$F$3:$G$4,2,FALSE)+VLOOKUP($L405,$B$20:$C$150,2,FALSE)+VLOOKUP($O405,$A$6:$B$16,2,FALSE) -> 3.0778227 | Q405: =IFERROR(($M405-$P405)^2,"") | R405: {=SUMPRODUCT((J405=$J$7:$J$1000)*(P405<$P$7:$P$1000))+1} -> 47
J406: 14 | K406: ARC | L406: Joe Apikotoa | M406: NULL | N406: Home | O406: OGDC | P406: =VLOOKUP($N406,$F$3:$G$4,2,FALSE)+VLOOKUP($L406,$B$20:$C$150,2,FALSE)+VLOOKUP($O406,$A$6:$B$16,2,FALSE) -> 4.4938413 | Q406: =IFERROR(($M406-$P406)^2,"") | R406: {=SUMPRODUCT((J406=$J$7:$J$1000)*(P406<$P$7:$P$1000))+1} -> 33
J407: 14 | K407: ARC | L407: Stephan Bernal-Wendt | M407: NULL | N407: Home | O407: OGDC | P407: =VLOOKUP($N407,$F$3:$G$4,2,FALSE)+VLOOKUP($L407,$B$20:$C$150,2,FALSE)+VLOOKUP($O407,$A$6:$B$16,2,FALSE) -> 2.4237843 | Q407: =IFERROR(($M407-$P407)^2,"") | R407: {=SUMPRODUCT((J407=$J$7:$J$1000)*(P407<$P$7:$P$1000))+1} -> 54
J408: 14 | K408: CHI | L408: Charlie Abel | M408: NULL | N408: Home | O408: LA | P408: =VLOOKUP($N408,$F$3:$G$4,2,FALSE)+VLOOKUP($L408,$B$20:$C$150,2,FALSE)+VLOOKUP($O408,$A$6:$B$16,2,FALSE) -> 4.0947931 | Q408: =IFERROR(($M408-$P408)^2,"") | R408: {=SUMPRODUCT((J408=$J$7:$J$1000)*(P408<$P$7:$P$1000))+1} -> 36
J409: 14 | K409: CHI | L409: Dylan Fawsitt | M409: NULL | N409: Home | O409: LA | P409: =VLOOKUP($N409,$F$3:$G$4,2,FALSE)+VLOOKUP($L409,$B$20:$C$150,2,FALSE)+VLOOKUP($O409,$A$6:$B$16,2,FALSE) -> 8.2413372 | Q409: =IFERROR(($M409-$P409)^2,"") | R409: {=SUMPRODUCT((J409=$J$7:$J$1000)*(P409<$P$7:$P$1000))+1} -> 4
J410: 14 | K410: CHI | L410: Faka'osi Pifeleti | M410: NULL | N410: Home | O410: LA | P410: =VLOOKUP($N410,$F$3:$G$4,2,FALSE)+VLOOKUP($L410,$B$20:$C$150,2,FALSE)+VLOOKUP($O410,$A$6:$B$16,2,FALSE) -> 2.807155 | Q410: =IFERROR(($M410-$P410)^2,"") | R410: {=SUMPRODUCT((J410=$J$7:$J$1000)*(P410<$P$7:$P$1000))+1} -> 50
J411: 14 | K411: CHI | L411: Ignacio Peculo | M411: NULL | N411: Home | O411: LA | P411: =VLOOKUP($N411,$F$3:$G$4,2,FALSE)+VLOOKUP($L411,$B$20:$C$150,2,FALSE)+VLOOKUP($O411,$A$6:$B$16,2,FALSE) -> 5.9127591 | Q411: =IFERROR(($M411-$P411)^2,"") | R411: {=SUMPRODUCT((J411=$J$7:$J$1000)*(P411<$P$7:$P$1000))+1} -> 19
... J630: 16 | K630: UTAH | L630: Tuvere Vugakoto | M630: NULL | N630: Home | O630: ARC | P630: =VLOOKUP($N630,$F$3:$G$4,2,FALSE)+VLOOKUP($L630,$B$20:$C$150,2,FALSE)+VLOOKUP($O630,$A$6:$B$16,2,FALSE) -> 0.9786768 | Q630: =IFERROR(($M630-$P630)^2,"") | R630: {=SUMPRODUCT((J630=$J$7:$J$1000)*(P630<$P$7:$P$1000))+1} -> 70

Sheet SRvsDef
A1: SR vs Def 2025 | F1: Finished Week: | G1: 12
B2: 0
A3: Mean: | B3: =AVERAGE(B6:B49) -> 2.8834744e-08 | F3: Home | G3: 0.0072205678
A4: (highest rank is most helpful matchup) | F4: Away | G4: =-G3 -> -0.0072205678
A5: Team | B5: Rating | C5: Rank | Q5: =SUM($Q$7:$Q1000) -> 1908.2806
A6: ARC | B6: 0.80302206 | C6: =RANK($B6,$B$6:$B$16,0) -> 1 | J6: Rnd | K6: Team | L6: Player | M6: Points | N6: home | O6: Opp | P6: Forecast | Q6: Squared Error | R6: GroupRnk | T6: Remaining Games for ROFS Calc | AA6: Players | AB6: Rnd
A7: OGDC | B7: 0.60834287 | C7: =RANK($B7,$B$6:$B$16,0) -> 2 | J7: 1 | K7: MIA | L7: Mauro Rebussone | M7: 15.3 | N7: Home | O7: OGDC | P7: =VLOOKUP($N7,$F$3:$G$4,2,FALSE)+VLOOKUP($L7,$B$20:$C$150,2,FALSE)+VLOOKUP($O7,$A$6:$B$16,2,FALSE) -> 5.7876544 | Q7: =IFERROR(($M7-$P7)^2,"") -> 90.484719 | R7: {=SUMPRODUCT((J7=$J$7:$J$1000)*(P7<$P$7:$P$1000))+1} -> 3 | T7: {=_xlfn._xlws.FILTER($J$7:$P$10000,($J$7:$J$10000>$G$1)*($J$7:$J$10000<18))} -> 13 | U7: ARC | V7: Alejandro Martinez Tapia | W7: NULL | X7: Away | Y7: LA | Z7: 5.7267055 | AA7: {=_xlfn._xlws.SORT(_xlfn.UNIQUE($L$7:$L$10000))} -> Alejandro Martinez Tapia | AB7: {=COUNT(_xlfn._xlws.FILTER($J$7:$J$10000,($L$7:$L$10000=AA7)*($M$7:$M$10000<>"NULL")*($J$7:$J$10000 >= ($G$1-5))))/5} -> 0.6
A8: SDL | B8: 0.58397849 | C8: =RANK($B8,$B$6:$B$16,0) -> 3 | J8: 1 | K8: SDL | L8: Jed Holloway | M8: 12.9 | N8: Home | O8: SEA | P8: =VLOOKUP($N8,$F$3:$G$4,2,FALSE)+VLOOKUP($L8,$B$20:$C$150,2,FALSE)+VLOOKUP($O8,$A$6:$B$16,2,FALSE) -> 8.1535589 | Q8: =IFERROR(($M8-$P8)^2,"") -> 22.528703 | R8: {=SUMPRODUCT((J8=$J$7:$J$1000)*(P8<$P$7:$P$1000))+1} -> 1 | T8: 13 | U8: ARC | V8: Javon Camp Villalovos | W8: NULL | X8: Away | Y8: LA | Z8: 2.5835745 | AA8: Bill Whiteside | AB8: {=COUNT(_xlfn._xlws.FILTER($J$7:$J$10000,($L$7:$L$10000=AA8)*($M$7:$M$10000<>"NULL")*($J$7:$J$10000 >= ($G$1-5))))/5} -> 0.4
A9: SEA | B9: 0.18479679 | C9: =RANK($B9,$B$6:$B$16,0) -> 4 | J9: 1 | K9: CHI | L9: James Scott | M9: 11 | N9: Away | O9: HOU | P9: =VLOOKUP($N9,$F$3:$G$4,2,FALSE)+VLOOKUP($L9,$B$20:$C$150,2,FALSE)+VLOOKUP($O9,$A$6:$B$16,2,FALSE) -> 5.1375299 | Q9: =IFERROR(($M9-$P9)^2,"") -> 34.368556 | R9: {=SUMPRODUCT((J9=$J$7:$J$1000)*(P9<$P$7:$P$1000))+1} -> 7 | T9: 13 | U9: ARC | V9: Javon Camp Villalovos | W9: NULL | X9: Away | Y9: SDL | Z9: 3.1678253 | AA9: Braemar Murray | AB9: {=COUNT(_xlfn._xlws.FILTER($J$7:$J$10000,($L$7:$L$10000=AA9)*($M$7:$M$10000<>"NULL")*($J$7:$J$10000 >= ($G$1-5))))/5} -> 0.4
A10: CHI | B10: 0.1265176 | C10: =RANK($B10,$B$6:$B$16,0) -> 5 | J10: 1 | K10: NEFJ | L10: Sam Caird | M10: 9.3 | N10: Away | O10: LA | P10: =VLOOKUP($N10,$F$3:$G$4,2,FALSE)+VLOOKUP($L10,$B$20:$C$150,2,FALSE)+VLOOKUP($O10,$A$6:$B$16,2,FALSE) -> 5.0081578 | Q10: =IFERROR(($M10-$P10)^2,"") -> 18.41991 | R10: {=SUMPRODUCT((J10=$J$7:$J$1000)*(P10<$P$7:$P$1000))+1} -> 8 | T10: 13 | U10: ARC | V10: Mikey Grandy | W10: NULL | X10: Away | Y10: LA | Z10: 4.5574912 | AA10: Brandon Harvey | AB10: {=COUNT(_xlfn._xlws.FILTER($J$7:$J$10000,($L$7:$L$10000=AA10)*($M$7:$M$10000<>"NULL")*($J$7:$J$10000 >= ($G$1-5))))/5} -> 0.4
A11: LA | B11: -0.00027227026 | C11: =RANK($B11,$B$6:$B$16,0) -> 6 | J11: 1 | K11: LA | L11: Jason Damm | M11: 8.4 | N11: Home | O11: NEFJ | P11: =VLOOKUP($N11,$F$3:$G$4,2,FALSE)+VLOOKUP($L11,$B$20:$C$150,2,FALSE)+VLOOKUP($O11,$A$6:$B$16,2,FALSE) -> 7.4958213 | Q11: =IFERROR(($M11-$P11)^2,"") -> 0.81753904 | R11: {=SUMPRODUCT((J11=$J$7:$J$1000)*(P11<$P$7:$P$1000))+1} -> 2 | T11: 13 | U11: ARC | V11: Sam Golla | W11: NULL | X11: Away | Y11: LA | Z11: 6.3414277 | AA11: Callum Botchar | AB11: {=COUNT(_xlfn._xlws.FILTER($J$7:$J$10000,($L$7:$L$10000=AA11)*($M$7:$M$10000<>"NULL")*($J$7:$J$10000 >= ($G$1-5))))/5} -> 0.2
A12: HOU | B12: -0.017425638 | C12: =RANK($B12,$B$6:$B$16,0) -> 7 | J12: 1 | K12: NEFJ | L12: Piers von Dadelszen | M12: 7.2 | N12: Away | O12: LA | P12: =VLOOKUP($N12,$F$3:$G$4,2,FALSE)+VLOOKUP($L12,$B$20:$C$150,2,FALSE)+VLOOKUP($O12,$A$6:$B$16,2,FALSE) -> 3.929463 | Q12: =IFERROR(($M12-$P12)^2,"") -> 10.696412 | R12: {=SUMPRODUCT((J12=$J$7:$J$1000)*(P12<$P$7:$P$1000))+1} -> 13 | T12: 13 | U12: ARC | V12: Shawn Clark | W12: NULL | X12: Away | Y12: LA | Z12: 3.1315344 | AA12: Cam Dolan | AB12: {=COUNT(_xlfn._xlws.FILTER($J$7:$J$10000,($L$7:$L$10000=AA12)*($M$7:$M$10000<>"NULL")*($J$7:$J$10000 >= ($G$1-5))))/5} -> 0.8
A13: NEFJ | B13: -0.12054481 | C13: =RANK($B13,$B$6:$B$16,0) -> 8 | J13: 1 | K13: SEA | L13: Rhyno Herbst | M13: 5.3 | N13: Away | O13: SDL | P13: =VLOOKUP($N13,$F$3:$G$4,2,FALSE)+VLOOKUP($L13,$B$20:$C$150,2,FALSE)+VLOOKUP($O13,$A$6:$B$16,2,FALSE) -> 4.9861334 | Q13: =IFERROR(($M13-$P13)^2,"") -> 0.098512222 | R13: {=SUMPRODUCT((J13=$J$7:$J$1000)*(P13<$P$7:$P$1000))+1} -> 9 | T13: 13 | U13: ARC | V13: Viliami Vuli | W13: NULL | X13: Away | Y13: LA | Z13: 4.946202 | AA13: Charlie Hewitt | AB13: {=COUNT(_xlfn._xlws.FILTER($J$7:$J$10000,($L$7:$L$10000=AA13)*($M$7:$M$10000<>"NULL")*($J$7:$J$10000 >= ($G$1-5))))/5} -> 0.4
A14: MIA | B14: -0.5956791 | C14: =RANK($B14,$B$6:$B$16,0) -> 9 | J14: 1 | K14: HOU | L14: Nathan Den Hoedt | M14: 4 | N14: Home | O14: CHI | P14: =VLOOKUP($N14,$F$3:$G$4,2,FALSE)+VLOOKUP($L14,$B$20:$C$150,2,FALSE)+VLOOKUP($O14,$A$6:$B$16,2,FALSE) -> 5.4080251 | Q14: =IFERROR(($M14-$P14)^2,"") -> 1.9825346 | R14: {=SUMPRODUCT((J14=$J$7:$J$1000)*(P14<$P$7:$P$1000))+1} -> 6 | T14: 13 | U14: CHI | V14: Hamish Bain | W14: NULL | X14: Away | Y14: NEFJ | Z14: 4.1432377 | AA14: Chase Jones | AB14: {=COUNT(_xlfn._xlws.FILTER($J$7:$J$10000,($L$7:$L$10000=AA14)*($M$7:$M$10000<>"NULL")*($J$7:$J$10000 >= ($G$1-5))))/5} -> 0.4
A15: UTAH | B15: -0.76631347 | C15: =RANK($B15,$B$6:$B$16,0) -> 10 | J15: 1 | K15: MIA | L15: Federico Gutíerrez | M15: 3.9 | N15: Home | O15: OGDC | P15: =VLOOKUP($N15,$F$3:$G$4,2,FALSE)+VLOOKUP($L15,$B$20:$C$150,2,FALSE)+VLOOKUP($O15,$A$6:$B$16,2,FALSE) -> 3.7582235 | Q15: =IFERROR(($M15-$P15)^2,"") -> 0.02010059 | R15: {=SUMPRODUCT((J15=$J$7:$J$1000)*(P15<$P$7:$P$1000))+1} -> 14 | T15: 13 | U15: CHI | V15: James Scott | W15: NULL | X15: Away | Y15: NEFJ | Z15: 5.0344107 | AA15: Conor Keys | AB15: {=COUNT(_xlfn._xlws.FILTER($J$7:$J$10000,($L$7:$L$10000=AA15)*($M$7:$M$10000<>"NULL")*($J$7:$J$10000 >= ($G$1-5))))/5} -> 0
A16: NOLA | B16: -0.80642221 | C16: =RANK($B16,$B$6:$B$16,0) -> 11 | J16: 1 | K16: OGDC | L16: Tevita Naqali | M16: 3.3 | N16: Away | O16: MIA | P16: =VLOOKUP($N16,$F$3:$G$4,2,FALSE)+VLOOKUP($L16,$B$20:$C$150,2,FALSE)+VLOOKUP($O16,$A$6:$B$16,2,FALSE) -> 5.5202493 | Q16: =IFERROR(($M16-$P16)^2,"") -> 4.929507 | R16: {=SUMPRODUCT((J16=$J$7:$J$1000)*(P16<$P$7:$P$1000))+1} -> 5 | T16: 13 | U16: CHI | V16: Mason Flesch | W16: NULL | X16: Away | Y16: NEFJ | Z16: 5.20125 | AA16: Federico Gutíerrez | AB16: {=COUNT(_xlfn._xlws.FILTER($J$7:$J$10000,($L$7:$L$10000=AA16)*($M$7:$M$10000<>"NULL")*($J$7:$J$10000 >= ($G$1-5))))/5} -> 0.2
J17: 1 | K17: ARC | L17: Sam Golla | M17: 2.5 | N17: Away | O17: NOLA | P17: =VLOOKUP($N17,$F$3:$G$4,2,FALSE)+VLOOKUP($L17,$B$20:$C$150,2,FALSE)+VLOOKUP($O17,$A$6:$B$16,2,FALSE) -> 5.5352777 | Q17: =IFERROR(($M17-$P17)^2,"") -> 9.2129109 | R17: {=SUMPRODUCT((J17=$J$7:$J$1000)*(P17<$P$7:$P$1000))+1} -> 4 | T17: 13 | U17: HOU | V17: Johan Momsen | W17: NULL | X17: Away | Y17: SDL | Z17: 6.1758772 | AA17: Frank Lochore | AB17: {=COUNT(_xlfn._xlws.FILTER($J$7:$J$10000,($L$7:$L$10000=AA17)*($M$7:$M$10000<>"NULL")*($J$7:$J$10000 >= ($G$1-5))))/5} -> 0.8
J18: 1 | K18: OGDC | L18: Rob Harley | M18: 2.5 | N18: Away | O18: MIA | P18: =VLOOKUP($N18,$F$3:$G$4,2,FALSE)+VLOOKUP($L18,$B$20:$C$150,2,FALSE)+VLOOKUP($O18,$A$6:$B$16,2,FALSE) -> 3.6748017 | Q18: =IFERROR(($M18-$P18)^2,"") -> 1.380159 | R18: {=SUMPRODUCT((J18=$J$7:$J$1000)*(P18<$P$7:$P$1000))+1} -> 15 | T18: 13 | U18: HOU | V18: Justin Basson | W18: NULL | X18: Away | Y18: SDL | Z18: 3.0066136 | AA18: Gavin Thornbury | AB18: {=COUNT(_xlfn._xlws.FILTER($J$7:$J$10000,($L$7:$L$10000=AA18)*($M$7:$M$10000<>"NULL")*($J$7:$J$10000 >= ($G$1-5))))/5} -> 0.4
A19: PlayerID | B19: Player | C19: OverallRating | D19: OverallRank | E19: WeeklyRating | F19: WeeklyRank | G19: ROFSRating | H19: ROFSRank | I19: Last5GamesStart% | J19: 1 | K19: SDL | L19: Brandon Harvey | M19: 2.2 | N19: Home | O19: SEA | P19: =VLOOKUP($N19,$F$3:$G$4,2,FALSE)+VLOOKUP($L19,$B$20:$C$150,2,FALSE)+VLOOKUP($O19,$A$6:$B$16,2,FALSE) -> 2.1920463 | Q19: =IFERROR(($M19-$P19)^2,"") -> 6.3261607e-05 | R19: {=SUMPRODUCT((J19=$J$7:$J$1000)*(P19<$P$7:$P$1000))+1} -> 19 | T19: 13 | U19: HOU | V19: Nathan Den Hoedt | W19: NULL | X19: Away | Y19: SDL | Z19: 5.8510448 | AA19: Hamish Bain | AB19: {=COUNT(_xlfn._xlws.FILTER($J$7:$J$10000,($L$7:$L$10000=AA19)*($M$7:$M$10000<>"NULL")*($J$7:$J$10000 >= ($G$1-5))))/5} -> 1.2
A20: =VLOOKUP($B20, PlayerIDs!$A$1:$B$516, 2, FALSE) -> 841 | B20: Tim Anstee | C20: 14.408778 | D20: =RANK($C20,$C$20:$C$106) -> 1 | E20: {=IFERROR(VLOOKUP($B20,_xlfn._xlws.FILTER($L$7:$P$10000,$J$7:$J$10000=G$1+1),5, FALSE), 0)} -> 15.219021 | F20: =RANK(E20,$E$20:$E$100) -> 1 | G20: =SUMIF(V:Z,$B20,Z:Z) -> 58.577316 | H20: =RANK($G20,$G$20:$G$106) -> 1 | I20: {=COUNT(_xlfn._xlws.FILTER($J$7:$J$10000,($L$7:$L$10000=B20)*($M$7:$M$10000<>"NULL")*($J$7:$J$10000 >= ($G$1-4))))/5} -> 0.2 | J20: 1 | K20: ARC | L20: Shawn Clark | M20: 1.8 | N20: Away | O20: NOLA | P20: =VLOOKUP($N20,$F$3:$G$4,2,FALSE)+VLOOKUP($L20,$B$20:$C$150,2,FALSE)+VLOOKUP($O20,$A$6:$B$16,2,FALSE) -> 2.3253845 | Q20: =IFERROR(($M20-$P20)^2,"") -> 0.27602886 | R20: {=SUMPRODUCT((J20=$J$7:$J$1000)*(P20<$P$7:$P$1000))+1} -> 18 | T20: 13 | U20: LA | V20: Jason Damm | W20: NULL | X20: Home | Y20: ARC | Z20: 8.4193882 | AA20: Ignacio Dotti | AB20: {=COUNT(_xlfn._xlws.FILTER($J$7:$J$10000,($L$7:$L$10000=AA20)*($M$7:$M$10000<>"NULL")*($J$7:$J$10000 >= ($G$1-5))))/5} -> 0.2
A21: =VLOOKUP($B21, PlayerIDs!$A$1:$B$516, 2, FALSE) -> 730 | B21: Jed Holloway | C21: 7.9615415 | D21: =RANK($C21,$C$20:$C$106) -> 2 | E21: {=IFERROR(VLOOKUP($B21,_xlfn._xlws.FILTER($L$7:$P$10000,$J$7:$J$10000=G$1+1),5, FALSE), 0)} -> 7.9513364 | F21: =RANK(E21,$E$20:$E$100) -> 3 | G21: =SUMIF(V:Z,$B21,Z:Z) -> 23.449096 | H21: =RANK($G21,$G$20:$G$106) -> 6 | I21: {=COUNT(_xlfn._xlws.FILTER($J$7:$J$10000,($L$7:$L$10000=B21)*($M$7:$M$10000<>"NULL")*($J$7:$J$10000 >= ($G$1-4))))/5} -> 1 | J21: 1 | K21: SEA | L21: Malembe Mpofu | M21: 1.7 | N21: Away | O21: SDL | P21: =VLOOKUP($N21,$F$3:$G$4,2,FALSE)+VLOOKUP($L21,$B$20:$C$150,2,FALSE)+VLOOKUP($O21,$A$6:$B$16,2,FALSE) -> 3.597167 | Q21: =IFERROR(($M21-$P21)^2,"") -> 3.5992428 | R21: {=SUMPRODUCT((J21=$J$7:$J$1000)*(P21<$P$7:$P$1000))+1} -> 16 | T21: 13 | U21: LA | V21: Jurie van Vuuren | W21: NULL | X21: Home | Y21: ARC | Z21: 4.9275484 | AA21: Isaia Lotawa | AB21: {=COUNT(_xlfn._xlws.FILTER($J$7:$J$10000,($L$7:$L$10000=AA21)*($M$7:$M$10000<>"NULL")*($J$7:$J$10000 >= ($G$1-5))))/5} -> 0.2
A22: =VLOOKUP($B22, PlayerIDs!$A$1:$B$516, 2, FALSE) -> 635 | B22: OJ Noa | C22: 7.8910085 | D22: =RANK($C22,$C$20:$C$106) -> 3 | E22: {=IFERROR(VLOOKUP($B22,_xlfn._xlws.FILTER($L$7:$P$10000,$J$7:$J$10000=G$1+1),5, FALSE), 0)} -> 7.1174744 | F22: =RANK(E22,$E$20:$E$100) -> 4 | G22: =SUMIF(V:Z,$B22,Z:Z) -> 31.243729 | H22: =RANK($G22,$G$20:$G$106) -> 3 | I22: {=COUNT(_xlfn._xlws.FILTER($J$7:$J$10000,($L$7:$L$10000=B22)*($M$7:$M$10000<>"NULL")*($J$7:$J$10000 >= ($G$1-4))))/5} -> 0.6 | J22: 1 | K22: NOLA | L22: Callum Botchar | M22: 1.3 | N22: Home | O22: ARC | P22: =VLOOKUP($N22,$F$3:$G$4,2,FALSE)+VLOOKUP($L22,$B$20:$C$150,2,FALSE)+VLOOKUP($O22,$A$6:$B$16,2,FALSE) -> 4.569392 | Q22: =IFERROR(($M22-$P22)^2,"") -> 10.688924 | R22: {=SUMPRODUCT((J22=$J$7:$J$1000)*(P22<$P$7:$P$1000))+1} -> 11 | T22: 13 | U22: LA | V22: Lucas Bur | W22: NULL | X22: Home | Y22: ARC | Z22: 5.2223054 | AA22: James Rivers | AB22: {=COUNT(_xlfn._xlws.FILTER($J$7:$J$10000,($L$7:$L$10000=AA22)*($M$7:$M$10000<>"NULL")*($J$7:$J$10000 >= ($G$1-5))))/5} -> 0.2
A23: =VLOOKUP($B23, PlayerIDs!$A$1:$B$516, 2, FALSE) -> 199 | B23: Jason Damm | C23: 7.6091456 | D23: =RANK($C23,$C$20:$C$106) -> 4 | E23: {=IFERROR(VLOOKUP($B23,_xlfn._xlws.FILTER($L$7:$P$10000,$J$7:$J$10000=G$1+1),5, FALSE), 0)} -> 8.4193882 | F23: =RANK(E23,$E$20:$E$100) -> 2 | G23: =SUMIF(V:Z,$B23,Z:Z) -> 31.378786 | H23: =RANK($G23,$G$20:$G$106) -> 2 | I23: {=COUNT(_xlfn._xlws.FILTER($J$7:$J$10000,($L$7:$L$10000=B23)*($M$7:$M$10000<>"NULL")*($J$7:$J$10000 >= ($G$1-4))))/5} -> 0.6 | J23: 1 | K23: LA | L23: Reegan O'Gorman | M23: 0.8 | N23: Home | O23: NEFJ | P23: =VLOOKUP($N23,$F$3:$G$4,2,FALSE)+VLOOKUP($L23,$B$20:$C$150,2,FALSE)+VLOOKUP($O23,$A$6:$B$16,2,FALSE) -> 1.0384795 | Q23: =IFERROR(($M23-$P23)^2,"") -> 0.056872455 | R23: {=SUMPRODUCT((J23=$J$7:$J$1000)*(P23<$P$7:$P$1000))+1} -> 20 | T23: 13 | U23: LA | V23: Reegan O'Gorman | W23: NULL | X23: Home | Y23: ARC | Z23: 1.9620463 | AA23: James Scott | AB23: {=COUNT(_xlfn._xlws.FILTER($J$7:$J$10000,($L$7:$L$10000=AA23)*($M$7:$M$10000<>"NULL")*($J$7:$J$10000 >= ($G$1-5))))/5} -> 1
A24: =VLOOKUP($B24, PlayerIDs!$A$1:$B$516, 2, FALSE) -> 382 | B24: Sam Golla | C24: 6.3489205 | D24: =RANK($C24,$C$20:$C$106) -> 5 | E24: {=IFERROR(VLOOKUP($B24,_xlfn._xlws.FILTER($L$7:$P$10000,$J$7:$J$10000=G$1+1),5, FALSE), 0)} -> 6.3414277 | F24: =RANK(E24,$E$20:$E$100) -> 6 | G24: =SUMIF(V:Z,$B24,Z:Z) -> 25.363957 | H24: =RANK($G24,$G$20:$G$106) -> 5 | I24: {=COUNT(_xlfn._xlws.FILTER($J$7:$J$10000,($L$7:$L$10000=B24)*($M$7:$M$10000<>"NULL")*($J$7:$J$10000 >= ($G$1-4))))/5} -> 0.8 | J24: 1 | K24: CHI | L24: Hamish Bain | M24: -2.3 | N24: Away | O24: HOU | P24: =VLOOKUP($N24,$F$3:$G$4,2,FALSE)+VLOOKUP($L24,$B$20:$C$150,2,FALSE)+VLOOKUP($O24,$A$6:$B$16,2,FALSE) -> 4.2463569 | Q24: =IFERROR(($M24-$P24)^2,"") -> 42.854789 | R24: {=SUMPRODUCT((J24=$J$7:$J$1000)*(P24<$P$7:$P$1000))+1} -> 12 | T24: 13 | U24: LA | V24: Tim Anstee | W24: NULL | X24: Home | Y24: ARC | Z24: 15.219021 | AA24: Jason Damm | AB24: {=COUNT(_xlfn._xlws.FILTER($J$7:$J$10000,($L$7:$L$10000=AA24)*($M$7:$M$10000<>"NULL")*($J$7:$J$10000 >= ($G$1-5))))/5} -> 0.6
A25: =VLOOKUP($B25, PlayerIDs!$A$1:$B$516, 2, FALSE) -> 681 | B25: Frank Lochore | C25: 6.3344374 | D25: =RANK($C25,$C$20:$C$106) -> 6 | E25: {=IFERROR(VLOOKUP($B25,_xlfn._xlws.FILTER($L$7:$P$10000,$J$7:$J$10000=G$1+1),5, FALSE), 0)} -> 6.5264547 | F25: =RANK(E25,$E$20:$E$100) -> 5 | G25: =SUMIF(V:Z,$B25,Z:Z) -> 25.501721 | H25: =RANK($G25,$G$20:$G$106) -> 4 | I25: {=COUNT(_xlfn._xlws.FILTER($J$7:$J$10000,($L$7:$L$10000=B25)*($M$7:$M$10000<>"NULL")*($J$7:$J$10000 >= ($G$1-4))))/5} -> 0.8 | J25: 1 | K25: NOLA | L25: Cam Dolan | M25: -3 | N25: Home | O25: ARC | P25: =VLOOKUP($N25,$F$3:$G$4,2,FALSE)+VLOOKUP($L25,$B$20:$C$150,2,FALSE)+VLOOKUP($O25,$A$6:$B$16,2,FALSE) -> 4.6057972 | Q25: =IFERROR(($M25-$P25)^2,"") -> 57.848151 | R25: {=SUMPRODUCT((J25=$J$7:$J$1000)*(P25<$P$7:$P$1000))+1} -> 10 | T25: 13 | U25: MIA | V25: Braemar Murray | W25: NULL | X25: Away | Y25: NOLA | Z25: 2.3311116 | AA25: Javon Camp Villalovos | AB25: {=COUNT(_xlfn._xlws.FILTER($J$7:$J$10000,($L$7:$L$10000=AA25)*($M$7:$M$10000<>"NULL")*($J$7:$J$10000 >= ($G$1-5))))/5} -> 0.2
A26: =VLOOKUP($B26, PlayerIDs!$A$1:$B$516, 2, FALSE) -> 414 | B26: Tevita Naqali | C26: 6.123149 | D26: =RANK($C26,$C$20:$C$106) -> 7 | E26: {=IFERROR(VLOOKUP($B26,_xlfn._xlws.FILTER($L$7:$P$10000,$J$7:$J$10000=G$1+1),5, FALSE), 0)} -> 0 | F26: =RANK(E26,$E$20:$E$100) -> 51 | G26: =SUMIF(V:Z,$B26,Z:Z) -> 19.044431 | H26: =RANK($G26,$G$20:$G$106) -> 17 | I26: {=COUNT(_xlfn._xlws.FILTER($J$7:$J$10000,($L$7:$L$10000=B26)*($M$7:$M$10000<>"NULL")*($J$7:$J$10000 >= ($G$1-4))))/5} -> 0.6 | J26: 1 | K26: HOU | L26: Justin Basson | M26: -3.1 | N26: Home | O26: CHI | P26: =VLOOKUP($N26,$F$3:$G$4,2,FALSE)+VLOOKUP($L26,$B$20:$C$150,2,FALSE)+VLOOKUP($O26,$A$6:$B$16,2,FALSE) -> 2.5635938 | Q26: =IFERROR(($M26-$P26)^2,"") -> 32.076295 | R26: {=SUMPRODUCT((J26=$J$7:$J$1000)*(P26<$P$7:$P$1000))+1} -> 17 | T26: 13 | U26: MIA | V26: Federico Gutíerrez | W26: NULL | X26: Away | Y26: NOLA | Z26: 2.3290172 | AA26: Jay Tuivaiti | AB26: {=COUNT(_xlfn._xlws.FILTER($J$7:$J$10000,($L$7:$L$10000=AA26)*($M$7:$M$10000<>"NULL")*($J$7:$J$10000 >= ($G$1-5))))/5} -> 0.4
A27: =VLOOKUP($B27, PlayerIDs!$A$1:$B$516, 2, FALSE) -> 62 | B27: Chase Jones | C27: 6.1168229 | D27: =RANK($C27,$C$20:$C$106) -> 8 | E27: {=IFERROR(VLOOKUP($B27,_xlfn._xlws.FILTER($L$7:$P$10000,$J$7:$J$10000=G$1+1),5, FALSE), 0)} -> 5.5283644 | F27: =RANK(E27,$E$20:$E$100) -> 11 | G27: =SUMIF(V:Z,$B27,Z:Z) -> 17.122214 | H27: =RANK($G27,$G$20:$G$106) -> 25 | I27: {=COUNT(_xlfn._xlws.FILTER($J$7:$J$10000,($L$7:$L$10000=B27)*($M$7:$M$10000<>"NULL")*($J$7:$J$10000 >= ($G$1-4))))/5} -> 0.4 | J27: 2 | K27: SDL | L27: Vili Helu | M27: 13.5 | N27: Away | O27: ARC | P27: =VLOOKUP($N27,$F$3:$G$4,2,FALSE)+VLOOKUP($L27,$B$20:$C$150,2,FALSE)+VLOOKUP($O27,$A$6:$B$16,2,FALSE) -> 6.7542381 | Q27: =IFERROR(($M27-$P27)^2,"") -> 45.505304 | R27: {=SUMPRODUCT((J27=$J$7:$J$1000)*(P27<$P$7:$P$1000))+1} -> 3 | T27: 13 | U27: MIA | V27: Mauro Rebussone | W27: NULL | X27: Away | Y27: NOLA | Z27: 4.3584482 | AA27: Jed Holloway | AB27: {=COUNT(_xlfn._xlws.FILTER($J$7:$J$10000,($L$7:$L$10000=AA27)*($M$7:$M$10000<>"NULL")*($J$7:$J$10000 >= ($G$1-5))))/5} -> 1.2
A28: =VLOOKUP($B28, PlayerIDs!$A$1:$B$516, 2, FALSE) -> 442 | B28: Vili Helu | C28: 5.9584366 | D28: =RANK($C28,$C$20:$C$106) -> 9 | E28: {=IFERROR(VLOOKUP($B28,_xlfn._xlws.FILTER($L$7:$P$10000,$J$7:$J$10000=G$1+1),5, FALSE), 0)} -> 5.9482315 | F28: =RANK(E28,$E$20:$E$100) -> 8 | G28: =SUMIF(V:Z,$B28,Z:Z) -> 17.439781 | H28: =RANK($G28,$G$20:$G$106) -> 21 | I28: {=COUNT(_xlfn._xlws.FILTER($J$7:$J$10000,($L$7:$L$10000=B28)*($M$7:$M$10000<>"NULL")*($J$7:$J$10000 >= ($G$1-4))))/5} -> 0.4 | J28: 2 | K28: UTAH | L28: Matt Jenson | M28: 7.6 | N28: Away | O28: CHI | P28: =VLOOKUP($N28,$F$3:$G$4,2,FALSE)+VLOOKUP($L28,$B$20:$C$150,2,FALSE)+VLOOKUP($O28,$A$6:$B$16,2,FALSE) -> 5.041353 | Q28: =IFERROR(($M28-$P28)^2,"") -> 6.5466744 | R28: {=SUMPRODUCT((J28=$J$7:$J$1000)*(P28<$P$7:$P$1000))+1} -> 10 | T28: 13 | U28: MIA | V28: Rick Rose | W28: NULL | X28: Away | Y28: NOLA | Z28: 4.1840285 | AA28: Jero Gomez Vara | AB28: {=COUNT(_xlfn._xlws.FILTER($J$7:$J$10000,($L$7:$L$10000=AA28)*($M$7:$M$10000<>"NULL")*($J$7:$J$10000 >= ($G$1-5))))/5} -> 0.2
A29: =VLOOKUP($B29, PlayerIDs!$A$1:$B$516, 2, FALSE) -> 452 | B29: William Waguespack | C29: 5.9071775 | D29: =RANK($C29,$C$20:$C$106) -> 10 | E29: {=IFERROR(VLOOKUP($B29,_xlfn._xlws.FILTER($L$7:$P$10000,$J$7:$J$10000=G$1+1),5, FALSE), 0)} -> 5.318719 | F29: =RANK(E29,$E$20:$E$100) -> 13 | G29: =SUMIF(V:Z,$B29,Z:Z) -> 16.493278 | H29: =RANK($G29,$G$20:$G$106) -> 29 | I29: {=COUNT(_xlfn._xlws.FILTER($J$7:$J$10000,($L$7:$L$10000=B29)*($M$7:$M$10000<>"NULL")*($J$7:$J$10000 >= ($G$1-4))))/5} -> 0.4 | J29: 2 | K29: NOLA | L29: Cam Dolan | M29: 6.9 | N29: Away | O29: MIA | P29: =VLOOKUP($N29,$F$3:$G$4,2,FALSE)+VLOOKUP($L29,$B$20:$C$150,2,FALSE)+VLOOKUP($O29,$A$6:$B$16,2,FALSE) -> 3.1926549 | Q29: =IFERROR(($M29-$P29)^2,"") -> 13.744407 | R29: {=SUMPRODUCT((J29=$J$7:$J$1000)*(P29<$P$7:$P$1000))+1} -> 14 | T29: 13 | U29: MIA | V29: Tomás Casares | W29: NULL | X29: Away | Y29: NOLA | Z29: 4.8601813 | AA29: Johan Momsen | AB29: {=COUNT(_xlfn._xlws.FILTER($J$7:$J$10000,($L$7:$L$10000=AA29)*($M$7:$M$10000<>"NULL")*($J$7:$J$10000 >= ($G$1-5))))/5} -> 0.6
A30: =VLOOKUP($B30, PlayerIDs!$A$1:$B$516, 2, FALSE) -> 279 | B30: Malcolm May | C30: 5.7901379 | D30: =RANK($C30,$C$20:$C$106) -> 11 | E30: {=IFERROR(VLOOKUP($B30,_xlfn._xlws.FILTER($L$7:$P$10000,$J$7:$J$10000=G$1+1),5, FALSE), 0)} -> 5.2016794 | F30: =RANK(E30,$E$20:$E$100) -> 15 | G30: =SUMIF(V:Z,$B30,Z:Z) -> 16.142159 | H30: =RANK($G30,$G$20:$G$106) -> 30 | I30: {=COUNT(_xlfn._xlws.FILTER($J$7:$J$10000,($L$7:$L$10000=B30)*($M$7:$M$10000<>"NULL")*($J$7:$J$10000 >= ($G$1-4))))/5} -> 0 | J30: 2 | K30: UTAH | L30: Gavin Thornbury | M30: 5.8 | N30: Away | O30: CHI | P30: =VLOOKUP($N30,$F$3:$G$4,2,FALSE)+VLOOKUP($L30,$B$20:$C$150,2,FALSE)+VLOOKUP($O30,$A$6:$B$16,2,FALSE) -> 5.3958753 | Q30: =IFERROR(($M30-$P30)^2,"") -> 0.16331674 | R30: {=SUMPRODUCT((J30=$J$7:$J$1000)*(P30<$P$7:$P$1000))+1} -> 6 | T30: 13 | U30: NEFJ | V30: Conor Keys | W30: NULL | X30: Home | Y30: CHI | Z30: 2.5922593 | AA30: Jurie van Vuuren | AB30: {=COUNT(_xlfn._xlws.FILTER($J$7:$J$10000,($L$7:$L$10000=AA30)*($M$7:$M$10000<>"NULL")*($J$7:$J$10000 >= ($G$1-5))))/5} -> 1
A31: =VLOOKUP($B31, PlayerIDs!$A$1:$B$516, 2, FALSE) -> 827 | B31: Alejandro Martinez Tapia | C31: 5.7341983 | D31: =RANK($C31,$C$20:$C$106) -> 12 | E31: {=IFERROR(VLOOKUP($B31,_xlfn._xlws.FILTER($L$7:$P$10000,$J$7:$J$10000=G$1+1),5, FALSE), 0)} -> 5.7267055 | F31: =RANK(E31,$E$20:$E$100) -> 10 | G31: =SUMIF(V:Z,$B31,Z:Z) -> 22.905068 | H31: =RANK($G31,$G$20:$G$106) -> 7 | I31: {=COUNT(_xlfn._xlws.FILTER($J$7:$J$10000,($L$7:$L$10000=B31)*($M$7:$M$10000<>"NULL")*($J$7:$J$10000 >= ($G$1-4))))/5} -> 0.4 | J31: 2 | K31: HOU | L31: Nathan Den Hoedt | M31: 5.5 | N31: Away | O31: LA | P31: =VLOOKUP($N31,$F$3:$G$4,2,FALSE)+VLOOKUP($L31,$B$20:$C$150,2,FALSE)+VLOOKUP($O31,$A$6:$B$16,2,FALSE) -> 5.2667941 | Q31: =IFERROR(($M31-$P31)^2,"") -> 0.054385005 | R31: {=SUMPRODUCT((J31=$J$7:$J$1000)*(P31<$P$7:$P$1000))+1} -> 7 | T31: 13 | U31: NEFJ | V31: Jero Gomez Vara | W31: NULL | X31: Home | Y31: CHI | Z31: 4.3819071 | AA31: Justin Basson | AB31: {=COUNT(_xlfn._xlws.FILTER($J$7:$J$10000,($L$7:$L$10000=AA31)*($M$7:$M$10000<>"NULL")*($J$7:$J$10000 >= ($G$1-5))))/5} -> 0.8
... A60: =VLOOKUP($B60, PlayerIDs!$A$1:$B$516, 2, FALSE) -> 826 | B60: Shawn Clark | C60: 3.1390273 | D60: =RANK($C60,$C$20:$C$106) -> 41 | E60: {=IFERROR(VLOOKUP($B60,_xlfn._xlws.FILTER($L$7:$P$10000,$J$7:$J$10000=G$1+1),5, FALSE), 0)} -> 3.1315344 | F60: =RANK(E60,$E$20:$E$100) -> 36 | G60: =SUMIF(V:Z,$B60,Z:Z) -> 12.524384 | H60: =RANK($G60,$G$20:$G$106) -> 34 | I60: {=COUNT(_xlfn._xlws.FILTER($J$7:$J$10000,($L$7:$L$10000=B60)*($M$7:$M$10000<>"NULL")*($J$7:$J$10000 >= ($G$1-4))))/5} -> 0.2 | J60: 3 | K60: UTAH | L60: Matt Jenson | M60: 2.4 | N60: Home | O60: NOLA | P60: =VLOOKUP($N60,$F$3:$G$4,2,FALSE)+VLOOKUP($L60,$B$20:$C$150,2,FALSE)+VLOOKUP($O60,$A$6:$B$16,2,FALSE) -> 4.1228543 | Q60: =IFERROR(($M60-$P60)^2,"") -> 2.9682271 | R60: {=SUMPRODUCT((J60=$J$7:$J$1000)*(P60<$P$7:$P$1000))+1} -> 16 | T60: 14 | U60: ARC | V60: Javon Camp Villalovos | W60: NULL | X60: Home | Y60: UTAH | Z60: 1.8319744 | AA60: Zak Farrance | AB60: {=COUNT(_xlfn._xlws.FILTER($J$7:$J$10000,($L$7:$L$10000=AA60)*($M$7:$M$10000<>"NULL")*($J$7:$J$10000 >= ($G$1-5))))/5} -> 0.2
A61: =VLOOKUP($B61, PlayerIDs!$A$1:$B$516, 2, FALSE) -> 760 | B61: Malembe Mpofu | C61: 3.0204091 | D61: =RANK($C61,$C$20:$C$106) -> 42 | E61: {=IFERROR(VLOOKUP($B61,_xlfn._xlws.FILTER($L$7:$P$10000,$J$7:$J$10000=G$1+1),5, FALSE), 0)} -> 2.2468751 | F61: =RANK(E61,$E$20:$E$100) -> 42 | G61: =SUMIF(V:Z,$B61,Z:Z) -> 11.761331 | H61: =RANK($G61,$G$20:$G$106) -> 37 | I61: {=COUNT(_xlfn._xlws.FILTER($J$7:$J$10000,($L$7:$L$10000=B61)*($M$7:$M$10000<>"NULL")*($J$7:$J$10000 >= ($G$1-4))))/5} -> 0.2 | J61: 3 | K61: HOU | L61: Nathan Den Hoedt | M61: 1.8 | N61: Home | O61: SEA | P61: =VLOOKUP($N61,$F$3:$G$4,2,FALSE)+VLOOKUP($L61,$B$20:$C$150,2,FALSE)+VLOOKUP($O61,$A$6:$B$16,2,FALSE) -> 5.4663043 | Q61: =IFERROR(($M61-$P61)^2,"") -> 13.441787 | R61: {=SUMPRODUCT((J61=$J$7:$J$1000)*(P61<$P$7:$P$1000))+1} -> 5 | T61: 14 | U61: ARC | V61: Mikey Grandy | W61: NULL | X61: Home | Y61: OGDC | Z61: 5.1805475 | AA61: 0 | AB61: {=COUNT(_xlfn._xlws.FILTER($J$7:$J$10000,($L$7:$L$10000=AA61)*($M$7:$M$10000<>"NULL")*($J$7:$J$10000 >= ($G$1-5))))/5} -> 0
A62: =VLOOKUP($B62, PlayerIDs!$A$1:$B$516, 2, FALSE) -> 747 | B62: Javon Camp Villalovos | C62: 2.5910673 | D62: =RANK($C62,$C$20:$C$106) -> 43 | E62: {=IFERROR(VLOOKUP($B62,_xlfn._xlws.FILTER($L$7:$P$10000,$J$7:$J$10000=G$1+1),5, FALSE), 0)} -> 2.5835745 | F62: =RANK(E62,$E$20:$E$100) -> 39 | G62: =SUMIF(V:Z,$B62,Z:Z) -> 18.100987 | H62: =RANK($G62,$G$20:$G$106) -> 20 | I62: {=COUNT(_xlfn._xlws.FILTER($J$7:$J$10000,($L$7:$L$10000=B62)*($M$7:$M$10000<>"NULL")*($J$7:$J$10000 >= ($G$1-4))))/5} -> 0.2 | J62: 3 | K62: SDL | L62: Brandon Harvey | M62: 0.9 | N62: Away | O62: OGDC | P62: =VLOOKUP($N62,$F$3:$G$4,2,FALSE)+VLOOKUP($L62,$B$20:$C$150,2,FALSE)+VLOOKUP($O62,$A$6:$B$16,2,FALSE) -> 2.6011512 | Q62: =IFERROR(($M62-$P62)^2,"") -> 2.8939155 | R62: {=SUMPRODUCT((J62=$J$7:$J$1000)*(P62<$P$7:$P$1000))+1} -> 20 | T62: 14 | U62: ARC | V62: Sam Golla | W62: NULL | X62: Home | Y62: OGDC | Z62: 6.9644839 | AB62: {=COUNT(_xlfn._xlws.FILTER($J$7:$J$10000,($L$7:$L$10000=AA62)*($M$7:$M$10000<>"NULL")*($J$7:$J$10000 >= ($G$1-5))))/5} -> 0
A63: =VLOOKUP($B63, PlayerIDs!$A$1:$B$516, 2, FALSE) -> 85 | B63: Conor Keys | C63: 2.4585211 | D63: =RANK($C63,$C$20:$C$106) -> 44 | E63: {=IFERROR(VLOOKUP($B63,_xlfn._xlws.FILTER($L$7:$P$10000,$J$7:$J$10000=G$1+1),5, FALSE), 0)} -> 2.5922593 | F63: =RANK(E63,$E$20:$E$100) -> 38 | G63: =SUMIF(V:Z,$B63,Z:Z) -> 10.172504 | H63: =RANK($G63,$G$20:$G$106) -> 42 | I63: {=COUNT(_xlfn._xlws.FILTER($J$7:$J$10000,($L$7:$L$10000=B63)*($M$7:$M$10000<>"NULL")*($J$7:$J$10000 >= ($G$1-4))))/5} -> 0 | J63: 4 | K63: HOU | L63: Nathan Den Hoedt | M63: 9.6 | N63: Away | O63: UTAH | P63: =VLOOKUP($N63,$F$3:$G$4,2,FALSE)+VLOOKUP($L63,$B$20:$C$150,2,FALSE)+VLOOKUP($O63,$A$6:$B$16,2,FALSE) -> 4.5007529 | Q63: =IFERROR(($M63-$P63)^2,"") -> 26.002321 | R63: {=SUMPRODUCT((J63=$J$7:$J$1000)*(P63<$P$7:$P$1000))+1} -> 12 | T63: 14 | U63: ARC | V63: Shawn Clark | W63: NULL | X63: Home | Y63: OGDC | Z63: 3.7545907 | AB63: {=COUNT(_xlfn._xlws.FILTER($J$7:$J$10000,($L$7:$L$10000=AA63)*($M$7:$M$10000<>"NULL")*($J$7:$J$10000 >= ($G$1-5))))/5} -> 0
A64: =VLOOKUP($B64, PlayerIDs!$A$1:$B$516, 2, FALSE) -> 236 | B64: Justin Basson | C64: 2.4298557 | D64: =RANK($C64,$C$20:$C$106) -> 45 | E64: {=IFERROR(VLOOKUP($B64,_xlfn._xlws.FILTER($L$7:$P$10000,$J$7:$J$10000=G$1+1),5, FALSE), 0)} -> 3.0066136 | F64: =RANK(E64,$E$20:$E$100) -> 37 | G64: =SUMIF(V:Z,$B64,Z:Z) -> 7.2848082 | H64: =RANK($G64,$G$20:$G$106) -> 48 | I64: {=COUNT(_xlfn._xlws.FILTER($J$7:$J$10000,($L$7:$L$10000=B64)*($M$7:$M$10000<>"NULL")*($J$7:$J$10000 >= ($G$1-4))))/5} -> 0.8 | J64: 4 | K64: UTAH | L64: Gavin Thornbury | M64: 8 | N64: Home | O64: HOU | P64: =VLOOKUP($N64,$F$3:$G$4,2,FALSE)+VLOOKUP($L64,$B$20:$C$150,2,FALSE)+VLOOKUP($O64,$A$6:$B$16,2,FALSE) -> 5.2663732 | Q64: =IFERROR(($M64-$P64)^2,"") -> 7.4727153 | R64: {=SUMPRODUCT((J64=$J$7:$J$1000)*(P64<$P$7:$P$1000))+1} -> 7 | T64: 14 | U64: ARC | V64: Viliami Vuli | W64: NULL | X64: Home | Y64: OGDC | Z64: 5.5692583 | AB64: {=COUNT(_xlfn._xlws.FILTER($J$7:$J$10000,($L$7:$L$10000=AA64)*($M$7:$M$10000<>"NULL")*($J$7:$J$10000 >= ($G$1-5))))/5} -> 0
A65: =VLOOKUP($B65, PlayerIDs!$A$1:$B$516, 2, FALSE) -> 644 | B65: Ignacio Dotti | C65: 2.3871161 | D65: =RANK($C65,$C$20:$C$106) -> 46 | E65: {=IFERROR(VLOOKUP($B65,_xlfn._xlws.FILTER($L$7:$P$10000,$J$7:$J$10000=G$1+1),5, FALSE), 0)} -> 0 | F65: =RANK(E65,$E$20:$E$100) -> 51 | G65: =SUMIF(V:Z,$B65,Z:Z) -> 7.8363327 | H65: =RANK($G65,$G$20:$G$106) -> 46 | I65: {=COUNT(_xlfn._xlws.FILTER($J$7:$J$10000,($L$7:$L$10000=B65)*($M$7:$M$10000<>"NULL")*($J$7:$J$10000 >= ($G$1-4))))/5} -> 0 | J65: 4 | K65: LA | L65: Jason Damm | M65: 7.8 | N65: Away | O65: SDL | P65: =VLOOKUP($N65,$F$3:$G$4,2,FALSE)+VLOOKUP($L65,$B$20:$C$150,2,FALSE)+VLOOKUP($O65,$A$6:$B$16,2,FALSE) -> 8.1859035 | Q65: =IFERROR(($M65-$P65)^2,"") -> 0.14892152 | R65: {=SUMPRODUCT((J65=$J$7:$J$1000)*(P65<$P$7:$P$1000))+1} -> 1 | T65: 14 | U65: CHI | V65: Hamish Bain | W65: NULL | X65: Home | Y65: LA | Z65: 4.2779514 | AB65: {=COUNT(_xlfn._xlws.FILTER($J$7:$J$10000,($L$7:$L$10000=AA65)*($M$7:$M$10000<>"NULL")*($J$7:$J$10000 >= ($G$1-5))))/5} -> 0
A66: =VLOOKUP($B66, PlayerIDs!$A$1:$B$516, 2, FALSE) -> 859 | B66: Kyle Baillie | C66: 2.0570073 | D66: =RANK($C66,$C$20:$C$106) -> 47 | E66: {=IFERROR(VLOOKUP($B66,_xlfn._xlws.FILTER($L$7:$P$10000,$J$7:$J$10000=G$1+1),5, FALSE), 0)} -> 2.1907455 | F66: =RANK(E66,$E$20:$E$100) -> 43 | G66: =SUMIF(V:Z,$B66,Z:Z) -> 8.5664486 | H66: =RANK($G66,$G$20:$G$106) -> 45 | I66: {=COUNT(_xlfn._xlws.FILTER($J$7:$J$10000,($L$7:$L$10000=B66)*($M$7:$M$10000<>"NULL")*($J$7:$J$10000 >= ($G$1-4))))/5} -> 0 | J66: 4 | K66: HOU | L66: Johan Momsen | M66: 7.1 | N66: Away | O66: UTAH | P66: =VLOOKUP($N66,$F$3:$G$4,2,FALSE)+VLOOKUP($L66,$B$20:$C$150,2,FALSE)+VLOOKUP($O66,$A$6:$B$16,2,FALSE) -> 4.8255852 | Q66: =IFERROR(($M66-$P66)^2,"") -> 5.1729627 | R66: {=SUMPRODUCT((J66=$J$7:$J$1000)*(P66<$P$7:$P$1000))+1} -> 10 | T66: 14 | U66: CHI | V66: James Scott | W66: NULL | X66: Home | Y66: LA | Z66: 5.1691244 | AB66: {=COUNT(_xlfn._xlws.FILTER($J$7:$J$10000,($L$7:$L$10000=AA66)*($M$7:$M$10000<>"NULL")*($J$7:$J$10000 >= ($G$1-5))))/5} -> 0
A67: =VLOOKUP($B67, PlayerIDs!$A$1:$B$516, 2, FALSE) -> 657 | B67: Brandon Harvey | C67: 2.0000289 | D67: =RANK($C67,$C$20:$C$106) -> 48 | E67: {=IFERROR(VLOOKUP($B67,_xlfn._xlws.FILTER($L$7:$P$10000,$J$7:$J$10000=G$1+1),5, FALSE), 0)} -> 1.9898239 | F67: =RANK(E67,$E$20:$E$100) -> 45 | G67: =SUMIF(V:Z,$B67,Z:Z) -> 5.5645583 | H67: =RANK($G67,$G$20:$G$106) -> 49 | I67: {=COUNT(_xlfn._xlws.FILTER($J$7:$J$10000,($L$7:$L$10000=B67)*($M$7:$M$10000<>"NULL")*($J$7:$J$10000 >= ($G$1-4))))/5} -> 0.2 | J67: 4 | K67: MIA | L67: Tomás Casares | M67: 7 | N67: Home | O67: CHI | P67: =VLOOKUP($N67,$F$3:$G$4,2,FALSE)+VLOOKUP($L67,$B$20:$C$150,2,FALSE)+VLOOKUP($O67,$A$6:$B$16,2,FALSE) -> 5.8075622 | Q67: =IFERROR(($M67-$P67)^2,"") -> 1.4219078 | R67: {=SUMPRODUCT((J67=$J$7:$J$1000)*(P67<$P$7:$P$1000))+1} -> 4 | T67: 14 | U67: CHI | V67: Mason Flesch | W67: NULL | X67: Home | Y67: LA | Z67: 5.3359637 | AB67: {=COUNT(_xlfn._xlws.FILTER($J$7:$J$10000,($L$7:$L$10000=AA67)*($M$7:$M$10000<>"NULL")*($J$7:$J$10000 >= ($G$1-5))))/5} -> 0
A68: =VLOOKUP($B68, PlayerIDs!$A$1:$B$516, 2, FALSE) -> 378 | B68: Saia 'Uhila | C68: 1.9068034 | D68: =RANK($C68,$C$20:$C$106) -> 49 | E68: {=IFERROR(VLOOKUP($B68,_xlfn._xlws.FILTER($L$7:$P$10000,$J$7:$J$10000=G$1+1),5, FALSE), 0)} -> 2.0988207 | F68: =RANK(E68,$E$20:$E$100) -> 44 | G68: =SUMIF(V:Z,$B68,Z:Z) -> 7.7911845 | H68: =RANK($G68,$G$20:$G$106) -> 47 | I68: {=COUNT(_xlfn._xlws.FILTER($J$7:$J$10000,($L$7:$L$10000=B68)*($M$7:$M$10000<>"NULL")*($J$7:$J$10000 >= ($G$1-4))))/5} -> 0.2 | J68: 4 | K68: SEA | L68: Malembe Mpofu | M68: 6.7 | N68: Home | O68: NEFJ | P68: =VLOOKUP($N68,$F$3:$G$4,2,FALSE)+VLOOKUP($L68,$B$20:$C$150,2,FALSE)+VLOOKUP($O68,$A$6:$B$16,2,FALSE) -> 2.9070849 | Q68: =IFERROR(($M68-$P68)^2,"") -> 14.386205 | R68: {=SUMPRODUCT((J68=$J$7:$J$1000)*(P68<$P$7:$P$1000))+1} -> 18 | T68: 14 | U68: HOU | V68: Johan Momsen | W68: NULL | X68: Home | Y68: UTAH | Z68: 4.8400263 | AB68: {=COUNT(_xlfn._xlws.FILTER($J$7:$J$10000,($L$7:$L$10000=AA68)*($M$7:$M$10000<>"NULL")*($J$7:$J$10000 >= ($G$1-5))))/5} -> 0
A69: =VLOOKUP($B69, PlayerIDs!$A$1:$B$516, 2, FALSE) -> 410 | B69: Taylor Krumrei | C69: 1.4436634 | D69: =RANK($C69,$C$20:$C$106) -> 50 | E69: {=IFERROR(VLOOKUP($B69,_xlfn._xlws.FILTER($L$7:$P$10000,$J$7:$J$10000=G$1+1),5, FALSE), 0)} -> 0.67012938 | F69: =RANK(E69,$E$20:$E$100) -> 47 | G69: =SUMIF(V:Z,$B69,Z:Z) -> 5.4543482 | H69: =RANK($G69,$G$20:$G$106) -> 51 | I69: {=COUNT(_xlfn._xlws.FILTER($J$7:$J$10000,($L$7:$L$10000=B69)*($M$7:$M$10000<>"NULL")*($J$7:$J$10000 >= ($G$1-4))))/5} -> 0.2 | J69: 4 | K69: MIA | L69: Mauro Rebussone | M69: 6.5 | N69: Home | O69: CHI | P69: =VLOOKUP($N69,$F$3:$G$4,2,FALSE)+VLOOKUP($L69,$B$20:$C$150,2,FALSE)+VLOOKUP($O69,$A$6:$B$16,2,FALSE) -> 5.3058291 | Q69: =IFERROR(($M69-$P69)^2,"") -> 1.4260441 | R69: {=SUMPRODUCT((J69=$J$7:$J$1000)*(P69<$P$7:$P$1000))+1} -> 6 | T69: 14 | U69: HOU | V69: Justin Basson | W69: NULL | X69: Home | Y69: UTAH | Z69: 1.6707628 | AB69: {=COUNT(_xlfn._xlws.FILTER($J$7:$J$10000,($L$7:$L$10000=AA69)*($M$7:$M$10000<>"NULL")*($J$7:$J$10000 >= ($G$1-5))))/5} -> 0
A70: =VLOOKUP($B70, PlayerIDs!$A$1:$B$516, 2, FALSE) -> 178 | B70: Isaia Lotawa | C70: 1.2808304 | D70: =RANK($C70,$C$20:$C$106) -> 51 | E70: {=IFERROR(VLOOKUP($B70,_xlfn._xlws.FILTER($L$7:$P$10000,$J$7:$J$10000=G$1+1),5, FALSE), 0)} -> 0.50729636 | F70: =RANK(E70,$E$20:$E$100) -> 48 | G70: =SUMIF(V:Z,$B70,Z:Z) -> 4.8030162 | H70: =RANK($G70,$G$20:$G$106) -> 52 | I70: {=COUNT(_xlfn._xlws.FILTER($J$7:$J$10000,($L$7:$L$10000=B70)*($M$7:$M$10000<>"NULL")*($J$7:$J$10000 >= ($G$1-4))))/5} -> 0 | J70: 4 | K70: OGDC | L70: Bill Whiteside | M70: 6.3 | N70: Home | O70: ARC | P70: =VLOOKUP($N70,$F$3:$G$4,2,FALSE)+VLOOKUP($L70,$B$20:$C$150,2,FALSE)+VLOOKUP($O70,$A$6:$B$16,2,FALSE) -> 4.4473109 | Q70: =IFERROR(($M70-$P70)^2,"") -> 3.4324567 | R70: {=SUMPRODUCT((J70=$J$7:$J$1000)*(P70<$P$7:$P$1000))+1} -> 13 | T70: 14 | U70: HOU | V70: Nathan Den Hoedt | W70: NULL | X70: Home | Y70: UTAH | Z70: 4.515194 | AB70: {=COUNT(_xlfn._xlws.FILTER($J$7:$J$10000,($L$7:$L$10000=AA70)*($M$7:$M$10000<>"NULL")*($J$7:$J$10000 >= ($G$1-5))))/5} -> 0
A71: =VLOOKUP($B71, PlayerIDs!$A$1:$B$516, 2, FALSE) -> 360 | B71: Reegan O'Gorman | C71: 1.1518037 | D71: =RANK($C71,$C$20:$C$106) -> 52 | E71: {=IFERROR(VLOOKUP($B71,_xlfn._xlws.FILTER($L$7:$P$10000,$J$7:$J$10000=G$1+1),5, FALSE), 0)} -> 1.9620463 | F71: =RANK(E71,$E$20:$E$100) -> 46 | G71: =SUMIF(V:Z,$B71,Z:Z) -> 5.5494183 | H71: =RANK($G71,$G$20:$G$106) -> 50 | I71: {=COUNT(_xlfn._xlws.FILTER($J$7:$J$10000,($L$7:$L$10000=B71)*($M$7:$M$10000<>"NULL")*($J$7:$J$10000 >= ($G$1-4))))/5} -> 0 | J71: 4 | K71: ARC | L71: Mikey Grandy | M71: 5.8 | N71: Away | O71: OGDC | P71: =VLOOKUP($N71,$F$3:$G$4,2,FALSE)+VLOOKUP($L71,$B$20:$C$150,2,FALSE)+VLOOKUP($O71,$A$6:$B$16,2,FALSE) -> 5.1661063 | Q71: =IFERROR(($M71-$P71)^2,"") -> 0.4018212 | R71: {=SUMPRODUCT((J71=$J$7:$J$1000)*(P71<$P$7:$P$1000))+1} -> 8 | T71: 14 | U71: LA | V71: Jason Damm | W71: NULL | X71: Away | Y71: CHI | Z71: 7.7284426 | AB71: {=COUNT(_xlfn._xlws.FILTER($J$7:$J$10000,($L$7:$L$10000=AA71)*($M$7:$M$10000<>"NULL")*($J$7:$J$10000 >= ($G$1-5))))/5} -> 0
A72: =VLOOKUP($B72, PlayerIDs!$A$1:$B$516, 2, FALSE) -> 769 | B72: Kaden Duguid | C72: 0.90902881 | D72: =RANK($C72,$C$20:$C$106) -> 53 | E72: {=IFERROR(VLOOKUP($B72,_xlfn._xlws.FILTER($L$7:$P$10000,$J$7:$J$10000=G$1+1),5, FALSE), 0)} -> 0.32057028 | F72: =RANK(E72,$E$20:$E$100) -> 49 | G72: =SUMIF(V:Z,$B72,Z:Z) -> 1.498832 | H72: =RANK($G72,$G$20:$G$106) -> 53 | I72: {=COUNT(_xlfn._xlws.FILTER($J$7:$J$10000,($L$7:$L$10000=B72)*($M$7:$M$10000<>"NULL")*($J$7:$J$10000 >= ($G$1-4))))/5} -> 0 | J72: 4 | K72: SDL | L72: Jed Holloway | M72: 5.7 | N72: Home | O72: LA | P72: =VLOOKUP($N72,$F$3:$G$4,2,FALSE)+VLOOKUP($L72,$B$20:$C$150,2,FALSE)+VLOOKUP($O72,$A$6:$B$16,2,FALSE) -> 7.9684898 | Q72: =IFERROR(($M72-$P72)^2,"") -> 5.146046 | R72: {=SUMPRODUCT((J72=$J$7:$J$1000)*(P72<$P$7:$P$1000))+1} -> 2 | T72: 14 | U72: LA | V72: Jurie van Vuuren | W72: NULL | X72: Away | Y72: CHI | Z72: 4.2366028 | AB72: {=COUNT(_xlfn._xlws.FILTER($J$7:$J$10000,($L$7:$L$10000=AA72)*($M$7:$M$10000<>"NULL")*($J$7:$J$10000 >= ($G$1-5))))/5} -> 0
A73: =VLOOKUP($B73, PlayerIDs!$A$1:$B$516, 2, FALSE) -> 866 | B73: Zak Farrance | C73: 0.11668032 | D73: =RANK($C73,$C$20:$C$106) -> 54 | E73: {=IFERROR(VLOOKUP($B73,_xlfn._xlws.FILTER($L$7:$P$10000,$J$7:$J$10000=G$1+1),5, FALSE), 0)} -> 0.10647525 | F73: =RANK(E73,$E$20:$E$100) -> 50 | G73: =SUMIF(V:Z,$B73,Z:Z) -> -0.085487555 | H73: =RANK($G73,$G$20:$G$106) -> 54 | I73: {=COUNT(_xlfn._xlws.FILTER($J$7:$J$10000,($L$7:$L$10000=B73)*($M$7:$M$10000<>"NULL")*($J$7:$J$10000 >= ($G$1-4))))/5} -> 0.2 | J73: 4 | K73: ARC | L73: Viliami Vuli | M73: 5.6 | N73: Away | O73: OGDC | P73: =VLOOKUP($N73,$F$3:$G$4,2,FALSE)+VLOOKUP($L73,$B$20:$C$150,2,FALSE)+VLOOKUP($O73,$A$6:$B$16,2,FALSE) -> 5.5548171 | Q73: =IFERROR(($M73-$P73)^2,"") -> 0.0020414915 | R73: {=SUMPRODUCT((J73=$J$7:$J$1000)*(P73<$P$7:$P$1000))+1} -> 5 | T73: 14 | U73: LA | V73: Lucas Bur | W73: NULL | X73: Away | Y73: CHI | Z73: 4.5313598 | AB73: {=COUNT(_xlfn._xlws.FILTER($J$7:$J$10000,($L$7:$L$10000=AA73)*($M$7:$M$10000<>"NULL")*($J$7:$J$10000 >= ($G$1-5))))/5} -> 0
J74: 4 | K74: SEA | L74: Rhyno Herbst | M74: 4.7 | N74: Home | O74: NEFJ | P74: =VLOOKUP($N74,$F$3:$G$4,2,FALSE)+VLOOKUP($L74,$B$20:$C$150,2,FALSE)+VLOOKUP($O74,$A$6:$B$16,2,FALSE) -> 4.2960513 | Q74: =IFERROR(($M74-$P74)^2,"") -> 0.16317458 | R74: {=SUMPRODUCT((J74=$J$7:$J$1000)*(P74<$P$7:$P$1000))+1} -> 14 | T74: 14 | U74: LA | V74: Reegan O'Gorman | W74: NULL | X74: Away | Y74: CHI | Z74: 1.2711007 | AB74: {=COUNT(_xlfn._xlws.FILTER($J$7:$J$10000,($L$7:$L$10000=AA74)*($M$7:$M$10000<>"NULL")*($J$7:$J$10000 >= ($G$1-5))))/5} -> 0
J75: 4 | K75: NEFJ | L75: Conor Keys | M75: 4.2 | N75: Away | O75: SEA | P75: =VLOOKUP($N75,$F$3:$G$4,2,FALSE)+VLOOKUP($L75,$B$20:$C$150,2,FALSE)+VLOOKUP($O75,$A$6:$B$16,2,FALSE) -> 2.6360973 | Q75: =IFERROR(($M75-$P75)^2,"") -> 2.4457916 | R75: {=SUMPRODUCT((J75=$J$7:$J$1000)*(P75<$P$7:$P$1000))+1} -> 19 | T75: 14 | U75: LA | V75: Tim Anstee | W75: NULL | X75: Away | Y75: CHI | Z75: 14.528075 | AB75: {=COUNT(_xlfn._xlws.FILTER($J$7:$J$10000,($L$7:$L$10000=AA75)*($M$7:$M$10000<>"NULL")*($J$7:$J$10000 >= ($G$1-5))))/5} -> 0
J76: 4 | K76: CHI | L76: James Scott | M76: 3.6 | N76: Away | O76: MIA | P76: =VLOOKUP($N76,$F$3:$G$4,2,FALSE)+VLOOKUP($L76,$B$20:$C$150,2,FALSE)+VLOOKUP($O76,$A$6:$B$16,2,FALSE) -> 4.5592764 | Q76: =IFERROR(($M76-$P76)^2,"") -> 0.92021122 | R76: {=SUMPRODUCT((J76=$J$7:$J$1000)*(P76<$P$7:$P$1000))+1} -> 11 | T76: 14 | U76: MIA | V76: Braemar Murray | W76: NULL | X76: Home | Y76: NEFJ | Z76: 3.0314301 | AB76: {=COUNT(_xlfn._xlws.FILTER($J$7:$J$10000,($L$7:$L$10000=AA76)*($M$7:$M$10000<>"NULL")*($J$7:$J$10000 >= ($G$1-5))))/5} -> 0
J77: 4 | K77: UTAH | L77: Matt Jenson | M77: 2.8 | N77: Home | O77: HOU | P77: =VLOOKUP($N77,$F$3:$G$4,2,FALSE)+VLOOKUP($L77,$B$20:$C$150,2,FALSE)+VLOOKUP($O77,$A$6:$B$16,2,FALSE) -> 4.9118509 | Q77: =IFERROR(($M77-$P77)^2,"") -> 4.4599142 | R77: {=SUMPRODUCT((J77=$J$7:$J$1000)*(P77<$P$7:$P$1000))+1} -> 9 | T77: 14 | U77: MIA | V77: Federico Gutíerrez | W77: NULL | X77: Home | Y77: NEFJ | Z77: 3.0293358 | AB77: {=COUNT(_xlfn._xlws.FILTER($J$7:$J$10000,($L$7:$L$10000=AA77)*($M$7:$M$10000<>"NULL")*($J$7:$J$10000 >= ($G$1-5))))/5} -> 0
J78: 4 | K78: NEFJ | L78: Piers von Dadelszen | M78: 2.7 | N78: Away | O78: SEA | P78: =VLOOKUP($N78,$F$3:$G$4,2,FALSE)+VLOOKUP($L78,$B$20:$C$150,2,FALSE)+VLOOKUP($O78,$A$6:$B$16,2,FALSE) -> 4.1145321 | Q78: =IFERROR(($M78-$P78)^2,"") -> 2.0009011 | R78: {=SUMPRODUCT((J78=$J$7:$J$1000)*(P78<$P$7:$P$1000))+1} -> 15 | T78: 14 | U78: MIA | V78: Mauro Rebussone | W78: NULL | X78: Home | Y78: NEFJ | Z78: 5.0587667 | AB78: {=COUNT(_xlfn._xlws.FILTER($J$7:$J$10000,($L$7:$L$10000=AA78)*($M$7:$M$10000<>"NULL")*($J$7:$J$10000 >= ($G$1-5))))/5} -> 0
J79: 4 | K79: SDL | L79: Vili Helu | M79: 2.4 | N79: Home | O79: LA | P79: =VLOOKUP($N79,$F$3:$G$4,2,FALSE)+VLOOKUP($L79,$B$20:$C$150,2,FALSE)+VLOOKUP($O79,$A$6:$B$16,2,FALSE) -> 5.9653849 | Q79: =IFERROR(($M79-$P79)^2,"") -> 12.711969 | R79: {=SUMPRODUCT((J79=$J$7:$J$1000)*(P79<$P$7:$P$1000))+1} -> 3 | T79: 14 | U79: MIA | V79: Rick Rose | W79: NULL | X79: Home | Y79: NEFJ | Z79: 4.884347 | AB79: {=COUNT(_xlfn._xlws.FILTER($J$7:$J$10000,($L$7:$L$10000=AA79)*($M$7:$M$10000<>"NULL")*($J$7:$J$10000 >= ($G$1-5))))/5} -> 0
J80: 4 | K80: OGDC | L80: Ignacio Dotti | M80: 2.2 | N80: Home | O80: ARC | P80: =VLOOKUP($N80,$F$3:$G$4,2,FALSE)+VLOOKUP($L80,$B$20:$C$150,2,FALSE)+VLOOKUP($O80,$A$6:$B$16,2,FALSE) -> 3.1973587 | Q80: =IFERROR(($M80-$P80)^2,"") -> 0.99472445 | R80: {=SUMPRODUCT((J80=$J$7:$J$1000)*(P80<$P$7:$P$1000))+1} -> 17 | T80: 14 | U80: MIA | V80: Tomás Casares | W80: NULL | X80: Home | Y80: NEFJ | Z80: 5.5604998 | AB80: {=COUNT(_xlfn._xlws.FILTER($J$7:$J$10000,($L$7:$L$10000=AA80)*($M$7:$M$10000<>"NULL")*($J$7:$J$10000 >= ($G$1-5))))/5} -> 0
J81: 4 | K81: CHI | L81: Hamish Bain | M81: 1.5 | N81: Away | O81: MIA | P81: =VLOOKUP($N81,$F$3:$G$4,2,FALSE)+VLOOKUP($L81,$B$20:$C$150,2,FALSE)+VLOOKUP($O81,$A$6:$B$16,2,FALSE) -> 3.6681034 | Q81: =IFERROR(($M81-$P81)^2,"") -> 4.7006725 | R81: {=SUMPRODUCT((J81=$J$7:$J$1000)*(P81<$P$7:$P$1000))+1} -> 16 | T81: 14 | U81: NEFJ | V81: Conor Keys | W81: NULL | X81: Away | Y81: MIA | Z81: 1.8556214 | AB81: {=COUNT(_xlfn._xlws.FILTER($J$7:$J$10000,($L$7:$L$10000=AA81)*($M$7:$M$10000<>"NULL")*($J$7:$J$10000 >= ($G$1-5))))/5} -> 0
J82: 4 | K82: LA | L82: Reegan O'Gorman | M82: 1.2 | N82: Away | O82: SDL | P82: =VLOOKUP($N82,$F$3:$G$4,2,FALSE)+VLOOKUP($L82,$B$20:$C$150,2,FALSE)+VLOOKUP($O82,$A$6:$B$16,2,FALSE) -> 1.7285616 | Q82: =IFERROR(($M82-$P82)^2,"") -> 0.2793774 | R82: {=SUMPRODUCT((J82=$J$7:$J$1000)*(P82<$P$7:$P$1000))+1} -> 20 | T82: 14 | U82: NEFJ | V82: Jero Gomez Vara | W82: NULL | X82: Away | Y82: MIA | Z82: 3.6452693 | AB82: {=COUNT(_xlfn._xlws.FILTER($J$7:$J$10000,($L$7:$L$10000=AA82)*($M$7:$M$10000<>"NULL")*($J$7:$J$10000 >= ($G$1-5))))/5} -> 0
J83: 5 | K83: LA | L83: Jason Damm | M83: 12.4 | N83: Home | O83: SEA | P83: =VLOOKUP($N83,$F$3:$G$4,2,FALSE)+VLOOKUP($L83,$B$20:$C$150,2,FALSE)+VLOOKUP($O83,$A$6:$B$16,2,FALSE) -> 7.8011629 | Q83: =IFERROR(($M83-$P83)^2,"") -> 21.149302 | R83: {=SUMPRODUCT((J83=$J$7:$J$1000)*(P83<$P$7:$P$1000))+1} -> 1 | T83: 14 | U83: NEFJ | V83: Kyle Baillie | W83: NULL | X83: Away | Y83: MIA | Z83: 1.4541077 | AB83: {=COUNT(_xlfn._xlws.FILTER($J$7:$J$10000,($L$7:$L$10000=AA83)*($M$7:$M$10000<>"NULL")*($J$7:$J$10000 >= ($G$1-5))))/5} -> 0
J84: 5 | K84: NOLA | L84: Chase Jones | M84: 7.9 | N84: Away | O84: NEFJ | P84: =VLOOKUP($N84,$F$3:$G$4,2,FALSE)+VLOOKUP($L84,$B$20:$C$150,2,FALSE)+VLOOKUP($O84,$A$6:$B$16,2,FALSE) -> 5.9890575 | Q84: =IFERROR(($M84-$P84)^2,"") -> 3.6517012 | R84: {=SUMPRODUCT((J84=$J$7:$J$1000)*(P84<$P$7:$P$1000))+1} -> 3 | T84: 14 | U84: NEFJ | V84: Piers von Dadelszen | W84: NULL | X84: Away | Y84: MIA | Z84: 3.3340562 | AB84: {=COUNT(_xlfn._xlws.FILTER($J$7:$J$10000,($L$7:$L$10000=AA84)*($M$7:$M$10000<>"NULL")*($J$7:$J$10000 >= ($G$1-5))))/5} -> 0
J85: 5 | K85: OGDC | L85: Rob Harley | M85: 7.1 | N85: Away | O85: CHI | P85: =VLOOKUP($N85,$F$3:$G$4,2,FALSE)+VLOOKUP($L85,$B$20:$C$150,2,FALSE)+VLOOKUP($O85,$A$6:$B$16,2,FALSE) -> 4.3969984 | Q85: =IFERROR(($M85-$P85)^2,"") -> 7.3062177 | R85: {=SUMPRODUCT((J85=$J$7:$J$1000)*(P85<$P$7:$P$1000))+1} -> 11 | T85: 14 | U85: NEFJ | V85: Sam Caird | W85: NULL | X85: Away | Y85: MIA | Z85: 4.4127509 | AB85: {=COUNT(_xlfn._xlws.FILTER($J$7:$J$10000,($L$7:$L$10000=AA85)*($M$7:$M$10000<>"NULL")*($J$7:$J$10000 >= ($G$1-5))))/5} -> 0
... J91: 5 | K91: SEA | L91: Malembe Mpofu | M91: 4.6 | N91: Away | O91: LA | P91: =VLOOKUP($N91,$F$3:$G$4,2,FALSE)+VLOOKUP($L91,$B$20:$C$150,2,FALSE)+VLOOKUP($O91,$A$6:$B$16,2,FALSE) -> 3.0129163 | Q91: =IFERROR(($M91-$P91)^2,"") -> 2.5188347 | R91: {=SUMPRODUCT((J91=$J$7:$J$1000)*(P91<$P$7:$P$1000))+1} -> 15 | T91: 14 | U91: SDL | V91: Charlie Hewitt | W91: NULL | X91: Away | Y91: SEA | Z91: 3.9623036 | AB91: {=COUNT(_xlfn._xlws.FILTER($J$7:$J$10000,($L$7:$L$10000=AA91)*($M$7:$M$10000<>"NULL")*($J$7:$J$10000 >= ($G$1-5))))/5} -> 0
J92: 5 | K92: OGDC | L92: Tevita Naqali | M92: 4.1 | N92: Away | O92: CHI | P92: =VLOOKUP($N92,$F$3:$G$4,2,FALSE)+VLOOKUP($L92,$B$20:$C$150,2,FALSE)+VLOOKUP($O92,$A$6:$B$16,2,FALSE) -> 6.242446 | Q92: =IFERROR(($M92-$P92)^2,"") -> 4.5900749 | R92: {=SUMPRODUCT((J92=$J$7:$J$1000)*(P92<$P$7:$P$1000))+1} -> 2 | T92: 14 | U92: SDL | V92: James Rivers | W92: NULL | X92: Away | Y92: SEA | Z92: 3.7900815
J93: 5 | K93: MIA | L93: Tomás Casares | M93: 3.9 | N93: Home | O93: UTAH | P93: =VLOOKUP($N93,$F$3:$G$4,2,FALSE)+VLOOKUP($L93,$B$20:$C$150,2,FALSE)+VLOOKUP($O93,$A$6:$B$16,2,FALSE) -> 4.9147312 | Q93: =IFERROR(($M93-$P93)^2,"") -> 1.0296794 | R93: {=SUMPRODUCT((J93=$J$7:$J$1000)*(P93<$P$7:$P$1000))+1} -> 8 | T93: 14 | U93: SDL | V93: Jed Holloway | W93: NULL | X93: Away | Y93: SEA | Z93: 8.1391177
J94: 5 | K94: LA | L94: Jurie van Vuuren | M94: 2.6 | N94: Home | O94: SEA | P94: =VLOOKUP($N94,$F$3:$G$4,2,FALSE)+VLOOKUP($L94,$B$20:$C$150,2,FALSE)+VLOOKUP($O94,$A$6:$B$16,2,FALSE) -> 4.3093231 | Q94: =IFERROR(($M94-$P94)^2,"") -> 2.9217854 | R94: {=SUMPRODUCT((J94=$J$7:$J$1000)*(P94<$P$7:$P$1000))+1} -> 12 | T94: 14 | U94: SDL | V94: Vili Helu | W94: NULL | X94: Away | Y94: SEA | Z94: 6.1360128
J95: 5 | K95: MIA | L95: Federico Gutíerrez | M95: 2.2 | N95: Home | O95: UTAH | P95: =VLOOKUP($N95,$F$3:$G$4,2,FALSE)+VLOOKUP($L95,$B$20:$C$150,2,FALSE)+VLOOKUP($O95,$A$6:$B$16,2,FALSE) -> 2.3835671 | Q95: =IFERROR(($M95-$P95)^2,"") -> 0.033696883 | R95: {=SUMPRODUCT((J95=$J$7:$J$1000)*(P95<$P$7:$P$1000))+1} -> 16 | T95: 14 | U95: SDL | V95: Zak Farrance | W95: NULL | X95: Away | Y95: SEA | Z95: 0.29425654
J96: 5 | K96: NEFJ | L96: Sam Caird | M96: 2.1 | N96: Home | O96: NOLA | P96: =VLOOKUP($N96,$F$3:$G$4,2,FALSE)+VLOOKUP($L96,$B$20:$C$150,2,FALSE)+VLOOKUP($O96,$A$6:$B$16,2,FALSE) -> 4.216449 | Q96: =IFERROR(($M96-$P96)^2,"") -> 4.4793563 | R96: {=SUMPRODUCT((J96=$J$7:$J$1000)*(P96<$P$7:$P$1000))+1} -> 13 | T96: 14 | U96: SEA | V96: Isaia Lotawa | W96: NULL | X96: Home | Y96: SDL | Z96: 1.8720295
J97: 5 | K97: NOLA | L97: William Waguespack | M97: 2.1 | N97: Away | O97: NEFJ | P97: =VLOOKUP($N97,$F$3:$G$4,2,FALSE)+VLOOKUP($L97,$B$20:$C$150,2,FALSE)+VLOOKUP($O97,$A$6:$B$16,2,FALSE) -> 5.7794121 | Q97: =IFERROR(($M97-$P97)^2,"") -> 13.538073 | R97: {=SUMPRODUCT((J97=$J$7:$J$1000)*(P97<$P$7:$P$1000))+1} -> 5 | T97: 14 | U97: SEA | V97: Malembe Mpofu | W97: NULL | X97: Home | Y97: SDL | Z97: 3.6116082
J98: 5 | K98: UTAH | L98: Frank Lochore | M98: -0.9 | N98: Away | O98: MIA | P98: =VLOOKUP($N98,$F$3:$G$4,2,FALSE)+VLOOKUP($L98,$B$20:$C$150,2,FALSE)+VLOOKUP($O98,$A$6:$B$16,2,FALSE) -> 5.7315377 | Q98: =IFERROR(($M98-$P98)^2,"") -> 43.977292 | R98: {=SUMPRODUCT((J98=$J$7:$J$1000)*(P98<$P$7:$P$1000))+1} -> 7 | T98: 14 | U98: SEA | V98: OJ Noa | W98: NULL | X98: Home | Y98: SDL | Z98: 8.4822075
J99: 6 | K99: SDL | L99: Jed Holloway | M99: 14.2 | N99: Home | O99: MIA | P99: =VLOOKUP($N99,$F$3:$G$4,2,FALSE)+VLOOKUP($L99,$B$20:$C$150,2,FALSE)+VLOOKUP($O99,$A$6:$B$16,2,FALSE) -> 7.373083 | Q99: =IFERROR(($M99-$P99)^2,"") -> 46.606796 | R99: {=SUMPRODUCT((J99=$J$7:$J$1000)*(P99<$P$7:$P$1000))+1} -> 1 | T99: 14 | U99: SEA | V99: Rhyno Herbst | W99: NULL | X99: Home | Y99: SDL | Z99: 5.0005746
J100: 6 | K100: ARC | L100: Sam Golla | M100: 12.4 | N100: Home | O100: HOU | P100: =VLOOKUP($N100,$F$3:$G$4,2,FALSE)+VLOOKUP($L100,$B$20:$C$150,2,FALSE)+VLOOKUP($O100,$A$6:$B$16,2,FALSE) -> 6.3387154 | Q100: =IFERROR(($M100-$P100)^2,"") -> 36.739171 | R100: {=SUMPRODUCT((J100=$J$7:$J$1000)*(P100<$P$7:$P$1000))+1} -> 4 | T100: 14 | U100: SEA | V100: Siaosi Mahoni | W100: NULL | X100: Home | Y100: SDL | Z100: 4.8154421
J101: 6 | K101: LA | L101: Jurie van Vuuren | M101: 10.3 | N101: Away | O101: NOLA | P101: =VLOOKUP($N101,$F$3:$G$4,2,FALSE)+VLOOKUP($L101,$B$20:$C$150,2,FALSE)+VLOOKUP($O101,$A$6:$B$16,2,FALSE) -> 3.303663 | Q101: =IFERROR(($M101-$P101)^2,"") -> 48.948732 | R101: {=SUMPRODUCT((J101=$J$7:$J$1000)*(P101<$P$7:$P$1000))+1} -> 17 | T101: 14 | U101: SEA | V101: Taylor Krumrei | W101: NULL | X101: Home | Y101: SDL | Z101: 2.0348625
J102: 6 | K102: UTAH | L102: Frank Lochore | M102: 8.7 | N102: Away | O102: SEA | P102: =VLOOKUP($N102,$F$3:$G$4,2,FALSE)+VLOOKUP($L102,$B$20:$C$150,2,FALSE)+VLOOKUP($O102,$A$6:$B$16,2,FALSE) -> 6.5120136 | Q102: =IFERROR(($M102-$P102)^2,"") -> 4.7872845 | R102: {=SUMPRODUCT((J102=$J$7:$J$1000)*(P102<$P$7:$P$1000))+1} -> 3 | T102: 14 | U102: UTAH | V102: Frank Lochore | W102: NULL | X102: Away | Y102: HOU | Z102: 6.3097912
J103: 6 | K103: UTAH | L103: Gavin Thornbury | M103: 7.4 | N103: Away | O103: SEA | P103: =VLOOKUP($N103,$F$3:$G$4,2,FALSE)+VLOOKUP($L103,$B$20:$C$150,2,FALSE)+VLOOKUP($O103,$A$6:$B$16,2,FALSE) -> 5.4541545 | Q103: =IFERROR(($M103-$P103)^2,"") -> 3.7863146 | R103: {=SUMPRODUCT((J103=$J$7:$J$1000)*(P103<$P$7:$P$1000))+1} -> 9 | T103: 14 | U103: UTAH | V103: Gavin Thornbury | W103: NULL | X103: Away | Y103: HOU | Z103: 5.2519321
... J205: 11 | K205: MIA | L205: Rick Rose | M205: 5.8 | N205: Home | O205: ARC | P205: =VLOOKUP($N205,$F$3:$G$4,2,FALSE)+VLOOKUP($L205,$B$20:$C$150,2,FALSE)+VLOOKUP($O205,$A$6:$B$16,2,FALSE) -> 5.8079139 | Q205: =IFERROR(($M205-$P205)^2,"") -> 6.2629675e-05 | R205: {=SUMPRODUCT((J205=$J$7:$J$1000)*(P205<$P$7:$P$1000))+1} -> 9 | T205: 16 | U205: UTAH | V205: Saia 'Uhila | W205: NULL | X205: Home | Y205: ARC | Z205: 2.717046
J206: 11 | K206: SDL | L206: Vili Helu | M206: 5 | N206: Away | O206: LA | P206: =VLOOKUP($N206,$F$3:$G$4,2,FALSE)+VLOOKUP($L206,$B$20:$C$150,2,FALSE)+VLOOKUP($O206,$A$6:$B$16,2,FALSE) -> 5.9509438 | Q206: =IFERROR(($M206-$P206)^2,"") -> 0.90429405 | R206: {=SUMPRODUCT((J206=$J$7:$J$1000)*(P206<$P$7:$P$1000))+1} -> 7
J207: 11 | K207: CHI | L207: Mason Flesch | M207: 4.8 | N207: Away | O207: UTAH | P207: =VLOOKUP($N207,$F$3:$G$4,2,FALSE)+VLOOKUP($L207,$B$20:$C$150,2,FALSE)+VLOOKUP($O207,$A$6:$B$16,2,FALSE) -> 4.5554814 | Q207: =IFERROR(($M207-$P207)^2,"") -> 0.059789356 | R207: {=SUMPRODUCT((J207=$J$7:$J$1000)*(P207<$P$7:$P$1000))+1} -> 14
J208: 11 | K208: NOLA | L208: Cam Dolan | M208: 4.7 | N208: Home | O208: SEA | P208: =VLOOKUP($N208,$F$3:$G$4,2,FALSE)+VLOOKUP($L208,$B$20:$C$150,2,FALSE)+VLOOKUP($O208,$A$6:$B$16,2,FALSE) -> 3.987572 | Q208: =IFERROR(($M208-$P208)^2,"") -> 0.50755372 | R208: {=SUMPRODUCT((J208=$J$7:$J$1000)*(P208<$P$7:$P$1000))+1} -> 18
J209: 11 | K209: OGDC | L209: Tevita Naqali | M209: 4.5 | N209: Away | O209: HOU | P209: =VLOOKUP($N209,$F$3:$G$4,2,FALSE)+VLOOKUP($L209,$B$20:$C$150,2,FALSE)+VLOOKUP($O209,$A$6:$B$16,2,FALSE) -> 6.0985028 | Q209: =IFERROR(($M209-$P209)^2,"") -> 2.5552111 | R209: {=SUMPRODUCT((J209=$J$7:$J$1000)*(P209<$P$7:$P$1000))+1} -> 6
J210: 11 | K210: MIA | L210: Braemar Murray | M210: 4.1 | N210: Home | O210: ARC | P210: =VLOOKUP($N210,$F$3:$G$4,2,FALSE)+VLOOKUP($L210,$B$20:$C$150,2,FALSE)+VLOOKUP($O210,$A$6:$B$16,2,FALSE) -> 3.954997 | Q210: =IFERROR(($M210-$P210)^2,"") -> 0.021025873 | R210: {=SUMPRODUCT((J210=$J$7:$J$1000)*(P210<$P$7:$P$1000))+1} -> 19
J211: 11 | K211: SEA | L211: OJ Noa | M211: 4.1 | N211: Away | O211: NOLA | P211: =VLOOKUP($N211,$F$3:$G$4,2,FALSE)+VLOOKUP($L211,$B$20:$C$150,2,FALSE)+VLOOKUP($O211,$A$6:$B$16,2,FALSE) -> 7.0773657 | Q211: =IFERROR(($M211-$P211)^2,"") -> 8.8647066 | R211: {=SUMPRODUCT((J211=$J$7:$J$1000)*(P211<$P$7:$P$1000))+1} -> 4
J212: 11 | K212: ARC | L212: Viliami Vuli | M212: 3.5 | N212: Away | O212: MIA | P212: =VLOOKUP($N212,$F$3:$G$4,2,FALSE)+VLOOKUP($L212,$B$20:$C$150,2,FALSE)+VLOOKUP($O212,$A$6:$B$16,2,FALSE) -> 4.3507952 | Q212: =IFERROR(($M212-$P212)^2,"") -> 0.72385241 | R212: {=SUMPRODUCT((J212=$J$7:$J$1000)*(P212<$P$7:$P$1000))+1} -> 15
J213: 11 | K213: UTAH | L213: Matt Jenson | M213: 3.5 | N213: Home | O213: CHI | P213: =VLOOKUP($N213,$F$3:$G$4,2,FALSE)+VLOOKUP($L213,$B$20:$C$150,2,FALSE)+VLOOKUP($O213,$A$6:$B$16,2,FALSE) -> 5.0557941 | Q213: =IFERROR(($M213-$P213)^2,"") -> 2.4204954 | R213: {=SUMPRODUCT((J213=$J$7:$J$1000)*(P213<$P$7:$P$1000))+1} -> 11
J214: 11 | K214: ARC | L214: Sam Golla | M214: 3.4 | N214: Away | O214: MIA | P214: =VLOOKUP($N214,$F$3:$G$4,2,FALSE)+VLOOKUP($L214,$B$20:$C$150,2,FALSE)+VLOOKUP($O214,$A$6:$B$16,2,FALSE) -> 5.7460208 | Q214: =IFERROR(($M214-$P214)^2,"") -> 5.5038137 | R214: {=SUMPRODUCT((J214=$J$7:$J$1000)*(P214<$P$7:$P$1000))+1} -> 10
J215: 11 | K215: OGDC | L215: Rob Harley | M215: 3.3 | N215: Away | O215: HOU | P215: =VLOOKUP($N215,$F$3:$G$4,2,FALSE)+VLOOKUP($L215,$B$20:$C$150,2,FALSE)+VLOOKUP($O215,$A$6:$B$16,2,FALSE) -> 4.2530551 | Q215: =IFERROR(($M215-$P215)^2,"") -> 0.9083141 | R215: {=SUMPRODUCT((J215=$J$7:$J$1000)*(P215<$P$7:$P$1000))+1} -> 16
J216: 11 | K216: ARC | L216: Shawn Clark | M216: 3.1 | N216: Home | O216: MIA | P216: =VLOOKUP($N216,$F$3:$G$4,2,FALSE)+VLOOKUP($L216,$B$20:$C$150,2,FALSE)+VLOOKUP($O216,$A$6:$B$16,2,FALSE) -> 2.5505687 | Q216: =IFERROR(($M216-$P216)^2,"") -> 0.30187472 | R216: {=SUMPRODUCT((J216=$J$7:$J$1000)*(P216<$P$7:$P$1000))+1} -> 24
J217: 11 | K217: CHI | L217: Hamish Bain | M217: 2.9 | N217: Away | O217: UTAH | P217: =VLOOKUP($N217,$F$3:$G$4,2,FALSE)+VLOOKUP($L217,$B$20:$C$150,2,FALSE)+VLOOKUP($O217,$A$6:$B$16,2,FALSE) -> 3.4974691 | Q217: =IFERROR(($M217-$P217)^2,"") -> 0.35696928 | R217: {=SUMPRODUCT((J217=$J$7:$J$1000)*(P217<$P$7:$P$1000))+1} -> 22
... J248: 12 | K248: SDL | L248: Jed Holloway | M248: 2.1 | N248: Home | O248: NOLA | P248: =VLOOKUP($N248,$F$3:$G$4,2,FALSE)+VLOOKUP($L248,$B$20:$C$150,2,FALSE)+VLOOKUP($O248,$A$6:$B$16,2,FALSE) -> 7.1623399 | Q248: =IFERROR(($M248-$P248)^2,"") -> 25.627285 | R248: {=SUMPRODUCT((J248=$J$7:$J$1000)*(P248<$P$7:$P$1000))+1} -> 3
J249: 13 | K249: ARC | L249: Alejandro Martinez Tapia | M249: NULL | N249: Away | O249: LA | P249: =VLOOKUP($N249,$F$3:$G$4,2,FALSE)+VLOOKUP($L249,$B$20:$C$150,2,FALSE)+VLOOKUP($O249,$A$6:$B$16,2,FALSE) -> 5.7267055 | Q249: =IFERROR(($M249-$P249)^2,"") | R249: {=SUMPRODUCT((J249=$J$7:$J$1000)*(P249<$P$7:$P$1000))+1} -> 10
J250: 13 | K250: ARC | L250: Javon Camp Villalovos | M250: NULL | N250: Away | O250: LA | P250: =VLOOKUP($N250,$F$3:$G$4,2,FALSE)+VLOOKUP($L250,$B$20:$C$150,2,FALSE)+VLOOKUP($O250,$A$6:$B$16,2,FALSE) -> 2.5835745 | Q250: =IFERROR(($M250-$P250)^2,"") | R250: {=SUMPRODUCT((J250=$J$7:$J$1000)*(P250<$P$7:$P$1000))+1} -> 40
J251: 13 | K251: ARC | L251: Javon Camp Villalovos | M251: NULL | N251: Away | O251: SDL | P251: =VLOOKUP($N251,$F$3:$G$4,2,FALSE)+VLOOKUP($L251,$B$20:$C$150,2,FALSE)+VLOOKUP($O251,$A$6:$B$16,2,FALSE) -> 3.1678253 | Q251: =IFERROR(($M251-$P251)^2,"") | R251: {=SUMPRODUCT((J251=$J$7:$J$1000)*(P251<$P$7:$P$1000))+1} -> 36
J252: 13 | K252: ARC | L252: Mikey Grandy | M252: NULL | N252: Away | O252: LA | P252: =VLOOKUP($N252,$F$3:$G$4,2,FALSE)+VLOOKUP($L252,$B$20:$C$150,2,FALSE)+VLOOKUP($O252,$A$6:$B$16,2,FALSE) -> 4.5574912 | Q252: =IFERROR(($M252-$P252)^2,"") | R252: {=SUMPRODUCT((J252=$J$7:$J$1000)*(P252<$P$7:$P$1000))+1} -> 23
J253: 13 | K253: ARC | L253: Sam Golla | M253: NULL | N253: Away | O253: LA | P253: =VLOOKUP($N253,$F$3:$G$4,2,FALSE)+VLOOKUP($L253,$B$20:$C$150,2,FALSE)+VLOOKUP($O253,$A$6:$B$16,2,FALSE) -> 6.3414277 | Q253: =IFERROR(($M253-$P253)^2,"") | R253: {=SUMPRODUCT((J253=$J$7:$J$1000)*(P253<$P$7:$P$1000))+1} -> 6
J254: 13 | K254: ARC | L254: Shawn Clark | M254: NULL | N254: Away | O254: LA | P254: =VLOOKUP($N254,$F$3:$G$4,2,FALSE)+VLOOKUP($L254,$B$20:$C$150,2,FALSE)+VLOOKUP($O254,$A$6:$B$16,2,FALSE) -> 3.1315344 | Q254: =IFERROR(($M254-$P254)^2,"") | R254: {=SUMPRODUCT((J254=$J$7:$J$1000)*(P254<$P$7:$P$1000))+1} -> 37
J255: 13 | K255: ARC | L255: Viliami Vuli | M255: NULL | N255: Away | O255: LA | P255: =VLOOKUP($N255,$F$3:$G$4,2,FALSE)+VLOOKUP($L255,$B$20:$C$150,2,FALSE)+VLOOKUP($O255,$A$6:$B$16,2,FALSE) -> 4.946202 | Q255: =IFERROR(($M255-$P255)^2,"") | R255: {=SUMPRODUCT((J255=$J$7:$J$1000)*(P255<$P$7:$P$1000))+1} -> 20
J256: 13 | K256: CHI | L256: Hamish Bain | M256: NULL | N256: Away | O256: NEFJ | P256: =VLOOKUP($N256,$F$3:$G$4,2,FALSE)+VLOOKUP($L256,$B$20:$C$150,2,FALSE)+VLOOKUP($O256,$A$6:$B$16,2,FALSE) -> 4.1432377 | Q256: =IFERROR(($M256-$P256)^2,"") | R256: {=SUMPRODUCT((J256=$J$7:$J$1000)*(P256<$P$7:$P$1000))+1} -> 27
J257: 13 | K257: CHI | L257: James Scott | M257: NULL | N257: Away | O257: NEFJ | P257: =VLOOKUP($N257,$F$3:$G$4,2,FALSE)+VLOOKUP($L257,$B$20:$C$150,2,FALSE)+VLOOKUP($O257,$A$6:$B$16,2,FALSE) -> 5.0344107 | Q257: =IFERROR(($M257-$P257)^2,"") | R257: {=SUMPRODUCT((J257=$J$7:$J$1000)*(P257<$P$7:$P$1000))+1} -> 19
J258: 13 | K258: CHI | L258: Mason Flesch | M258: NULL | N258: Away | O258: NEFJ | P258: =VLOOKUP($N258,$F$3:$G$4,2,FALSE)+VLOOKUP($L258,$B$20:$C$150,2,FALSE)+VLOOKUP($O258,$A$6:$B$16,2,FALSE) -> 5.20125 | Q258: =IFERROR(($M258-$P258)^2,"") | R258: {=SUMPRODUCT((J258=$J$7:$J$1000)*(P258<$P$7:$P$1000))+1} -> 16
J259: 13 | K259: HOU | L259: Johan Momsen | M259: NULL | N259: Away | O259: SDL | P259: =VLOOKUP($N259,$F$3:$G$4,2,FALSE)+VLOOKUP($L259,$B$20:$C$150,2,FALSE)+VLOOKUP($O259,$A$6:$B$16,2,FALSE) -> 6.1758772 | Q259: =IFERROR(($M259-$P259)^2,"") | R259: {=SUMPRODUCT((J259=$J$7:$J$1000)*(P259<$P$7:$P$1000))+1} -> 7
J260: 13 | K260: HOU | L260: Justin Basson | M260: NULL | N260: Away | O260: SDL | P260: =VLOOKUP($N260,$F$3:$G$4,2,FALSE)+VLOOKUP($L260,$B$20:$C$150,2,FALSE)+VLOOKUP($O260,$A$6:$B$16,2,FALSE) -> 3.0066136 | Q260: =IFERROR(($M260-$P260)^2,"") | R260: {=SUMPRODUCT((J260=$J$7:$J$1000)*(P260<$P$7:$P$1000))+1} -> 38
... J447: 16 | K447: UTAH | L447: Saia 'Uhila | M447: NULL | N447: Home | O447: ARC | P447: =VLOOKUP($N447,$F$3:$G$4,2,FALSE)+VLOOKUP($L447,$B$20:$C$150,2,FALSE)+VLOOKUP($O447,$A$6:$B$16,2,FALSE) -> 2.717046 | Q447: =IFERROR(($M447-$P447)^2,"") | R447: {=SUMPRODUCT((J447=$J$7:$J$1000)*(P447<$P$7:$P$1000))+1} -> 40

Sheet BRvsDef
A1: BR vs Def 2025 | F1: Finished Week: | G1: 12
B2: 0
A3: Mean: | B3: =AVERAGE(B6:B48) -> -7.7267131e-09 | F3: Home | G3: -0.30000506
A4: (highest rank is most helpful matchup) | F4: Away | G4: =-G3 -> 0.30000506
A5: Team | B5: Rating | C5: Rank | Q5: =SUM($Q$7:$Q1000) -> 5951.0339
A6: ARC | B6: 0.97013303 | C6: =RANK($B6,$B$6:$B$16,0) -> 1 | J6: Rnd | K6: Team | L6: Player | M6: Points | N6: home | O6: Opp | P6: Forecast | Q6: Squared Error | R6: GroupRnk | T6: Remaining Games for ROFS Calc | AA6: Players | AB6: Rnd
A7: NOLA | B7: 0.86579235 | C7: =RANK($B7,$B$6:$B$16,0) -> 2 | J7: 1 | K7: ARC | L7: Makeen Alikhan | M7: 16.2 | N7: Away | O7: NOLA | P7: =VLOOKUP($N7,$F$3:$G$4,2,FALSE)+VLOOKUP($L7,$B$20:$C$150,2,FALSE)+VLOOKUP($O7,$A$6:$B$16,2,FALSE) -> 9.4159483 | Q7: =IFERROR(($M7-$P7)^2,"") -> 46.023357 | R7: {=SUMPRODUCT((J7=$J$7:$J$1000)*(P7<$P$7:$P$1000))+1} -> 9 | T7: {=_xlfn._xlws.FILTER($J$7:$P$10000,($J$7:$J$10000>$G$1)*($J$7:$J$10000<18))} -> 13 | U7: ARC | V7: Albert O'Shannessey | W7: NULL | X7: Away | Y7: LA | Z7: 4.2397848 | AA7: {=_xlfn._xlws.SORT(_xlfn.UNIQUE($L$7:$L$10000))} -> Aidan King | AB7: {=COUNT(_xlfn._xlws.FILTER($J$7:$J$10000,($L$7:$L$10000=AA7)*($M$7:$M$10000<>"NULL")*($J$7:$J$10000 >= ($G$1-5))))/5} -> 1
A8: SDL | B8: 0.85900411 | C8: =RANK($B8,$B$6:$B$16,0) -> 3 | J8: 1 | K8: NEFJ | L8: Jed Melvin | M8: 15.5 | N8: Away | O8: LA | P8: =VLOOKUP($N8,$F$3:$G$4,2,FALSE)+VLOOKUP($L8,$B$20:$C$150,2,FALSE)+VLOOKUP($O8,$A$6:$B$16,2,FALSE) -> 12.183721 | Q8: =IFERROR(($M8-$P8)^2,"") -> 10.997705 | R8: {=SUMPRODUCT((J8=$J$7:$J$1000)*(P8<$P$7:$P$1000))+1} -> 2 | T8: 13 | U8: ARC | V8: Alejandro Martinez Tapia | W8: NULL | X8: Away | Y8: LA | Z8: 6.7814523 | AA8: Albert O'Shannessey | AB8: {=COUNT(_xlfn._xlws.FILTER($J$7:$J$10000,($L$7:$L$10000=AA8)*($M$7:$M$10000<>"NULL")*($J$7:$J$10000 >= ($G$1-5))))/5} -> 0.6
A9: CHI | B9: 0.72014556 | C9: =RANK($B9,$B$6:$B$16,0) -> 4 | J9: 1 | K9: SDL | L9: Christian Poidevin | M9: 12.7 | N9: Home | O9: SEA | P9: =VLOOKUP($N9,$F$3:$G$4,2,FALSE)+VLOOKUP($L9,$B$20:$C$150,2,FALSE)+VLOOKUP($O9,$A$6:$B$16,2,FALSE) -> 11.410433 | Q9: =IFERROR(($M9-$P9)^2,"") -> 1.662984 | R9: {=SUMPRODUCT((J9=$J$7:$J$1000)*(P9<$P$7:$P$1000))+1} -> 3 | T9: 13 | U9: ARC | V9: Colin Turner | W9: NULL | X9: Away | Y9: LA | Z9: 5.2378288 | AA9: Alejandro Martinez Tapia | AB9: {=COUNT(_xlfn._xlws.FILTER($J$7:$J$10000,($L$7:$L$10000=AA9)*($M$7:$M$10000<>"NULL")*($J$7:$J$10000 >= ($G$1-5))))/5} -> 0.4
A10: SEA | B10: 0.33956018 | C10: =RANK($B10,$B$6:$B$16,0) -> 5 | J10: 1 | K10: CHI | L10: Maclean Jones | M10: 11.2 | N10: Away | O10: HOU | P10: =VLOOKUP($N10,$F$3:$G$4,2,FALSE)+VLOOKUP($L10,$B$20:$C$150,2,FALSE)+VLOOKUP($O10,$A$6:$B$16,2,FALSE) -> 9.9740523 | Q10: =IFERROR(($M10-$P10)^2,"") -> 1.5029478 | R10: {=SUMPRODUCT((J10=$J$7:$J$1000)*(P10<$P$7:$P$1000))+1} -> 5 | T10: 13 | U10: ARC | V10: Dylan Fortune | W10: NULL | X10: Away | Y10: LA | Z10: 4.0489856 | AA10: Aminae Amiatu-Tanoi | AB10: {=COUNT(_xlfn._xlws.FILTER($J$7:$J$10000,($L$7:$L$10000=AA10)*($M$7:$M$10000<>"NULL")*($J$7:$J$10000 >= ($G$1-5))))/5} -> 0.2
A11: LA | B11: -0.053424802 | C11: =RANK($B11,$B$6:$B$16,0) -> 6 | J11: 1 | K11: NEFJ | L11: Joe Johnston | M11: 10.8 | N11: Away | O11: LA | P11: =VLOOKUP($N11,$F$3:$G$4,2,FALSE)+VLOOKUP($L11,$B$20:$C$150,2,FALSE)+VLOOKUP($O11,$A$6:$B$16,2,FALSE) -> 9.7333189 | Q11: =IFERROR(($M11-$P11)^2,"") -> 1.1378086 | R11: {=SUMPRODUCT((J11=$J$7:$J$1000)*(P11<$P$7:$P$1000))+1} -> 7 | T11: 13 | U11: ARC | V11: Graeme Pedegana | W11: NULL | X11: Away | Y11: LA | Z11: 6.3538157 | AA11: Bailey Wilson | AB11: {=COUNT(_xlfn._xlws.FILTER($J$7:$J$10000,($L$7:$L$10000=AA11)*($M$7:$M$10000<>"NULL")*($J$7:$J$10000 >= ($G$1-5))))/5} -> 0.4
A12: HOU | B12: -0.10298824 | C12: =RANK($B12,$B$6:$B$16,0) -> 7 | J12: 1 | K12: SDL | L12: Brad Wilkin | M12: 9.9 | N12: Home | O12: SEA | P12: =VLOOKUP($N12,$F$3:$G$4,2,FALSE)+VLOOKUP($L12,$B$20:$C$150,2,FALSE)+VLOOKUP($O12,$A$6:$B$16,2,FALSE) -> 9.8868535 | Q12: =IFERROR(($M12-$P12)^2,"") -> 0.00017283 | R12: {=SUMPRODUCT((J12=$J$7:$J$1000)*(P12<$P$7:$P$1000))+1} -> 6 | T12: 13 | U12: ARC | V12: Makeen Alikhan | W12: NULL | X12: Away | Y12: LA | Z12: 8.4967312 | AA12: Ben Houston | AB12: {=COUNT(_xlfn._xlws.FILTER($J$7:$J$10000,($L$7:$L$10000=AA12)*($M$7:$M$10000<>"NULL")*($J$7:$J$10000 >= ($G$1-5))))/5} -> 1
A13: MIA | B13: -0.40737348 | C13: =RANK($B13,$B$6:$B$16,0) -> 8 | J13: 1 | K13: LA | L13: Ed Timpson | M13: 9 | N13: Home | O13: NEFJ | P13: =VLOOKUP($N13,$F$3:$G$4,2,FALSE)+VLOOKUP($L13,$B$20:$C$150,2,FALSE)+VLOOKUP($O13,$A$6:$B$16,2,FALSE) -> 8.8741715 | Q13: =IFERROR(($M13-$P13)^2,"") -> 0.015832809 | R13: {=SUMPRODUCT((J13=$J$7:$J$1000)*(P13<$P$7:$P$1000))+1} -> 11 | T13: 13 | U13: ARC | V13: Sam Golla | W13: NULL | X13: Away | Y13: LA | Z13: 5.8808243 | AA13: Benjamin Bonasso | AB13: {=COUNT(_xlfn._xlws.FILTER($J$7:$J$10000,($L$7:$L$10000=AA13)*($M$7:$M$10000<>"NULL")*($J$7:$J$10000 >= ($G$1-5))))/5} -> 1
A14: OGDC | B14: -0.47148254 | C14: =RANK($B14,$B$6:$B$16,0) -> 9 | J14: 1 | K14: SEA | L14: OJ Noa | M14: 8.9 | N14: Away | O14: SDL | P14: =VLOOKUP($N14,$F$3:$G$4,2,FALSE)+VLOOKUP($L14,$B$20:$C$150,2,FALSE)+VLOOKUP($O14,$A$6:$B$16,2,FALSE) -> 7.0753367 | Q14: =IFERROR(($M14-$P14)^2,"") -> 3.3293963 | R14: {=SUMPRODUCT((J14=$J$7:$J$1000)*(P14<$P$7:$P$1000))+1} -> 20 | T14: 13 | U14: ARC | V14: Tomalati Ma'afu | W14: NULL | X14: Away | Y14: LA | Z14: 5.3221918 | AA14: Brad Tucker | AB14: {=COUNT(_xlfn._xlws.FILTER($J$7:$J$10000,($L$7:$L$10000=AA14)*($M$7:$M$10000<>"NULL")*($J$7:$J$10000 >= ($G$1-5))))/5} -> 0.2
A15: UTAH | B15: -1.0567835 | C15: =RANK($B15,$B$6:$B$16,0) -> 10 | J15: 1 | K15: CHI | L15: Mason Flesch | M15: 8.2 | N15: Away | O15: HOU | P15: =VLOOKUP($N15,$F$3:$G$4,2,FALSE)+VLOOKUP($L15,$B$20:$C$150,2,FALSE)+VLOOKUP($O15,$A$6:$B$16,2,FALSE) -> 9.6162547 | Q15: =IFERROR(($M15-$P15)^2,"") -> 2.0057773 | R15: {=SUMPRODUCT((J15=$J$7:$J$1000)*(P15<$P$7:$P$1000))+1} -> 8 | T15: 13 | U15: CHI | V15: Brad Tucker | W15: NULL | X15: Away | Y15: NEFJ | Z15: 2.3887153 | AA15: Brad Wilkin | AB15: {=COUNT(_xlfn._xlws.FILTER($J$7:$J$10000,($L$7:$L$10000=AA15)*($M$7:$M$10000<>"NULL")*($J$7:$J$10000 >= ($G$1-5))))/5} -> 1
A16: NEFJ | B16: -1.6625828 | C16: =RANK($B16,$B$6:$B$16,0) -> 11 | J16: 1 | K16: NOLA | L16: Jonah Mau'u | M16: 8 | N16: Home | O16: ARC | P16: =VLOOKUP($N16,$F$3:$G$4,2,FALSE)+VLOOKUP($L16,$B$20:$C$150,2,FALSE)+VLOOKUP($O16,$A$6:$B$16,2,FALSE) -> 13.93141 | Q16: =IFERROR(($M16-$P16)^2,"") -> 35.181619 | R16: {=SUMPRODUCT((J16=$J$7:$J$1000)*(P16<$P$7:$P$1000))+1} -> 1 | T16: 13 | U16: CHI | V16: Conall Boomer | W16: NULL | X16: Away | Y16: NEFJ | Z16: 5.1784374 | AA16: Charles Elton | AB16: {=COUNT(_xlfn._xlws.FILTER($J$7:$J$10000,($L$7:$L$10000=AA16)*($M$7:$M$10000<>"NULL")*($J$7:$J$10000 >= ($G$1-5))))/5} -> 1.2
J17: 1 | K17: MIA | L17: Benjamin Bonasso | M17: 7.7 | N17: Home | O17: OGDC | P17: =VLOOKUP($N17,$F$3:$G$4,2,FALSE)+VLOOKUP($L17,$B$20:$C$150,2,FALSE)+VLOOKUP($O17,$A$6:$B$16,2,FALSE) -> 8.002076 | Q17: =IFERROR(($M17-$P17)^2,"") -> 0.091249918 | R17: {=SUMPRODUCT((J17=$J$7:$J$1000)*(P17<$P$7:$P$1000))+1} -> 14 | T17: 13 | U17: CHI | V17: Lucas Rumball | W17: NULL | X17: Away | Y17: NEFJ | Z17: 7.0948291 | AA17: Christian Poidevin | AB17: {=COUNT(_xlfn._xlws.FILTER($J$7:$J$10000,($L$7:$L$10000=AA17)*($M$7:$M$10000<>"NULL")*($J$7:$J$10000 >= ($G$1-5))))/5} -> 1
J18: 1 | K18: NOLA | L18: Tesimoni Tonga'uiha | M18: 7 | N18: Home | O18: ARC | P18: =VLOOKUP($N18,$F$3:$G$4,2,FALSE)+VLOOKUP($L18,$B$20:$C$150,2,FALSE)+VLOOKUP($O18,$A$6:$B$16,2,FALSE) -> 6.8481086 | Q18: =IFERROR(($M18-$P18)^2,"") -> 0.023071011 | R18: {=SUMPRODUCT((J18=$J$7:$J$1000)*(P18<$P$7:$P$1000))+1} -> 22 | T18: 13 | U18: CHI | V18: Luke White | W18: NULL | X18: Away | Y18: NEFJ | Z18: 2.9133326 | AA18: Cian Darling | AB18: {=COUNT(_xlfn._xlws.FILTER($J$7:$J$10000,($L$7:$L$10000=AA18)*($M$7:$M$10000<>"NULL")*($J$7:$J$10000 >= ($G$1-5))))/5} -> 0.2
A19: PlayerID | B19: Player | C19: OverallRating | D19: OverallRank | E19: WeeklyRating | F19: WeeklyRank | G19: ROFSRating | H19: ROFSRank | I19: Last5GamesStart% | J19: 1 | K19: LA | L19: Tim Anstee | M19: 6.8 | N19: Home | O19: NEFJ | P19: =VLOOKUP($N19,$F$3:$G$4,2,FALSE)+VLOOKUP($L19,$B$20:$C$150,2,FALSE)+VLOOKUP($O19,$A$6:$B$16,2,FALSE) -> 2.2080017 | Q19: =IFERROR(($M19-$P19)^2,"") -> 21.086449 | R19: {=SUMPRODUCT((J19=$J$7:$J$1000)*(P19<$P$7:$P$1000))+1} -> 30 | T19: 13 | U19: CHI | V19: Maclean Jones | W19: NULL | X19: Away | Y19: NEFJ | Z19: 8.4144577 | AA19: Colin Turner | AB19: {=COUNT(_xlfn._xlws.FILTER($J$7:$J$10000,($L$7:$L$10000=AA19)*($M$7:$M$10000<>"NULL")*($J$7:$J$10000 >= ($G$1-5))))/5} -> 0.8
A20: =VLOOKUP($B20, PlayerIDs!$A$1:$B$516, 2, FALSE) -> 637 | B20: Jonah Mau'u | C20: 13.261282 | D20: =RANK($C20,$C$20:$C$106) -> 1 | E20: {=IFERROR(VLOOKUP($B20,_xlfn._xlws.FILTER($L$7:$P$10000,$J$7:$J$10000=G$1+1),5, FALSE), 0)} -> 12.553903 | F20: =RANK(E20,$E$20:$E$100) -> 3 | G20: =SUMIF(V:Z,$B20,Z:Z) -> 38.739828 | H20: =RANK($G20,$G$20:$G$106) -> 7 | I20: {=COUNT(_xlfn._xlws.FILTER($J$7:$J$10000,($L$7:$L$10000=B20)*($M$7:$M$10000<>"NULL")*($J$7:$J$10000 >= ($G$1-4))))/5} -> 0.6 | J20: 1 | K20: NEFJ | L20: Jero Gomez Vara | M20: 6.6 | N20: Away | O20: LA | P20: =VLOOKUP($N20,$F$3:$G$4,2,FALSE)+VLOOKUP($L20,$B$20:$C$150,2,FALSE)+VLOOKUP($O20,$A$6:$B$16,2,FALSE) -> 7.5226543 | Q20: =IFERROR(($M20-$P20)^2,"") -> 0.85129103 | R20: {=SUMPRODUCT((J20=$J$7:$J$1000)*(P20<$P$7:$P$1000))+1} -> 17 | T20: 13 | U20: CHI | V20: Mason Flesch | W20: NULL | X20: Away | Y20: NEFJ | Z20: 8.0566601 | AA20: Collin Grosse | AB20: {=COUNT(_xlfn._xlws.FILTER($J$7:$J$10000,($L$7:$L$10000=AA20)*($M$7:$M$10000<>"NULL")*($J$7:$J$10000 >= ($G$1-5))))/5} -> 0.8
A21: =VLOOKUP($B21, PlayerIDs!$A$1:$B$516, 2, FALSE) -> 609 | B21: Manuel Ardao | C21: 12.10855 | D21: =RANK($C21,$C$20:$C$106) -> 2 | E21: {=IFERROR(VLOOKUP($B21,_xlfn._xlws.FILTER($L$7:$P$10000,$J$7:$J$10000=G$1+1),5, FALSE), 0)} -> 13.274347 | F21: =RANK(E21,$E$20:$E$100) -> 1 | G21: =SUMIF(V:Z,$B21,Z:Z) -> 48.442988 | H21: =RANK($G21,$G$20:$G$106) -> 1 | I21: {=COUNT(_xlfn._xlws.FILTER($J$7:$J$10000,($L$7:$L$10000=B21)*($M$7:$M$10000<>"NULL")*($J$7:$J$10000 >= ($G$1-4))))/5} -> 0.6 | J21: 1 | K21: HOU | L21: Marno Redelinghuys | M21: 6.3 | N21: Home | O21: CHI | P21: =VLOOKUP($N21,$F$3:$G$4,2,FALSE)+VLOOKUP($L21,$B$20:$C$150,2,FALSE)+VLOOKUP($O21,$A$6:$B$16,2,FALSE) -> 5.2342101 | Q21: =IFERROR(($M21-$P21)^2,"") -> 1.1359082 | R21: {=SUMPRODUCT((J21=$J$7:$J$1000)*(P21<$P$7:$P$1000))+1} -> 24 | T21: 13 | U21: CHI | V21: Matt Oworu | W21: NULL | X21: Away | Y21: NEFJ | Z21: 5.4885535 | AA21: Conall Boomer | AB21: {=COUNT(_xlfn._xlws.FILTER($J$7:$J$10000,($L$7:$L$10000=AA21)*($M$7:$M$10000<>"NULL")*($J$7:$J$10000 >= ($G$1-5))))/5} -> 0.2
A22: =VLOOKUP($B22, PlayerIDs!$A$1:$B$516, 2, FALSE) -> 736 | B22: Jed Melvin | C22: 11.937141 | D22: =RANK($C22,$C$20:$C$106) -> 3 | E22: {=IFERROR(VLOOKUP($B22,_xlfn._xlws.FILTER($L$7:$P$10000,$J$7:$J$10000=G$1+1),5, FALSE), 0)} -> 12.357281 | F22: =RANK(E22,$E$20:$E$100) -> 4 | G22: =SUMIF(V:Z,$B22,Z:Z) -> 47.329403 | H22: =RANK($G22,$G$20:$G$106) -> 2 | I22: {=COUNT(_xlfn._xlws.FILTER($J$7:$J$10000,($L$7:$L$10000=B22)*($M$7:$M$10000<>"NULL")*($J$7:$J$10000 >= ($G$1-4))))/5} -> 0.8 | J22: 1 | K22: LA | L22: Ben Houston | M22: 5.3 | N22: Home | O22: NEFJ | P22: =VLOOKUP($N22,$F$3:$G$4,2,FALSE)+VLOOKUP($L22,$B$20:$C$150,2,FALSE)+VLOOKUP($O22,$A$6:$B$16,2,FALSE) -> 8.8707941 | Q22: =IFERROR(($M22-$P22)^2,"") -> 12.75057 | R22: {=SUMPRODUCT((J22=$J$7:$J$1000)*(P22<$P$7:$P$1000))+1} -> 12 | T22: 13 | U22: HOU | V22: Emmanuel Albert | W22: NULL | X22: Away | Y22: SDL | Z22: 8.2478046 | AA22: Cory Daniel | AB22: {=COUNT(_xlfn._xlws.FILTER($J$7:$J$10000,($L$7:$L$10000=AA22)*($M$7:$M$10000<>"NULL")*($J$7:$J$10000 >= ($G$1-5))))/5} -> 1
A23: =VLOOKUP($B23, PlayerIDs!$A$1:$B$516, 2, FALSE) -> 566 | B23: Sam Tuifua | C23: 11.77118 | D23: =RANK($C23,$C$20:$C$106) -> 4 | E23: {=IFERROR(VLOOKUP($B23,_xlfn._xlws.FILTER($L$7:$P$10000,$J$7:$J$10000=G$1+1),5, FALSE), 0)} -> 12.930189 | F23: =RANK(E23,$E$20:$E$100) -> 2 | G23: =SUMIF(V:Z,$B23,Z:Z) -> 35.755325 | H23: =RANK($G23,$G$20:$G$106) -> 11 | I23: {=COUNT(_xlfn._xlws.FILTER($J$7:$J$10000,($L$7:$L$10000=B23)*($M$7:$M$10000<>"NULL")*($J$7:$J$10000 >= ($G$1-4))))/5} -> 1 | J23: 1 | K23: NOLA | L23: Kellen Galletier | M23: 5.1 | N23: Home | O23: ARC | P23: =VLOOKUP($N23,$F$3:$G$4,2,FALSE)+VLOOKUP($L23,$B$20:$C$150,2,FALSE)+VLOOKUP($O23,$A$6:$B$16,2,FALSE) -> 5.1096297 | Q23: =IFERROR(($M23-$P23)^2,"") -> 9.2731817e-05 | R23: {=SUMPRODUCT((J23=$J$7:$J$1000)*(P23<$P$7:$P$1000))+1} -> 26 | T23: 13 | U23: HOU | V23: Johan Momsen | W23: NULL | X23: Away | Y23: SDL | Z23: 7.2145174 | AA23: Devin Short | AB23: {=COUNT(_xlfn._xlws.FILTER($J$7:$J$10000,($L$7:$L$10000=AA23)*($M$7:$M$10000<>"NULL")*($J$7:$J$10000 >= ($G$1-5))))/5} -> 0.2
A24: =VLOOKUP($B24, PlayerIDs!$A$1:$B$516, 2, FALSE) -> 68 | B24: Christian Poidevin | C24: 11.370878 | D24: =RANK($C24,$C$20:$C$106) -> 5 | E24: {=IFERROR(VLOOKUP($B24,_xlfn._xlws.FILTER($L$7:$P$10000,$J$7:$J$10000=G$1+1),5, FALSE), 0)} -> 10.967884 | F24: =RANK(E24,$E$20:$E$100) -> 8 | G24: =SUMIF(V:Z,$B24,Z:Z) -> 34.241836 | H24: =RANK($G24,$G$20:$G$106) -> 15 | I24: {=COUNT(_xlfn._xlws.FILTER($J$7:$J$10000,($L$7:$L$10000=B24)*($M$7:$M$10000<>"NULL")*($J$7:$J$10000 >= ($G$1-4))))/5} -> 1 | J24: 1 | K24: SEA | L24: Devin Short | M24: 4.9 | N24: Away | O24: SDL | P24: =VLOOKUP($N24,$F$3:$G$4,2,FALSE)+VLOOKUP($L24,$B$20:$C$150,2,FALSE)+VLOOKUP($O24,$A$6:$B$16,2,FALSE) -> 8.9174346 | Q24: =IFERROR(($M24-$P24)^2,"") -> 16.139781 | R24: {=SUMPRODUCT((J24=$J$7:$J$1000)*(P24<$P$7:$P$1000))+1} -> 10 | T24: 13 | U24: HOU | V24: Keni Nasoqeqe | W24: NULL | X24: Away | Y24: SDL | Z24: 3.5932114 | AA24: Dylan Fortune | AB24: {=COUNT(_xlfn._xlws.FILTER($J$7:$J$10000,($L$7:$L$10000=AA24)*($M$7:$M$10000<>"NULL")*($J$7:$J$10000 >= ($G$1-5))))/5} -> 0.2
A25: =VLOOKUP($B25, PlayerIDs!$A$1:$B$516, 2, FALSE) -> 752 | B25: Ed Timpson | C25: 10.836759 | D25: =RANK($C25,$C$20:$C$106) -> 6 | E25: {=IFERROR(VLOOKUP($B25,_xlfn._xlws.FILTER($L$7:$P$10000,$J$7:$J$10000=G$1+1),5, FALSE), 0)} -> 11.506887 | F25: =RANK(E25,$E$20:$E$100) -> 5 | G25: =SUMIF(V:Z,$B25,Z:Z) -> 44.15846 | H25: =RANK($G25,$G$20:$G$106) -> 3 | I25: {=COUNT(_xlfn._xlws.FILTER($J$7:$J$10000,($L$7:$L$10000=B25)*($M$7:$M$10000<>"NULL")*($J$7:$J$10000 >= ($G$1-4))))/5} -> 0.8 | J25: 1 | K25: MIA | L25: Marques Fuala'au | M25: 4.7 | N25: Home | O25: OGDC | P25: =VLOOKUP($N25,$F$3:$G$4,2,FALSE)+VLOOKUP($L25,$B$20:$C$150,2,FALSE)+VLOOKUP($O25,$A$6:$B$16,2,FALSE) -> 3.0636468 | Q25: =IFERROR(($M25-$P25)^2,"") -> 2.6776517 | R25: {=SUMPRODUCT((J25=$J$7:$J$1000)*(P25<$P$7:$P$1000))+1} -> 29 | T25: 13 | U25: HOU | V25: Marno Redelinghuys | W25: NULL | X25: Away | Y25: SDL | Z25: 5.9730787 | AA25: Dylan Nel | AB25: {=COUNT(_xlfn._xlws.FILTER($J$7:$J$10000,($L$7:$L$10000=AA25)*($M$7:$M$10000<>"NULL")*($J$7:$J$10000 >= ($G$1-5))))/5} -> 0.8
A26: =VLOOKUP($B26, PlayerIDs!$A$1:$B$516, 2, FALSE) -> 751 | B26: Ben Houston | C26: 10.833382 | D26: =RANK($C26,$C$20:$C$106) -> 7 | E26: {=IFERROR(VLOOKUP($B26,_xlfn._xlws.FILTER($L$7:$P$10000,$J$7:$J$10000=G$1+1),5, FALSE), 0)} -> 11.50351 | F26: =RANK(E26,$E$20:$E$100) -> 6 | G26: =SUMIF(V:Z,$B26,Z:Z) -> 44.14495 | H26: =RANK($G26,$G$20:$G$106) -> 4 | I26: {=COUNT(_xlfn._xlws.FILTER($J$7:$J$10000,($L$7:$L$10000=B26)*($M$7:$M$10000<>"NULL")*($J$7:$J$10000 >= ($G$1-4))))/5} -> 0.8 | J26: 1 | K26: OGDC | L26: Lautaro Bavaro | M26: 4.5 | N26: Away | O26: MIA | P26: =VLOOKUP($N26,$F$3:$G$4,2,FALSE)+VLOOKUP($L26,$B$20:$C$150,2,FALSE)+VLOOKUP($O26,$A$6:$B$16,2,FALSE) -> 5.8532116 | Q26: =IFERROR(($M26-$P26)^2,"") -> 1.8311816 | R26: {=SUMPRODUCT((J26=$J$7:$J$1000)*(P26<$P$7:$P$1000))+1} -> 23 | T26: 13 | U26: HOU | V26: Ronan Murphy | W26: NULL | X26: Away | Y26: SDL | Z26: 4.5147437 | AA26: Ed Timpson | AB26: {=COUNT(_xlfn._xlws.FILTER($J$7:$J$10000,($L$7:$L$10000=AA26)*($M$7:$M$10000<>"NULL")*($J$7:$J$10000 >= ($G$1-5))))/5} -> 1
A27: =VLOOKUP($B27, PlayerIDs!$A$1:$B$516, 2, FALSE) -> 595 | B27: Semi Kunitani | C27: 10.617796 | D27: =RANK($C27,$C$20:$C$106) -> 8 | E27: {=IFERROR(VLOOKUP($B27,_xlfn._xlws.FILTER($L$7:$P$10000,$J$7:$J$10000=G$1+1),5, FALSE), 0)} -> 11.287924 | F27: =RANK(E27,$E$20:$E$100) -> 7 | G27: =SUMIF(V:Z,$B27,Z:Z) -> 43.282606 | H27: =RANK($G27,$G$20:$G$106) -> 5 | I27: {=COUNT(_xlfn._xlws.FILTER($J$7:$J$10000,($L$7:$L$10000=B27)*($M$7:$M$10000<>"NULL")*($J$7:$J$10000 >= ($G$1-4))))/5} -> 0.4 | J27: 1 | K27: ARC | L27: Dylan Fortune | M27: 4.1 | N27: Away | O27: NOLA | P27: =VLOOKUP($N27,$F$3:$G$4,2,FALSE)+VLOOKUP($L27,$B$20:$C$150,2,FALSE)+VLOOKUP($O27,$A$6:$B$16,2,FALSE) -> 4.9682027 | Q27: =IFERROR(($M27-$P27)^2,"") -> 0.753776 | R27: {=SUMPRODUCT((J27=$J$7:$J$1000)*(P27<$P$7:$P$1000))+1} -> 27 | T27: 13 | U27: HOU | V27: Sam Tuifua | W27: NULL | X27: Away | Y27: SDL | Z27: 12.930189 | AA27: Emmanuel Albert | AB27: {=COUNT(_xlfn._xlws.FILTER($J$7:$J$10000,($L$7:$L$10000=AA27)*($M$7:$M$10000<>"NULL")*($J$7:$J$10000 >= ($G$1-5))))/5} -> 1
A28: =VLOOKUP($B28, PlayerIDs!$A$1:$B$516, 2, FALSE) -> 729 | B28: Brad Wilkin | C28: 9.8472984 | D28: =RANK($C28,$C$20:$C$106) -> 9 | E28: {=IFERROR(VLOOKUP($B28,_xlfn._xlws.FILTER($L$7:$P$10000,$J$7:$J$10000=G$1+1),5, FALSE), 0)} -> 9.4443051 | F28: =RANK(E28,$E$20:$E$100) -> 11 | G28: =SUMIF(V:Z,$B28,Z:Z) -> 29.671099 | H28: =RANK($G28,$G$20:$G$106) -> 19 | I28: {=COUNT(_xlfn._xlws.FILTER($J$7:$J$10000,($L$7:$L$10000=B28)*($M$7:$M$10000<>"NULL")*($J$7:$J$10000 >= ($G$1-4))))/5} -> 0.8 | J28: 1 | K28: OGDC | L28: Jamason Fa'anana-Schultz | M28: 4.1 | N28: Away | O28: MIA | P28: =VLOOKUP($N28,$F$3:$G$4,2,FALSE)+VLOOKUP($L28,$B$20:$C$150,2,FALSE)+VLOOKUP($O28,$A$6:$B$16,2,FALSE) -> 7.4469573 | Q28: =IFERROR(($M28-$P28)^2,"") -> 11.202123 | R28: {=SUMPRODUCT((J28=$J$7:$J$1000)*(P28<$P$7:$P$1000))+1} -> 19 | T28: 13 | U28: LA | V28: Ben Houston | W28: NULL | X28: Home | Y28: ARC | Z28: 11.50351 | AA28: Frank Lochore | AB28: {=COUNT(_xlfn._xlws.FILTER($J$7:$J$10000,($L$7:$L$10000=AA28)*($M$7:$M$10000<>"NULL")*($J$7:$J$10000 >= ($G$1-5))))/5} -> 0.2
A29: =VLOOKUP($B29, PlayerIDs!$A$1:$B$516, 2, FALSE) -> 77 | B29: Collin Grosse | C29: 9.7771045 | D29: =RANK($C29,$C$20:$C$106) -> 10 | E29: {=IFERROR(VLOOKUP($B29,_xlfn._xlws.FILTER($L$7:$P$10000,$J$7:$J$10000=G$1+1),5, FALSE), 0)} -> 0 | F29: =RANK(E29,$E$20:$E$100) -> 66 | G29: =SUMIF(V:Z,$B29,Z:Z) -> 28.885444 | H29: =RANK($G29,$G$20:$G$106) -> 22 | I29: {=COUNT(_xlfn._xlws.FILTER($J$7:$J$10000,($L$7:$L$10000=B29)*($M$7:$M$10000<>"NULL")*($J$7:$J$10000 >= ($G$1-4))))/5} -> 0.6 | J29: 1 | K29: OGDC | L29: Cory Daniel | M29: 3.9 | N29: Away | O29: MIA | P29: =VLOOKUP($N29,$F$3:$G$4,2,FALSE)+VLOOKUP($L29,$B$20:$C$150,2,FALSE)+VLOOKUP($O29,$A$6:$B$16,2,FALSE) -> 7.8554748 | Q29: =IFERROR(($M29-$P29)^2,"") -> 15.645781 | R29: {=SUMPRODUCT((J29=$J$7:$J$1000)*(P29<$P$7:$P$1000))+1} -> 15 | T29: 13 | U29: LA | V29: Ed Timpson | W29: NULL | X29: Home | Y29: ARC | Z29: 11.506887 | AA29: Graeme Pedegana | AB29: {=COUNT(_xlfn._xlws.FILTER($J$7:$J$10000,($L$7:$L$10000=AA29)*($M$7:$M$10000<>"NULL")*($J$7:$J$10000 >= ($G$1-5))))/5} -> 0.2
A30: =VLOOKUP($B30, PlayerIDs!$A$1:$B$516, 2, FALSE) -> 277 | B30: Maclean Jones | C30: 9.7770355 | D30: =RANK($C30,$C$20:$C$106) -> 11 | E30: {=IFERROR(VLOOKUP($B30,_xlfn._xlws.FILTER($L$7:$P$10000,$J$7:$J$10000=G$1+1),5, FALSE), 0)} -> 8.4144577 | F30: =RANK(E30,$E$20:$E$100) -> 17 | G30: =SUMIF(V:Z,$B30,Z:Z) -> 39.22806 | H30: =RANK($G30,$G$20:$G$106) -> 6 | I30: {=COUNT(_xlfn._xlws.FILTER($J$7:$J$10000,($L$7:$L$10000=B30)*($M$7:$M$10000<>"NULL")*($J$7:$J$10000 >= ($G$1-4))))/5} -> 0.8 | J30: 1 | K30: CHI | L30: Lucas Rumball | M30: 3.4 | N30: Away | O30: HOU | P30: =VLOOKUP($N30,$F$3:$G$4,2,FALSE)+VLOOKUP($L30,$B$20:$C$150,2,FALSE)+VLOOKUP($O30,$A$6:$B$16,2,FALSE) -> 8.6544236 | Q30: =IFERROR(($M30-$P30)^2,"") -> 27.608968 | R30: {=SUMPRODUCT((J30=$J$7:$J$1000)*(P30<$P$7:$P$1000))+1} -> 13 | T30: 13 | U30: LA | V30: Jason Damm | W30: NULL | X30: Home | Y30: ARC | Z30: 6.670251 | AA30: Huw Taylor | AB30: {=COUNT(_xlfn._xlws.FILTER($J$7:$J$10000,($L$7:$L$10000=AA30)*($M$7:$M$10000<>"NULL")*($J$7:$J$10000 >= ($G$1-5))))/5} -> 0.4
A31: =VLOOKUP($B31, PlayerIDs!$A$1:$B$516, 2, FALSE) -> 789 | B31: Joe Johnston | C31: 9.4867386 | D31: =RANK($C31,$C$20:$C$106) -> 12 | E31: {=IFERROR(VLOOKUP($B31,_xlfn._xlws.FILTER($L$7:$P$10000,$J$7:$J$10000=G$1+1),5, FALSE), 0)} -> 9.9068791 | F31: =RANK(E31,$E$20:$E$100) -> 10 | G31: =SUMIF(V:Z,$B31,Z:Z) -> 37.527794 | H31: =RANK($G31,$G$20:$G$106) -> 10 | I31: {=COUNT(_xlfn._xlws.FILTER($J$7:$J$10000,($L$7:$L$10000=B31)*($M$7:$M$10000<>"NULL")*($J$7:$J$10000 >= ($G$1-4))))/5} -> 0.8 | J31: 1 | K31: SEA | L31: Huw Taylor | M31: 3.4 | N31: Away | O31: SDL | P31: =VLOOKUP($N31,$F$3:$G$4,2,FALSE)+VLOOKUP($L31,$B$20:$C$150,2,FALSE)+VLOOKUP($O31,$A$6:$B$16,2,FALSE) -> 7.5660737 | Q31: =IFERROR(($M31-$P31)^2,"") -> 17.35617 | R31: {=SUMPRODUCT((J31=$J$7:$J$1000)*(P31<$P$7:$P$1000))+1} -> 16 | T31: 13 | U31: LA | V31: Matt Heaton | W31: NULL | X31: Home | Y31: ARC | Z31: 6.504553 | AA31: Jamason Fa'anana-Schultz | AB31: {=COUNT(_xlfn._xlws.FILTER($J$7:$J$10000,($L$7:$L$10000=AA31)*($M$7:$M$10000<>"NULL")*($J$7:$J$10000 >= ($G$1-5))))/5} -> 0.4
... A76: =VLOOKUP($B76, PlayerIDs!$A$1:$B$516, 2, FALSE) -> 527 | B76: Albert O'Shannessey | C76: 3.9932046 | D76: =RANK($C76,$C$20:$C$106) -> 57 | E76: {=IFERROR(VLOOKUP($B76,_xlfn._xlws.FILTER($L$7:$P$10000,$J$7:$J$10000=G$1+1),5, FALSE), 0)} -> 4.2397848 | F76: =RANK(E76,$E$20:$E$100) -> 51 | G76: =SUMIF(V:Z,$B76,Z:Z) -> 15.111273 | H76: =RANK($G76,$G$20:$G$106) -> 55 | I76: {=COUNT(_xlfn._xlws.FILTER($J$7:$J$10000,($L$7:$L$10000=B76)*($M$7:$M$10000<>"NULL")*($J$7:$J$10000 >= ($G$1-4))))/5} -> 0.4 | J76: 3 | K76: HOU | L76: Sam Tuifua | M76: 5.8 | N76: Home | O76: SEA | P76: =VLOOKUP($N76,$F$3:$G$4,2,FALSE)+VLOOKUP($L76,$B$20:$C$150,2,FALSE)+VLOOKUP($O76,$A$6:$B$16,2,FALSE) -> 11.810735 | Q76: =IFERROR(($M76-$P76)^2,"") -> 36.128932 | R76: {=SUMPRODUCT((J76=$J$7:$J$1000)*(P76<$P$7:$P$1000))+1} -> 3 | T76: 14 | U76: ARC | V76: Graeme Pedegana | W76: NULL | X76: Home | Y76: OGDC | Z76: 5.3357478 | AA76: Wian Conradie | AB76: {=COUNT(_xlfn._xlws.FILTER($J$7:$J$10000,($L$7:$L$10000=AA76)*($M$7:$M$10000<>"NULL")*($J$7:$J$10000 >= ($G$1-5))))/5} -> 0.8
A77: =VLOOKUP($B77, PlayerIDs!$A$1:$B$516, 2, FALSE) -> 428 | B77: Tomás Casares | C77: 3.9338614 | D77: =RANK($C77,$C$20:$C$106) -> 58 | E77: {=IFERROR(VLOOKUP($B77,_xlfn._xlws.FILTER($L$7:$P$10000,$J$7:$J$10000=G$1+1),5, FALSE), 0)} -> 5.0996588 | F77: =RANK(E77,$E$20:$E$100) -> 46 | G77: =SUMIF(V:Z,$B77,Z:Z) -> 15.744234 | H77: =RANK($G77,$G$20:$G$106) -> 52 | I77: {=COUNT(_xlfn._xlws.FILTER($J$7:$J$10000,($L$7:$L$10000=B77)*($M$7:$M$10000<>"NULL")*($J$7:$J$10000 >= ($G$1-4))))/5} -> 0 | J77: 3 | K77: HOU | L77: Marno Redelinghuys | M77: 4.5 | N77: Home | O77: SEA | P77: =VLOOKUP($N77,$F$3:$G$4,2,FALSE)+VLOOKUP($L77,$B$20:$C$150,2,FALSE)+VLOOKUP($O77,$A$6:$B$16,2,FALSE) -> 4.8536247 | Q77: =IFERROR(($M77-$P77)^2,"") -> 0.12505042 | R77: {=SUMPRODUCT((J77=$J$7:$J$1000)*(P77<$P$7:$P$1000))+1} -> 27 | T77: 14 | U77: ARC | V77: Makeen Alikhan | W77: NULL | X77: Home | Y77: OGDC | Z77: 7.4786633 | AA77: 0 | AB77: {=COUNT(_xlfn._xlws.FILTER($J$7:$J$10000,($L$7:$L$10000=AA77)*($M$7:$M$10000<>"NULL")*($J$7:$J$10000 >= ($G$1-5))))/5} -> 0
A78: =VLOOKUP($B78, PlayerIDs!$A$1:$B$516, 2, FALSE) -> 564 | B78: Marques Fuala'au | C78: 3.8351344 | D78: =RANK($C78,$C$20:$C$106) -> 59 | E78: {=IFERROR(VLOOKUP($B78,_xlfn._xlws.FILTER($L$7:$P$10000,$J$7:$J$10000=G$1+1),5, FALSE), 0)} -> 5.0009318 | F78: =RANK(E78,$E$20:$E$100) -> 47 | G78: =SUMIF(V:Z,$B78,Z:Z) -> 15.349327 | H78: =RANK($G78,$G$20:$G$106) -> 53 | I78: {=COUNT(_xlfn._xlws.FILTER($J$7:$J$10000,($L$7:$L$10000=B78)*($M$7:$M$10000<>"NULL")*($J$7:$J$10000 >= ($G$1-4))))/5} -> 0.2 | J78: 3 | K78: NEFJ | L78: Jero Gomez Vara | M78: 4.5 | N78: Away | O78: CHI | P78: =VLOOKUP($N78,$F$3:$G$4,2,FALSE)+VLOOKUP($L78,$B$20:$C$150,2,FALSE)+VLOOKUP($O78,$A$6:$B$16,2,FALSE) -> 8.2962247 | Q78: =IFERROR(($M78-$P78)^2,"") -> 14.411322 | R78: {=SUMPRODUCT((J78=$J$7:$J$1000)*(P78<$P$7:$P$1000))+1} -> 12 | T78: 14 | U78: ARC | V78: Sam Golla | W78: NULL | X78: Home | Y78: OGDC | Z78: 4.8627565 | AB78: {=COUNT(_xlfn._xlws.FILTER($J$7:$J$10000,($L$7:$L$10000=AA78)*($M$7:$M$10000<>"NULL")*($J$7:$J$10000 >= ($G$1-5))))/5} -> 0
A79: =VLOOKUP($B79, PlayerIDs!$A$1:$B$516, 2, FALSE) -> 528 | B79: Dylan Fortune | C79: 3.8024053 | D79: =RANK($C79,$C$20:$C$106) -> 60 | E79: {=IFERROR(VLOOKUP($B79,_xlfn._xlws.FILTER($L$7:$P$10000,$J$7:$J$10000=G$1+1),5, FALSE), 0)} -> 4.0489856 | F79: =RANK(E79,$E$20:$E$100) -> 54 | G79: =SUMIF(V:Z,$B79,Z:Z) -> 14.348076 | H79: =RANK($G79,$G$20:$G$106) -> 57 | I79: {=COUNT(_xlfn._xlws.FILTER($J$7:$J$10000,($L$7:$L$10000=B79)*($M$7:$M$10000<>"NULL")*($J$7:$J$10000 >= ($G$1-4))))/5} -> 0.2 | J79: 3 | K79: ARC | L79: Makeen Alikhan | M79: 4.4 | N79: Home | O79: MIA | P79: =VLOOKUP($N79,$F$3:$G$4,2,FALSE)+VLOOKUP($L79,$B$20:$C$150,2,FALSE)+VLOOKUP($O79,$A$6:$B$16,2,FALSE) -> 7.5427724 | Q79: =IFERROR(($M79-$P79)^2,"") -> 9.8770181 | R79: {=SUMPRODUCT((J79=$J$7:$J$1000)*(P79<$P$7:$P$1000))+1} -> 16 | T79: 14 | U79: ARC | V79: Tomalati Ma'afu | W79: NULL | X79: Home | Y79: OGDC | Z79: 4.304124 | AB79: {=COUNT(_xlfn._xlws.FILTER($J$7:$J$10000,($L$7:$L$10000=AA79)*($M$7:$M$10000<>"NULL")*($J$7:$J$10000 >= ($G$1-5))))/5} -> 0
A80: =VLOOKUP($B80, PlayerIDs!$A$1:$B$516, 2, FALSE) -> 37 | B80: Brad Tucker | C80: 3.751293 | D80: =RANK($C80,$C$20:$C$106) -> 61 | E80: {=IFERROR(VLOOKUP($B80,_xlfn._xlws.FILTER($L$7:$P$10000,$J$7:$J$10000=G$1+1),5, FALSE), 0)} -> 2.3887153 | F80: =RANK(E80,$E$20:$E$100) -> 60 | G80: =SUMIF(V:Z,$B80,Z:Z) -> 15.12509 | H80: =RANK($G80,$G$20:$G$106) -> 54 | I80: {=COUNT(_xlfn._xlws.FILTER($J$7:$J$10000,($L$7:$L$10000=B80)*($M$7:$M$10000<>"NULL")*($J$7:$J$10000 >= ($G$1-4))))/5} -> 0.2 | J80: 3 | K80: CHI | L80: Mason Flesch | M80: 4.3 | N80: Home | O80: NEFJ | P80: =VLOOKUP($N80,$F$3:$G$4,2,FALSE)+VLOOKUP($L80,$B$20:$C$150,2,FALSE)+VLOOKUP($O80,$A$6:$B$16,2,FALSE) -> 7.45665 | Q80: =IFERROR(($M80-$P80)^2,"") -> 9.9644394 | R80: {=SUMPRODUCT((J80=$J$7:$J$1000)*(P80<$P$7:$P$1000))+1} -> 17 | T80: 14 | U80: CHI | V80: Brad Tucker | W80: NULL | X80: Home | Y80: LA | Z80: 3.3978631 | AB80: {=COUNT(_xlfn._xlws.FILTER($J$7:$J$10000,($L$7:$L$10000=AA80)*($M$7:$M$10000<>"NULL")*($J$7:$J$10000 >= ($G$1-5))))/5} -> 0
A81: =VLOOKUP($B81, PlayerIDs!$A$1:$B$516, 2, FALSE) -> 580 | B81: Ronan Murphy | C81: 3.3557345 | D81: =RANK($C81,$C$20:$C$106) -> 62 | E81: {=IFERROR(VLOOKUP($B81,_xlfn._xlws.FILTER($L$7:$P$10000,$J$7:$J$10000=G$1+1),5, FALSE), 0)} -> 4.5147437 | F81: =RANK(E81,$E$20:$E$100) -> 49 | G81: =SUMIF(V:Z,$B81,Z:Z) -> 10.508989 | H81: =RANK($G81,$G$20:$G$106) -> 63 | I81: {=COUNT(_xlfn._xlws.FILTER($J$7:$J$10000,($L$7:$L$10000=B81)*($M$7:$M$10000<>"NULL")*($J$7:$J$10000 >= ($G$1-4))))/5} -> 0 | J81: 3 | K81: NOLA | L81: Jonah Mau'u | M81: 4.2 | N81: Away | O81: UTAH | P81: =VLOOKUP($N81,$F$3:$G$4,2,FALSE)+VLOOKUP($L81,$B$20:$C$150,2,FALSE)+VLOOKUP($O81,$A$6:$B$16,2,FALSE) -> 12.504503 | Q81: =IFERROR(($M81-$P81)^2,"") -> 68.964773 | R81: {=SUMPRODUCT((J81=$J$7:$J$1000)*(P81<$P$7:$P$1000))+1} -> 2 | T81: 14 | U81: CHI | V81: Conall Boomer | W81: NULL | X81: Home | Y81: LA | Z81: 6.1875852 | AB81: {=COUNT(_xlfn._xlws.FILTER($J$7:$J$10000,($L$7:$L$10000=AA81)*($M$7:$M$10000<>"NULL")*($J$7:$J$10000 >= ($G$1-5))))/5} -> 0
A82: =VLOOKUP($B82, PlayerIDs!$A$1:$B$516, 2, FALSE) -> 565 | B82: Ronnie McElligott | C82: 2.8667847 | D82: =RANK($C82,$C$20:$C$106) -> 63 | E82: {=IFERROR(VLOOKUP($B82,_xlfn._xlws.FILTER($L$7:$P$10000,$J$7:$J$10000=G$1+1),5, FALSE), 0)} -> 2.9063399 | F82: =RANK(E82,$E$20:$E$100) -> 59 | G82: =SUMIF(V:Z,$B82,Z:Z) -> 13.539636 | H82: =RANK($G82,$G$20:$G$106) -> 60 | I82: {=COUNT(_xlfn._xlws.FILTER($J$7:$J$10000,($L$7:$L$10000=B82)*($M$7:$M$10000<>"NULL")*($J$7:$J$10000 >= ($G$1-4))))/5} -> 0.2 | J82: 3 | K82: ARC | L82: Sam Golla | M82: 4.1 | N82: Home | O82: MIA | P82: =VLOOKUP($N82,$F$3:$G$4,2,FALSE)+VLOOKUP($L82,$B$20:$C$150,2,FALSE)+VLOOKUP($O82,$A$6:$B$16,2,FALSE) -> 4.9268655 | Q82: =IFERROR(($M82-$P82)^2,"") -> 0.68370661 | R82: {=SUMPRODUCT((J82=$J$7:$J$1000)*(P82<$P$7:$P$1000))+1} -> 26 | T82: 14 | U82: CHI | V82: Lucas Rumball | W82: NULL | X82: Home | Y82: LA | Z82: 8.1039769 | AB82: {=COUNT(_xlfn._xlws.FILTER($J$7:$J$10000,($L$7:$L$10000=AA82)*($M$7:$M$10000<>"NULL")*($J$7:$J$10000 >= ($G$1-5))))/5} -> 0
A83: =VLOOKUP($B83, PlayerIDs!$A$1:$B$516, 2, FALSE) -> 416 | B83: Tevita Tameilau | C83: 2.7733742 | D83: =RANK($C83,$C$20:$C$106) -> 64 | E83: {=IFERROR(VLOOKUP($B83,_xlfn._xlws.FILTER($L$7:$P$10000,$J$7:$J$10000=G$1+1),5, FALSE), 0)} -> 2.3703809 | F83: =RANK(E83,$E$20:$E$100) -> 61 | G83: =SUMIF(V:Z,$B83,Z:Z) -> 8.4493262 | H83: =RANK($G83,$G$20:$G$106) -> 65 | I83: {=COUNT(_xlfn._xlws.FILTER($J$7:$J$10000,($L$7:$L$10000=B83)*($M$7:$M$10000<>"NULL")*($J$7:$J$10000 >= ($G$1-4))))/5} -> 0.2 | J83: 3 | K83: HOU | L83: Emmanuel Albert | M83: 4 | N83: Home | O83: SEA | P83: =VLOOKUP($N83,$F$3:$G$4,2,FALSE)+VLOOKUP($L83,$B$20:$C$150,2,FALSE)+VLOOKUP($O83,$A$6:$B$16,2,FALSE) -> 7.1283505 | Q83: =IFERROR(($M83-$P83)^2,"") -> 9.786577 | R83: {=SUMPRODUCT((J83=$J$7:$J$1000)*(P83<$P$7:$P$1000))+1} -> 18 | T83: 14 | U83: CHI | V83: Luke White | W83: NULL | X83: Home | Y83: LA | Z83: 3.9224805 | AB83: {=COUNT(_xlfn._xlws.FILTER($J$7:$J$10000,($L$7:$L$10000=AA83)*($M$7:$M$10000<>"NULL")*($J$7:$J$10000 >= ($G$1-5))))/5} -> 0
A84: =VLOOKUP($B84, PlayerIDs!$A$1:$B$516, 2, FALSE) -> 436 | B84: Tupou Ma'afu Afungia | C84: 2.561687 | D84: =RANK($C84,$C$20:$C$106) -> 65 | E84: {=IFERROR(VLOOKUP($B84,_xlfn._xlws.FILTER($L$7:$P$10000,$J$7:$J$10000=G$1+1),5, FALSE), 0)} -> 1.8543084 | F84: =RANK(E84,$E$20:$E$100) -> 63 | G84: =SUMIF(V:Z,$B84,Z:Z) -> 6.6410444 | H84: =RANK($G84,$G$20:$G$106) -> 68 | I84: {=COUNT(_xlfn._xlws.FILTER($J$7:$J$10000,($L$7:$L$10000=B84)*($M$7:$M$10000<>"NULL")*($J$7:$J$10000 >= ($G$1-4))))/5} -> 0.2 | J84: 3 | K84: OGDC | L84: Lautaro Bavaro | M84: 4 | N84: Home | O84: SDL | P84: =VLOOKUP($N84,$F$3:$G$4,2,FALSE)+VLOOKUP($L84,$B$20:$C$150,2,FALSE)+VLOOKUP($O84,$A$6:$B$16,2,FALSE) -> 6.5195791 | Q84: =IFERROR(($M84-$P84)^2,"") -> 6.3482786 | R84: {=SUMPRODUCT((J84=$J$7:$J$1000)*(P84<$P$7:$P$1000))+1} -> 21 | T84: 14 | U84: CHI | V84: Maclean Jones | W84: NULL | X84: Home | Y84: LA | Z84: 9.4236056 | AB84: {=COUNT(_xlfn._xlws.FILTER($J$7:$J$10000,($L$7:$L$10000=AA84)*($M$7:$M$10000<>"NULL")*($J$7:$J$10000 >= ($G$1-5))))/5} -> 0
A85: =VLOOKUP($B85, PlayerIDs!$A$1:$B$516, 2, FALSE) -> 241 | B85: Keni Nasoqeqe | C85: 2.4342022 | D85: =RANK($C85,$C$20:$C$106) -> 66 | E85: {=IFERROR(VLOOKUP($B85,_xlfn._xlws.FILTER($L$7:$P$10000,$J$7:$J$10000=G$1+1),5, FALSE), 0)} -> 3.5932114 | F85: =RANK(E85,$E$20:$E$100) -> 56 | G85: =SUMIF(V:Z,$B85,Z:Z) -> 7.7443926 | H85: =RANK($G85,$G$20:$G$106) -> 67 | I85: {=COUNT(_xlfn._xlws.FILTER($J$7:$J$10000,($L$7:$L$10000=B85)*($M$7:$M$10000<>"NULL")*($J$7:$J$10000 >= ($G$1-4))))/5} -> 0 | J85: 3 | K85: UTAH | L85: Kalisi Moli | M85: 3.8 | N85: Home | O85: NOLA | P85: =VLOOKUP($N85,$F$3:$G$4,2,FALSE)+VLOOKUP($L85,$B$20:$C$150,2,FALSE)+VLOOKUP($O85,$A$6:$B$16,2,FALSE) -> 5.8349573 | Q85: =IFERROR(($M85-$P85)^2,"") -> 4.1410513 | R85: {=SUMPRODUCT((J85=$J$7:$J$1000)*(P85<$P$7:$P$1000))+1} -> 24 | T85: 14 | U85: CHI | V85: Mason Flesch | W85: NULL | X85: Home | Y85: LA | Z85: 9.065808 | AB85: {=COUNT(_xlfn._xlws.FILTER($J$7:$J$10000,($L$7:$L$10000=AA85)*($M$7:$M$10000<>"NULL")*($J$7:$J$10000 >= ($G$1-5))))/5} -> 0
A86: =VLOOKUP($B86, PlayerIDs!$A$1:$B$516, 2, FALSE) -> 560 | B86: Tomas Bekerman | C86: 2.0340487 | D86: =RANK($C86,$C$20:$C$106) -> 67 | E86: {=IFERROR(VLOOKUP($B86,_xlfn._xlws.FILTER($L$7:$P$10000,$J$7:$J$10000=G$1+1),5, FALSE), 0)} -> 3.1998461 | F86: =RANK(E86,$E$20:$E$100) -> 57 | G86: =SUMIF(V:Z,$B86,Z:Z) -> 8.1449838 | H86: =RANK($G86,$G$20:$G$106) -> 66 | I86: {=COUNT(_xlfn._xlws.FILTER($J$7:$J$10000,($L$7:$L$10000=B86)*($M$7:$M$10000<>"NULL")*($J$7:$J$10000 >= ($G$1-4))))/5} -> 0.4 | J86: 3 | K86: NOLA | L86: Tupou Ma'afu Afungia | M86: 3.7 | N86: Away | O86: UTAH | P86: =VLOOKUP($N86,$F$3:$G$4,2,FALSE)+VLOOKUP($L86,$B$20:$C$150,2,FALSE)+VLOOKUP($O86,$A$6:$B$16,2,FALSE) -> 1.8049085 | Q86: =IFERROR(($M86-$P86)^2,"") -> 3.5913716 | R86: {=SUMPRODUCT((J86=$J$7:$J$1000)*(P86<$P$7:$P$1000))+1} -> 30 | T86: 14 | U86: CHI | V86: Matt Oworu | W86: NULL | X86: Home | Y86: LA | Z86: 6.4977014 | AB86: {=COUNT(_xlfn._xlws.FILTER($J$7:$J$10000,($L$7:$L$10000=AA86)*($M$7:$M$10000<>"NULL")*($J$7:$J$10000 >= ($G$1-5))))/5} -> 0
A87: =VLOOKUP($B87, PlayerIDs!$A$1:$B$516, 2, FALSE) -> 672 | B87: Reid Davis | C87: 2.0196927 | D87: =RANK($C87,$C$20:$C$106) -> 68 | E87: {=IFERROR(VLOOKUP($B87,_xlfn._xlws.FILTER($L$7:$P$10000,$J$7:$J$10000=G$1+1),5, FALSE), 0)} -> 2.0592478 | F87: =RANK(E87,$E$20:$E$100) -> 62 | G87: =SUMIF(V:Z,$B87,Z:Z) -> 10.151268 | H87: =RANK($G87,$G$20:$G$106) -> 64 | I87: {=COUNT(_xlfn._xlws.FILTER($J$7:$J$10000,($L$7:$L$10000=B87)*($M$7:$M$10000<>"NULL")*($J$7:$J$10000 >= ($G$1-4))))/5} -> 0.2 | J87: 3 | K87: MIA | L87: Marques Fuala'au | M87: 3.3 | N87: Away | O87: ARC | P87: =VLOOKUP($N87,$F$3:$G$4,2,FALSE)+VLOOKUP($L87,$B$20:$C$150,2,FALSE)+VLOOKUP($O87,$A$6:$B$16,2,FALSE) -> 5.1052725 | Q87: =IFERROR(($M87-$P87)^2,"") -> 3.2590089 | R87: {=SUMPRODUCT((J87=$J$7:$J$1000)*(P87<$P$7:$P$1000))+1} -> 25 | T87: 14 | U87: HOU | V87: Emmanuel Albert | W87: NULL | X87: Home | Y87: UTAH | Z87: 5.7320069 | AB87: {=COUNT(_xlfn._xlws.FILTER($J$7:$J$10000,($L$7:$L$10000=AA87)*($M$7:$M$10000<>"NULL")*($J$7:$J$10000 >= ($G$1-5))))/5} -> 0
A88: =VLOOKUP($B88, PlayerIDs!$A$1:$B$516, 2, FALSE) -> 698 | B88: Aminae Amiatu-Tanoi | C88: 0.63672237 | D88: =RANK($C88,$C$20:$C$106) -> 69 | E88: {=IFERROR(VLOOKUP($B88,_xlfn._xlws.FILTER($L$7:$P$10000,$J$7:$J$10000=G$1+1),5, FALSE), 0)} -> 0.23372908 | F88: =RANK(E88,$E$20:$E$100) -> 65 | G88: =SUMIF(V:Z,$B88,Z:Z) -> 2.0393706 | H88: =RANK($G88,$G$20:$G$106) -> 70 | I88: {=COUNT(_xlfn._xlws.FILTER($J$7:$J$10000,($L$7:$L$10000=B88)*($M$7:$M$10000<>"NULL")*($J$7:$J$10000 >= ($G$1-4))))/5} -> 0.2 | J88: 3 | K88: NEFJ | L88: Wian Conradie | M88: 2.9 | N88: Away | O88: CHI | P88: =VLOOKUP($N88,$F$3:$G$4,2,FALSE)+VLOOKUP($L88,$B$20:$C$150,2,FALSE)+VLOOKUP($O88,$A$6:$B$16,2,FALSE) -> 9.8519176 | Q88: =IFERROR(($M88-$P88)^2,"") -> 48.329158 | R88: {=SUMPRODUCT((J88=$J$7:$J$1000)*(P88<$P$7:$P$1000))+1} -> 6 | T88: 14 | U88: HOU | V88: Johan Momsen | W88: NULL | X88: Home | Y88: UTAH | Z88: 4.6987197 | AB88: {=COUNT(_xlfn._xlws.FILTER($J$7:$J$10000,($L$7:$L$10000=AA88)*($M$7:$M$10000<>"NULL")*($J$7:$J$10000 >= ($G$1-5))))/5} -> 0
A89: =VLOOKUP($B89, PlayerIDs!$A$1:$B$516, 2, FALSE) -> 255 | B89: Lance Williams | C89: 0.37760844 | D89: =RANK($C89,$C$20:$C$106) -> 70 | E89: {=IFERROR(VLOOKUP($B89,_xlfn._xlws.FILTER($L$7:$P$10000,$J$7:$J$10000=G$1+1),5, FALSE), 0)} -> 0.41716356 | F89: =RANK(E89,$E$20:$E$100) -> 64 | G89: =SUMIF(V:Z,$B89,Z:Z) -> 3.5829311 | H89: =RANK($G89,$G$20:$G$106) -> 69 | I89: {=COUNT(_xlfn._xlws.FILTER($J$7:$J$10000,($L$7:$L$10000=B89)*($M$7:$M$10000<>"NULL")*($J$7:$J$10000 >= ($G$1-4))))/5} -> 0.4 | J89: 3 | K89: ARC | L89: Dylan Fortune | M89: 2.2 | N89: Home | O89: MIA | P89: =VLOOKUP($N89,$F$3:$G$4,2,FALSE)+VLOOKUP($L89,$B$20:$C$150,2,FALSE)+VLOOKUP($O89,$A$6:$B$16,2,FALSE) -> 3.0950268 | Q89: =IFERROR(($M89-$P89)^2,"") -> 0.80107294 | R89: {=SUMPRODUCT((J89=$J$7:$J$1000)*(P89<$P$7:$P$1000))+1} -> 29 | T89: 14 | U89: HOU | V89: Keni Nasoqeqe | W89: NULL | X89: Home | Y89: UTAH | Z89: 1.0774137 | AB89: {=COUNT(_xlfn._xlws.FILTER($J$7:$J$10000,($L$7:$L$10000=AA89)*($M$7:$M$10000<>"NULL")*($J$7:$J$10000 >= ($G$1-5))))/5} -> 0
J90: 3 | K90: NOLA | L90: Kellen Galletier | M90: 1.1 | N90: Away | O90: UTAH | P90: =VLOOKUP($N90,$F$3:$G$4,2,FALSE)+VLOOKUP($L90,$B$20:$C$150,2,FALSE)+VLOOKUP($O90,$A$6:$B$16,2,FALSE) -> 3.6827233 | Q90: =IFERROR(($M90-$P90)^2,"") -> 6.6704599 | R90: {=SUMPRODUCT((J90=$J$7:$J$1000)*(P90<$P$7:$P$1000))+1} -> 28 | T90: 14 | U90: HOU | V90: Marno Redelinghuys | W90: NULL | X90: Home | Y90: UTAH | Z90: 3.457281 | AB90: {=COUNT(_xlfn._xlws.FILTER($J$7:$J$10000,($L$7:$L$10000=AA90)*($M$7:$M$10000<>"NULL")*($J$7:$J$10000 >= ($G$1-5))))/5} -> 0
J91: 4 | K91: MIA | L91: Manuel Ardao | M91: 19.6 | N91: Home | O91: CHI | P91: =VLOOKUP($N91,$F$3:$G$4,2,FALSE)+VLOOKUP($L91,$B$20:$C$150,2,FALSE)+VLOOKUP($O91,$A$6:$B$16,2,FALSE) -> 12.52869 | Q91: =IFERROR(($M91-$P91)^2,"") -> 50.00342 | R91: {=SUMPRODUCT((J91=$J$7:$J$1000)*(P91<$P$7:$P$1000))+1} -> 1 | T91: 14 | U91: HOU | V91: Ronan Murphy | W91: NULL | X91: Home | Y91: UTAH | Z91: 1.998946 | AB91: {=COUNT(_xlfn._xlws.FILTER($J$7:$J$10000,($L$7:$L$10000=AA91)*($M$7:$M$10000<>"NULL")*($J$7:$J$10000 >= ($G$1-5))))/5} -> 0
J92: 4 | K92: HOU | L92: Emmanuel Albert | M92: 16.5 | N92: Away | O92: UTAH | P92: =VLOOKUP($N92,$F$3:$G$4,2,FALSE)+VLOOKUP($L92,$B$20:$C$150,2,FALSE)+VLOOKUP($O92,$A$6:$B$16,2,FALSE) -> 6.332017 | Q92: =IFERROR(($M92-$P92)^2,"") -> 103.38788 | R92: {=SUMPRODUCT((J92=$J$7:$J$1000)*(P92<$P$7:$P$1000))+1} -> 22 | T92: 14 | U92: HOU | V92: Sam Tuifua | W92: NULL | X92: Home | Y92: UTAH | Z92: 10.414391
J93: 4 | K93: LA | L93: Ben Houston | M93: 14.5 | N93: Away | O93: SDL | P93: =VLOOKUP($N93,$F$3:$G$4,2,FALSE)+VLOOKUP($L93,$B$20:$C$150,2,FALSE)+VLOOKUP($O93,$A$6:$B$16,2,FALSE) -> 11.992391 | Q93: =IFERROR(($M93-$P93)^2,"") -> 6.2881024 | R93: {=SUMPRODUCT((J93=$J$7:$J$1000)*(P93<$P$7:$P$1000))+1} -> 2 | T93: 14 | U93: LA | V93: Ben Houston | W93: NULL | X93: Away | Y93: CHI | Z93: 11.853533
J94: 4 | K94: CHI | L94: Mason Flesch | M94: 13.1 | N94: Away | O94: MIA | P94: =VLOOKUP($N94,$F$3:$G$4,2,FALSE)+VLOOKUP($L94,$B$20:$C$150,2,FALSE)+VLOOKUP($O94,$A$6:$B$16,2,FALSE) -> 9.3118694 | Q94: =IFERROR(($M94-$P94)^2,"") -> 14.349933 | R94: {=SUMPRODUCT((J94=$J$7:$J$1000)*(P94<$P$7:$P$1000))+1} -> 10 | T94: 14 | U94: LA | V94: Ed Timpson | W94: NULL | X94: Away | Y94: CHI | Z94: 11.85691
J95: 4 | K95: CHI | L95: Maclean Jones | M95: 12.9 | N95: Away | O95: MIA | P95: =VLOOKUP($N95,$F$3:$G$4,2,FALSE)+VLOOKUP($L95,$B$20:$C$150,2,FALSE)+VLOOKUP($O95,$A$6:$B$16,2,FALSE) -> 9.669667 | Q95: =IFERROR(($M95-$P95)^2,"") -> 10.435051 | R95: {=SUMPRODUCT((J95=$J$7:$J$1000)*(P95<$P$7:$P$1000))+1} -> 7 | T95: 14 | U95: LA | V95: Jason Damm | W95: NULL | X95: Away | Y95: CHI | Z95: 7.0202736
J96: 4 | K96: SDL | L96: Brad Wilkin | M96: 11.8 | N96: Home | O96: LA | P96: =VLOOKUP($N96,$F$3:$G$4,2,FALSE)+VLOOKUP($L96,$B$20:$C$150,2,FALSE)+VLOOKUP($O96,$A$6:$B$16,2,FALSE) -> 9.4938685 | Q96: =IFERROR(($M96-$P96)^2,"") -> 5.3182423 | R96: {=SUMPRODUCT((J96=$J$7:$J$1000)*(P96<$P$7:$P$1000))+1} -> 8 | T96: 14 | U96: LA | V96: Matt Heaton | W96: NULL | X96: Away | Y96: CHI | Z96: 6.8545757
J97: 4 | K97: SDL | L97: Christian Poidevin | M97: 11.8 | N97: Home | O97: LA | P97: =VLOOKUP($N97,$F$3:$G$4,2,FALSE)+VLOOKUP($L97,$B$20:$C$150,2,FALSE)+VLOOKUP($O97,$A$6:$B$16,2,FALSE) -> 11.017448 | Q97: =IFERROR(($M97-$P97)^2,"") -> 0.6123882 | R97: {=SUMPRODUCT((J97=$J$7:$J$1000)*(P97<$P$7:$P$1000))+1} -> 3 | T97: 14 | U97: LA | V97: Semi Kunitani | W97: NULL | X97: Away | Y97: CHI | Z97: 11.637947
J98: 4 | K98: NEFJ | L98: Joe Johnston | M98: 10.9 | N98: Away | O98: SEA | P98: =VLOOKUP($N98,$F$3:$G$4,2,FALSE)+VLOOKUP($L98,$B$20:$C$150,2,FALSE)+VLOOKUP($O98,$A$6:$B$16,2,FALSE) -> 10.126304 | Q98: =IFERROR(($M98-$P98)^2,"") -> 0.59860572 | R98: {=SUMPRODUCT((J98=$J$7:$J$1000)*(P98<$P$7:$P$1000))+1} -> 6 | T98: 14 | U98: LA | V98: Tim Anstee | W98: NULL | X98: Away | Y98: CHI | Z98: 5.1907401
J99: 4 | K99: NEFJ | L99: Jero Gomez Vara | M99: 10.8 | N99: Away | O99: SEA | P99: =VLOOKUP($N99,$F$3:$G$4,2,FALSE)+VLOOKUP($L99,$B$20:$C$150,2,FALSE)+VLOOKUP($O99,$A$6:$B$16,2,FALSE) -> 7.9156393 | Q99: =IFERROR(($M99-$P99)^2,"") -> 8.3195365 | R99: {=SUMPRODUCT((J99=$J$7:$J$1000)*(P99<$P$7:$P$1000))+1} -> 18 | T99: 14 | U99: MIA | V99: Benjamin Bonasso | W99: NULL | X99: Home | Y99: NEFJ | Z99: 6.8109758
J100: 4 | K100: UTAH | L100: Frank Lochore | M100: 10.5 | N100: Home | O100: HOU | P100: =VLOOKUP($N100,$F$3:$G$4,2,FALSE)+VLOOKUP($L100,$B$20:$C$150,2,FALSE)+VLOOKUP($O100,$A$6:$B$16,2,FALSE) -> 8.0168538 | Q100: =IFERROR(($M100-$P100)^2,"") -> 6.1660151 | R100: {=SUMPRODUCT((J100=$J$7:$J$1000)*(P100<$P$7:$P$1000))+1} -> 17 | T100: 14 | U100: MIA | V100: Manuel Ardao | W100: NULL | X100: Home | Y100: NEFJ | Z100: 10.145962
